Workbook
Name FAMILIA_CON_NIÑO_NANEAS: #REF!
Name FAMILIA_CON_NIÑO_NANEAS: #REF!
Name FAMILIA_CON_NIÑO_NANEAS: #REF!

Sheet NOMBRE
A1: DATOS DEL ESTABLECIMIENTO | C1: CÓDIGOS
A2: NOMBRE DE COMUNA | I2: =IF(OR(NOMBRE!C2="",NOMBRE!D2="",NOMBRE!E2="",NOMBRE!F2="",NOMBRE!G2=""),"Falta Cód. Com.","") -> Falta Cód. Com. | AG2: =IF(I2>"",1,0) -> 1
A3: NOMBRE ESTABLECIMIENTO/ESTRATEGIA | I3: =IF(OR(NOMBRE!C3="",NOMBRE!D3="",NOMBRE!E3="",NOMBRE!F3="",NOMBRE!G3="",NOMBRE!H3=""),"Falta Cód. Est.","") -> Falta Cód. Est. | AG3: =IF(I3>"",1,0) -> 1
A4: TIPO DE ESTABLECIMIENTO/ESTRATEGIA | I4: =IF(OR(NOMBRE!B4=""),"Falta Tipo. Est.","") -> Falta Tipo. Est. | AG4: =IF(I4>"",1,0) -> 1
A5: DEPENDENCIA | I5: =IF(OR(NOMBRE!B5=""),"Falta Dependencia. Est.","") -> Falta Dependencia. Est. | AG5: =IF(I5>"",1,0) -> 1
A6: MES: | I6: =IF(OR(NOMBRE!C6="",NOMBRE!D6=""),"Falta Cód. Mes.","") -> Falta Cód. Mes. | AG6: =IF(I6>"",1,0) -> 1
A7: AÑO: | B7: 2020 | AG7: =SUM(AG2:AG6) -> 5
A9: Versión 1.1: ENERO 2020 | G9: Para habilitar el contenido de las celdas "Tipo de Establecimiento", "Dependencia" y "Mes", presione el boton "Verificar Habilitacion de Macros". Para poder tener un 100% de funcionalidad debe hablitar la opcion Macros en esta planilla.
A11: Director Servicio de Salud o Director Establecimiento | AA11: ENERO | AB11: Establecimiento de Mayor Complejidad (EMAYC) | AC11: SERVICIO DE SALUD
A12: Jefe de Estadísticas | AA12: FEBRERO | AB12: Establecimiento de Mediana Complejidad (EMEDC) | AC12: MUNICIPAL
AA13: MARZO | AB13: Establecimiento de Menor Complejidad (EMENC) | AC13: OTRA INSTITUCIÓN (Delegado)
AA14: ABRIL | AB14: Centros de Diagnóstico Terapéutico (CDT)
A15: MINSAL - DEIS | AA15: MAYO | AB15: Centro de Referencia de Salud (CRS)
AA16: JUNIO | AB16: Consultorio General Urbano (CGU)
B17: SERIE A | G17: ESTADO MACROS: | AA17: JULIO | AB17: Consultorio General Urbano (CGU) - CESFAM
I18: HABILITADO | AA18: AGOSTO | AB18: Consultorio General Urbano(CGU) con SAPU/SUR/SAR
AA19: SEPTIEMBRE | AB19: Consultorio General Urbano (CGU) - CESFAM con SAPU/SAR
AA20: OCTUBRE | AB20: Consultorio General Rural (CGR)
AA21: NOVIEMBRE | AB21: Consultorio General Rural (CGR) - CESFAM
AA22: DICIEMBRE | AB22: Consultorio General Rural (CGR) con SAPU/SAR/SUR
AB23: Consultorio General Rural (CGR) - CESFAM con SAPU/SAR/SUR
AB24: Posta de Salud Rural (PSR)
AB25: Centro Comunitario de Salud Familiar (CECOF)
AB26: Consultorio de Salud Mental (COSAM)
AB27: Programa de Reparación y Atención Integral de Salud (PRAIS)
AB28: Centro de Atención Funcionarios (CAF)
AB29: Clínica Dental Móvil (CDM)
AB30: Dirección Servicio de Salud (DSS)
AB31: Servicio de Atención Primaria de Urgencia (SAPU)
AB32: SAPU Alta Resolución (SAR)
AB33: Laboratorio Clínico o Dental
AB34: Servicio de Atención Primaria de Urgencia Dental (SAPUDENT)
... AB37: Centro Oncologico

Sheet A01
B1: SERVICIO DE SALUD
B2: =CONCATENATE("COMUNA: ",NOMBRE!B2," - ","( ",NOMBRE!C2,NOMBRE!D2,NOMBRE!E2,NOMBRE!F2,NOMBRE!G2," )") -> COMUNA: - ( )
B3: =CONCATENATE("ESTABLECIMIENTO/ESTRATEGIA: ",NOMBRE!B3," - ","( ",NOMBRE!C3,NOMBRE!D3,NOMBRE!E3,NOMBRE!F3,NOMBRE!G3,NOMBRE!H3," )") -> ESTABLECIMIENTO/ESTRATEGIA: - ( )
B4: =CONCATENATE("MES: ",NOMBRE!B6," - ","( ",NOMBRE!C6,NOMBRE!D6," )") -> MES: - ( )
B5: =CONCATENATE("AÑO: ",NOMBRE!B7) -> AÑO: 2020
B6: REM-A01. CONTROLES DE SALUD
B9: SECCIÓN A: CONTROLES DE SALUD SEXUAL Y REPRODUCTIVA
B10: TIPO DE CONTROL | C10: PROFESIONAL | D10: TOTAL | E10: POR EDAD | U10: SEXO | W10: Beneficiarios | X10: Control con pareja familiar u otro | Y10: Control de diada con presencia del padre | Z10: TIPOS DE LACTANCIA
A11: CODIGO DICCIONARIO | E11: 5 - 9 | F11: 10 - 14 | G11: 15 a 19 | H11: 20 - 24 | I11: 25 - 29 | J11: 30 - 34 | K11: 35 - 39 | L11: 40 - 44 | M11: 45 - 49 | N11: 50 - 54 | O11: 55 - 59 | P11: 60 - 64 | Q11: 65 - 69 | R11: 70 - 74 | S11: 75 - 79 | T11: 80 y mas | U11: HOMBRES | V11: MUJERES | Z11: Lactancia Materna Exclusiva | AA11: Lactancia Materna / Formula Láctea | AB11: Formula Láctea
A12: 01010101 | B12: PRE- CONCEPCIONAL | C12: MÉDICO | D12: COL01 | E12: COL02 | F12: COL03 | G12: COL04 | H12: COL05 | I12: COL06 | J12: COL07 | K12: COL08 | L12: COL09 | M12: COL10 | N12: COL11 | O12: COL12 | P12: COL13 | Q12: COL14 | R12: COL15 | S12: COL16 | T12: COL17 | U12: COL18 | V12: COL19 | W12: COL20 | X12: COL21 | Y12: COL22 | Z12: COL23 | AA12: COL24 | AB12: COL25 | CM12: 0 | CN12: 0 | CR12: 0
A13: 01010103 | C13: MATRONA /ÓN | D13: COL01 | E13: COL02 | F13: COL03 | G13: COL04 | H13: COL05 | I13: COL06 | J13: COL07 | K13: COL08 | L13: COL09 | M13: COL10 | N13: COL11 | O13: COL12 | P13: COL13 | Q13: COL14 | R13: COL15 | S13: COL16 | T13: COL17 | U13: COL18 | V13: COL19 | W13: COL20 | X13: COL21 | Y13: COL22 | Z13: COL23 | AA13: COL24 | AB13: COL25 | CM13: 0 | CN13: 0 | CR13: 0
A14: 01010201 | B14: PRENATAL | C14: MÉDICO | D14: COL01 | E14: COL02 | F14: COL03 | G14: COL04 | H14: COL05 | I14: COL06 | J14: COL07 | K14: COL08 | L14: COL09 | M14: COL10 | N14: COL11 | O14: COL12 | P14: COL13 | Q14: COL14 | R14: COL15 | S14: COL16 | T14: COL17 | U14: COL18 | V14: COL19 | W14: COL20 | X14: COL21 | Y14: COL22 | Z14: COL23 | AA14: COL24 | AB14: COL25 | CM14: 0 | CN14: 0 | CO14: 0 | CR14: 0 | CS14: 0
A15: 01010203 | C15: MATRONA /ÓN | D15: COL01 | E15: COL02 | F15: COL03 | G15: COL04 | H15: COL05 | I15: COL06 | J15: COL07 | K15: COL08 | L15: COL09 | M15: COL10 | N15: COL11 | O15: COL12 | P15: COL13 | Q15: COL14 | R15: COL15 | S15: COL16 | T15: COL17 | U15: COL18 | V15: COL19 | W15: COL20 | X15: COL21 | Y15: COL22 | Z15: COL23 | AA15: COL24 | AB15: COL25 | CM15: 0 | CN15: 0 | CO15: 0 | CR15: 0 | CS15: 0
A16: 01080001 | B16: POST PARTO Y POST ABORTO | C16: MÉDICO | D16: COL01 | E16: COL02 | F16: COL03 | G16: COL04 | H16: COL05 | I16: COL06 | J16: COL07 | K16: COL08 | L16: COL09 | M16: COL10 | N16: COL11 | O16: COL12 | P16: COL13 | Q16: COL14 | R16: COL15 | S16: COL16 | T16: COL17 | U16: COL18 | V16: COL19 | W16: COL20 | X16: COL21 | Y16: COL22 | Z16: COL23 | AA16: COL24 | AB16: COL25 | CM16: 0 | CN16: 0 | CR16: 0
A17: 01080002 | C17: MATRONA /ÓN | D17: COL01 | E17: COL02 | F17: COL03 | G17: COL04 | H17: COL05 | I17: COL06 | J17: COL07 | K17: COL08 | L17: COL09 | M17: COL10 | N17: COL11 | O17: COL12 | P17: COL13 | Q17: COL14 | R17: COL15 | S17: COL16 | T17: COL17 | U17: COL18 | V17: COL19 | W17: COL20 | X17: COL21 | Y17: COL22 | Z17: COL23 | AA17: COL24 | AB17: COL25 | CM17: 0 | CN17: 0 | CR17: 0
A18: 01110106 | B18: PUÉRPERA CON RECIÉN NACIDO HASTA 10 DÍAS DE VIDA | C18: MÉDICO | D18: COL01 | E18: COL02 | F18: COL03 | G18: COL04 | H18: COL05 | I18: COL06 | J18: COL07 | K18: COL08 | L18: COL09 | M18: COL10 | N18: COL11 | O18: COL12 | P18: COL13 | Q18: COL14 | R18: COL15 | S18: COL16 | T18: COL17 | U18: COL18 | V18: COL19 | W18: COL20 | X18: COL21 | Y18: COL22 | Z18: COL23 | AA18: COL24 | AB18: COL25 | CG18: =IF(AND(D18<>0,'A05'!D50=""),"* No olvide registrar ingresos a control de salud de los respectivos RN, en REM A05-secci„n E. ","") | CM18: 0 | CN18: 0 | CP18: 0 | CQ18: 0 | CR18: 0 | CT18: 0 | CU18: 0
A19: 01110107 | C19: MATRONA /ÓN | D19: COL01 | E19: COL02 | F19: COL03 | G19: COL04 | H19: COL05 | I19: COL06 | J19: COL07 | K19: COL08 | L19: COL09 | M19: COL10 | N19: COL11 | O19: COL12 | P19: COL13 | Q19: COL14 | R19: COL15 | S19: COL16 | T19: COL17 | U19: COL18 | V19: COL19 | W19: COL20 | X19: COL21 | Y19: COL22 | Z19: COL23 | AA19: COL24 | AB19: COL25 | CG19: =IF(AND(D19<>0,'A05'!D50=""),"* No olvide registrar ingresos a control de salud de los respectivos RN, en REM A05-secci„n E. ","") | CM19: 0 | CN19: 0 | CP19: 0 | CQ19: 0 | CR19: 0 | CT19: 0 | CU19: 0
A20: 01080030 | B20: PUÉRPERA CON RECIÉN NACIDO ENTRE 11 y 28 DÍAS | C20: MÉDICO | D20: COL01 | E20: COL02 | F20: COL03 | G20: COL04 | H20: COL05 | I20: COL06 | J20: COL07 | K20: COL08 | L20: COL09 | M20: COL10 | N20: COL11 | O20: COL12 | P20: COL13 | Q20: COL14 | R20: COL15 | S20: COL16 | T20: COL17 | U20: COL18 | V20: COL19 | W20: COL20 | X20: COL21 | Y20: COL22 | Z20: COL23 | AA20: COL24 | AB20: COL25 | CG20: =IF(AND(D20<>0,'A05'!D50=""),"* No olvide registrar ingresos a control de salud de los respectivos RN, en REM A05-secci„n E. ","") | CM20: 0 | CN20: 0 | CP20: 0 | CQ20: 0 | CR20: 0 | CT20: 0 | CU20: 0
A21: 01080040 | C21: MATRONA /ÓN | D21: COL01 | E21: COL02 | F21: COL03 | G21: COL04 | H21: COL05 | I21: COL06 | J21: COL07 | K21: COL08 | L21: COL09 | M21: COL10 | N21: COL11 | O21: COL12 | P21: COL13 | Q21: COL14 | R21: COL15 | S21: COL16 | T21: COL17 | U21: COL18 | V21: COL19 | W21: COL20 | X21: COL21 | Y21: COL22 | Z21: COL23 | AA21: COL24 | AB21: COL25 | CG21: =IF(AND(D21<>0,'A05'!D50=""),"* No olvide registrar ingresos a control de salud de los respectivos RN, en REM A05-secci„n E. ","") | CM21: 0 | CN21: 0 | CP21: 0 | CQ21: 0 | CR21: 0 | CT21: 0 | CU21: 0
A22: 01010601 | B22: GINECOLÓGICO | C22: MÉDICO | D22: COL01 | E22: COL02 | F22: COL03 | G22: COL04 | H22: COL05 | I22: COL06 | J22: COL07 | K22: COL08 | L22: COL09 | M22: COL10 | N22: COL11 | O22: COL12 | P22: COL13 | Q22: COL14 | R22: COL15 | S22: COL16 | T22: COL17 | U22: COL18 | V22: COL19 | W22: COL20 | X22: COL21 | Y22: COL22 | Z22: COL23 | AA22: COL24 | AB22: COL25 | CM22: 0 | CN22: 0 | CR22: 0
A23: 01010603 | C23: MATRONA /ÓN | D23: COL01 | E23: COL02 | F23: COL03 | G23: COL04 | H23: COL05 | I23: COL06 | J23: COL07 | K23: COL08 | L23: COL09 | M23: COL10 | N23: COL11 | O23: COL12 | P23: COL13 | Q23: COL14 | R23: COL15 | S23: COL16 | T23: COL17 | U23: COL18 | V23: COL19 | W23: COL20 | X23: COL21 | Y23: COL22 | Z23: COL23 | AA23: COL24 | AB23: COL25 | CM23: 0 | CN23: 0 | CR23: 0
A24: 01010901 | B24: CLIMATERIO | C24: MÉDICO | D24: COL01 | E24: COL02 | F24: COL03 | G24: COL04 | H24: COL05 | I24: COL06 | J24: COL07 | K24: COL08 | L24: COL09 | M24: COL10 | N24: COL11 | O24: COL12 | P24: COL13 | Q24: COL14 | R24: COL15 | S24: COL16 | T24: COL17 | U24: COL18 | V24: COL19 | W24: COL20 | X24: COL21 | Y24: COL22 | Z24: COL23 | AA24: COL24 | AB24: COL25 | CM24: 0 | CN24: 0 | CR24: 0
A25: 01010903 | C25: MATRONA /ÓN | D25: COL01 | E25: COL02 | F25: COL03 | G25: COL04 | H25: COL05 | I25: COL06 | J25: COL07 | K25: COL08 | L25: COL09 | M25: COL10 | N25: COL11 | O25: COL12 | P25: COL13 | Q25: COL14 | R25: COL15 | S25: COL16 | T25: COL17 | U25: COL18 | V25: COL19 | W25: COL20 | X25: COL21 | Y25: COL22 | Z25: COL23 | AA25: COL24 | AB25: COL25 | CM25: 0 | CN25: 0 | CR25: 0
A26: 01010401 | B26: REGULACIÓN DE FECUNDIDAD | C26: MÉDICO | D26: COL01 | E26: COL02 | F26: COL03 | G26: COL04 | H26: COL05 | I26: COL06 | J26: COL07 | K26: COL08 | L26: COL09 | M26: COL10 | N26: COL11 | O26: COL12 | P26: COL13 | Q26: COL14 | R26: COL15 | S26: COL16 | T26: COL17 | U26: COL18 | V26: COL19 | W26: COL20 | X26: COL21 | Y26: COL22 | Z26: COL23 | AA26: COL24 | AB26: COL25 | CM26: 0 | CN26: 0 | CR26: 0
A27: 01010403 | C27: MATRONA /ÓN | D27: COL01 | E27: COL02 | F27: COL03 | G27: COL04 | H27: COL05 | I27: COL06 | J27: COL07 | K27: COL08 | L27: COL09 | M27: COL10 | N27: COL11 | O27: COL12 | P27: COL13 | Q27: COL14 | R27: COL15 | S27: COL16 | T27: COL17 | U27: COL18 | V27: COL19 | W27: COL20 | X27: COL21 | Y27: COL22 | Z27: COL23 | AA27: COL24 | AB27: COL25 | CM27: 0 | CN27: 0 | CR27: 0
B28: SECCIÓN B: CONTROLES DE SALUD SEGÚN CICLO VITAL
B29: TIPO DE CONTROL | C29: PROFESIONAL | D29: TOTAL | G29: POR EDAD | AJ29: Beneficiarios | AK29: CONTROL CON PRESENCIA DEL PADRE | AM29: Niños, Niñas, Adolescentes y Jóvenes Población SENAME
D30: Ambos Sexos | E30: Hombres | F30: Mujeres | G30: Menor de 1 mes | H30: 1 mes | I30: 2 meses | J30: 3 meses | K30: 4 meses | L30: 5 meses | M30: 6 meses | N30: 7 - 11 meses | O30: 12 a 17 meses | P30: 18 - 23 meses | Q30: 24 - 47 meses | R30: 48 - 59 meses | S30: 60 - 71 meses | T30: 6 - 9 | U30: 10 - 14 | V30: 15 - 19 | W30: 20 - 24 | X30: 25 - 29 | Y30: 30 - 34 | Z30: 35 - 39 | AA30: 40 - 44 | AB30: 45 - 49 | AC30: 50 - 54 | AD30: 55 - 59 | AE30: 60 - 64 | AF30: 65 - 69 | AG30: 70 - 74 | AH30: 75 - 79 | AI30: 80 y mas | AK30: menor 1 año | AL30: 1 año a 3 años 11 meses 29 días
A31: 02010101 | B31: DE SALUD | C31: MÉDICO | D31: COL01 | E31: COL02 | F31: COL03 | G31: COL04 | H31: COL05 | I31: COL06 | J31: COL07 | K31: COL08 | L31: COL09 | M31: COL10 | N31: COL11 | O31: COL12 | P31: COL13 | Q31: COL14 | R31: COL15 | S31: COL16 | T31: COL17 | U31: COL18 | V31: COL19 | W31: COL20 | X31: COL21 | Y31: COL22 | Z31: COL23 | AA31: COL24 | AB31: COL25 | AC31: COL26 | AD31: COL27 | AE31: COL28 | AF31: COL29 | AG31: COL30 | AH31: COL31 | AI31: COL32 | AJ31: COL33 | AK31: COL34 | AL31: COL35 | AM31: COL36 | CD31: =IF(AK31>SUM(G31:N31),"* Los controles con presencia del padre NO DEBE ser mayor que el total Controles Menor 1 año. ",IF(AL31>SUM(O31:Q31),"* Los controles con presencia del padre NO DEBE ser mayor que el total Controles 1 año a 3 años 11 meses 29 dÍas. ","")) -> * Los controles con presencia del padre NO DEBE ser mayor que el total Controles Menor 1 año. | CE31: =IF(AND(G31<>0,'A05'!D50=""),"* NO OLVIDE REGISTRAR INGRESOS A CONTROL DE SALUD DE LOS RESPECTIVOS RN, EN REM A05-SECCIÓN E. ","") | CI31: 0 | CJ31: =IF(AK31>SUM(G31:N31),1,IF(AL31>SUM(O31:Q31),1,0)) -> 1 | CK31: 0
A32: 02010201 | C32: ENFERMERA /O | D32: COL01 | E32: COL02 | F32: COL03 | G32: COL04 | H32: COL05 | I32: COL06 | J32: COL07 | K32: COL08 | L32: COL09 | M32: COL10 | N32: COL11 | O32: COL12 | P32: COL13 | Q32: COL14 | R32: COL15 | S32: COL16 | T32: COL17 | U32: COL18 | V32: COL19 | W32: COL20 | X32: COL21 | Y32: COL22 | Z32: COL23 | AA32: COL24 | AB32: COL25 | AC32: COL26 | AD32: COL27 | AE32: COL28 | AF32: COL29 | AG32: COL30 | AH32: COL31 | AI32: COL32 | AJ32: COL33 | AK32: COL34 | AL32: COL35 | AM32: COL36 | CD32: =IF(AK32>SUM(G32:N32),"* Los controles con presencia del padre NO DEBE ser mayor que el total Controles Menor 1 año. ",IF(AL32>SUM(O32:Q32),"* Los controles con presencia del padre NO DEBE ser mayor que el total Controles 1 año a 3 años 11 meses 29 dÍas. ","")) -> * Los controles con presencia del padre NO DEBE ser mayor que el total Controles Menor 1 año. | CE32: =IF(AND(G32<>0,'A05'!D50=""),"* NO OLVIDE REGISTRAR INGRESOS A CONTROL DE SALUD DE LOS RESPECTIVOS RN, EN REM A05-SECCIÓN E. ","") | CI32: 0 | CJ32: =IF(AK32>SUM(G32:N32),1,IF(AL32>SUM(O32:Q32),1,0)) -> 1 | CK32: 0
A33: 02010103 | C33: MATRONA /ÓN | D33: COL01 | E33: COL02 | F33: COL03 | G33: COL04 | H33: COL05 | I33: COL06 | J33: COL07 | K33: COL08 | L33: COL09 | M33: COL10 | N33: COL11 | O33: COL12 | P33: COL13 | Q33: COL14 | R33: COL15 | S33: COL16 | T33: COL17 | U33: COL18 | V33: COL19 | W33: COL20 | X33: COL21 | Y33: COL22 | Z33: COL23 | AA33: COL24 | AB33: COL25 | AC33: COL26 | AD33: COL27 | AE33: COL28 | AF33: COL29 | AG33: COL30 | AH33: COL31 | AI33: COL32 | AJ33: COL33 | AK33: COL34 | AL33: COL35 | AM33: COL36 | CD33: =IF((AK33>G33),"* Los controles con presencia del padre NO DEBE ser mayor que el total Controles Menor 1 año. ","") -> * Los controles con presencia del padre NO DEBE ser mayor que el total Controles Menor 1 año. | CE33: =IF(AND(G33<>0,'A05'!D50=""),"* NO OLVIDE REGISTRAR INGRESOS A CONTROL DE SALUD DE LOS RESPECTIVOS RN, EN REM A05-SECCIÓN E. ","") | CI33: 0 | CJ33: =IF(AK33>SUM(G33:N33),1,IF(AL33>SUM(O33:Q33),1,0)) -> 1 | CK33: 0
A34: 02010105 | C34: TÉCNICO PARAMÉDICO | D34: COL01 | E34: COL02 | F34: COL03 | G34: COL04 | H34: COL05 | I34: COL06 | J34: COL07 | K34: COL08 | L34: COL09 | M34: COL10 | N34: COL11 | O34: COL12 | P34: COL13 | Q34: COL14 | R34: COL15 | S34: COL16 | T34: COL17 | U34: COL18 | V34: COL19 | W34: COL20 | X34: COL21 | Y34: COL22 | Z34: COL23 | AA34: COL24 | AB34: COL25 | AC34: COL26 | AD34: COL27 | AE34: COL28 | AF34: COL29 | AG34: COL30 | AH34: COL31 | AI34: COL32 | AJ34: COL33 | AK34: COL34 | AL34: COL35 | AM34: COL36 | CD34: =IF(AL34>SUM(O34:T34),"* Los controles con presencia del padre NO DEBE ser mayor que el total Controles 1año a 3 años 11 meses 29 dÍas. ","") -> * Los controles con presencia del padre NO DEBE ser mayor que el total Controles 1año a 3 años 11 meses 29 dÍas. | CI34: 0 | CJ34: =IF(AK34>SUM(G34:N34),1,IF(AL34>SUM(O34:Q34),1,0)) -> 1 | CK34: 0
B35: SECCIÓN C: CONTROLES SEGÚN PROBLEMA DE SALUD
B36: TIPO DE CONTROL | C36: PROFESIONAL | D36: TOTAL | G36: POR EDAD | AO36: Beneficiarios
G37: 0 - 4 | I37: 5 - 9 | K37: 10 - 14 | M37: 15 a 19 | O37: 20 - 24 | Q37: 25 - 29 | S37: 30 - 34 | U37: 35 - 39 | W37: 40 - 44 | Y37: 45 - 49 | AA37: 50 - 54 | AC37: 55 - 59 | AE37: 60 - 64 | AG37: 65 - 69 | AI37: 70 - 74 | AK37: 75 - 79 | AM37: 80 y mas
D38: Ambos Sexos | E38: Hombres | F38: Mujeres | G38: Hombres | H38: Mujeres | I38: Hombres | J38: Mujeres | K38: Hombres | L38: Mujeres | M38: Hombres | N38: Mujeres | O38: Hombres | P38: Mujeres | Q38: Hombres | R38: Mujeres | S38: Hombres | T38: Mujeres | U38: Hombres | V38: Mujeres | W38: Hombres | X38: Mujeres | Y38: Hombres | Z38: Mujeres | AA38: Hombres | AB38: Mujeres | AC38: Hombres | AD38: Mujeres | AE38: Hombres | AF38: Mujeres | AG38: Hombres | AH38: Mujeres | AI38: Hombres | AJ38: Mujeres | AK38: Hombres | AL38: Mujeres | AM38: Hombres | AN38: Mujeres
A39: 03010501 | B39: DE SALUD CARDIOVASCULAR | C39: MÉDICO | D39: COL01 | E39: COL02 | F39: COL03 | G39: COL04 | H39: COL05 | I39: COL06 | J39: COL07 | K39: COL08 | L39: COL09 | M39: COL10 | N39: COL11 | O39: COL12 | P39: COL13 | Q39: COL14 | R39: COL15 | S39: COL16 | T39: COL17 | U39: COL18 | V39: COL19 | W39: COL20 | X39: COL21 | Y39: COL22 | Z39: COL23 | AA39: COL24 | AB39: COL25 | AC39: COL26 | AD39: COL27 | AE39: COL28 | AF39: COL29 | AG39: COL30 | AH39: COL31 | AI39: COL32 | AJ39: COL33 | AK39: COL34 | AL39: COL35 | AM39: COL36 | AN39: COL37 | AO39: COL38 | CJ39: 0
A40: 03010502 | C40: ENFERMERA /O | D40: COL01 | E40: COL02 | F40: COL03 | G40: COL04 | H40: COL05 | I40: COL06 | J40: COL07 | K40: COL08 | L40: COL09 | M40: COL10 | N40: COL11 | O40: COL12 | P40: COL13 | Q40: COL14 | R40: COL15 | S40: COL16 | T40: COL17 | U40: COL18 | V40: COL19 | W40: COL20 | X40: COL21 | Y40: COL22 | Z40: COL23 | AA40: COL24 | AB40: COL25 | AC40: COL26 | AD40: COL27 | AE40: COL28 | AF40: COL29 | AG40: COL30 | AH40: COL31 | AI40: COL32 | AJ40: COL33 | AK40: COL34 | AL40: COL35 | AM40: COL36 | AN40: COL37 | AO40: COL38 | CJ40: 0
A41: 03010504 | C41: NUTRICIONISTA | D41: COL01 | E41: COL02 | F41: COL03 | G41: COL04 | H41: COL05 | I41: COL06 | J41: COL07 | K41: COL08 | L41: COL09 | M41: COL10 | N41: COL11 | O41: COL12 | P41: COL13 | Q41: COL14 | R41: COL15 | S41: COL16 | T41: COL17 | U41: COL18 | V41: COL19 | W41: COL20 | X41: COL21 | Y41: COL22 | Z41: COL23 | AA41: COL24 | AB41: COL25 | AC41: COL26 | AD41: COL27 | AE41: COL28 | AF41: COL29 | AG41: COL30 | AH41: COL31 | AI41: COL32 | AJ41: COL33 | AK41: COL34 | AL41: COL35 | AM41: COL36 | AN41: COL37 | AO41: COL38 | CJ41: 0
A42: 03010505 | C42: TÉCNICO PARAMÉDICO | D42: COL01 | E42: COL02 | F42: COL03 | G42: COL04 | H42: COL05 | I42: COL06 | J42: COL07 | K42: COL08 | L42: COL09 | M42: COL10 | N42: COL11 | O42: COL12 | P42: COL13 | Q42: COL14 | R42: COL15 | S42: COL16 | T42: COL17 | U42: COL18 | V42: COL19 | W42: COL20 | X42: COL21 | Y42: COL22 | Z42: COL23 | AA42: COL24 | AB42: COL25 | AC42: COL26 | AD42: COL27 | AE42: COL28 | AF42: COL29 | AG42: COL30 | AH42: COL31 | AI42: COL32 | AJ42: COL33 | AK42: COL34 | AL42: COL35 | AM42: COL36 | AN42: COL37 | AO42: COL38 | CJ42: 0
A43: 03030190 | B43: DE TUBERCULOSIS | C43: MÉDICO | D43: COL01 | E43: COL02 | F43: COL03 | G43: COL04 | H43: COL05 | I43: COL06 | J43: COL07 | K43: COL08 | L43: COL09 | M43: COL10 | N43: COL11 | O43: COL12 | P43: COL13 | Q43: COL14 | R43: COL15 | S43: COL16 | T43: COL17 | U43: COL18 | V43: COL19 | W43: COL20 | X43: COL21 | Y43: COL22 | Z43: COL23 | AA43: COL24 | AB43: COL25 | AC43: COL26 | AD43: COL27 | AE43: COL28 | AF43: COL29 | AG43: COL30 | AH43: COL31 | AI43: COL32 | AJ43: COL33 | AK43: COL34 | AL43: COL35 | AM43: COL36 | AN43: COL37 | AO43: COL38 | CJ43: 0
A44: 03030200 | C44: ENFERMERA /O | D44: COL01 | E44: COL02 | F44: COL03 | G44: COL04 | H44: COL05 | I44: COL06 | J44: COL07 | K44: COL08 | L44: COL09 | M44: COL10 | N44: COL11 | O44: COL12 | P44: COL13 | Q44: COL14 | R44: COL15 | S44: COL16 | T44: COL17 | U44: COL18 | V44: COL19 | W44: COL20 | X44: COL21 | Y44: COL22 | Z44: COL23 | AA44: COL24 | AB44: COL25 | AC44: COL26 | AD44: COL27 | AE44: COL28 | AF44: COL29 | AG44: COL30 | AH44: COL31 | AI44: COL32 | AJ44: COL33 | AK44: COL34 | AL44: COL35 | AM44: COL36 | AN44: COL37 | AO44: COL38 | CJ44: 0
A45: 01030100A | B45: SEGUIMIENTO AUTOVALENTE CON RIESGO | C45: MÉDICO | D45: COL01 | E45: COL02 | F45: COL03 | G45: COL04 | H45: COL05 | I45: COL06 | J45: COL07 | K45: COL08 | L45: COL09 | M45: COL10 | N45: COL11 | O45: COL12 | P45: COL13 | Q45: COL14 | R45: COL15 | S45: COL16 | T45: COL17 | U45: COL18 | V45: COL19 | W45: COL20 | X45: COL21 | Y45: COL22 | Z45: COL23 | AA45: COL24 | AB45: COL25 | AC45: COL26 | AD45: COL27 | AE45: COL28 | AF45: COL29 | AG45: COL30 | AH45: COL31 | AI45: COL32 | AJ45: COL33 | AK45: COL34 | AL45: COL35 | AM45: COL36 | AN45: COL37 | AO45: COL38 | CJ45: 0
A46: 01030200B | C46: ENFERMERA /O | D46: COL01 | E46: COL02 | F46: COL03 | G46: COL04 | H46: COL05 | I46: COL06 | J46: COL07 | K46: COL08 | L46: COL09 | M46: COL10 | N46: COL11 | O46: COL12 | P46: COL13 | Q46: COL14 | R46: COL15 | S46: COL16 | T46: COL17 | U46: COL18 | V46: COL19 | W46: COL20 | X46: COL21 | Y46: COL22 | Z46: COL23 | AA46: COL24 | AB46: COL25 | AC46: COL26 | AD46: COL27 | AE46: COL28 | AF46: COL29 | AG46: COL30 | AH46: COL31 | AI46: COL32 | AJ46: COL33 | AK46: COL34 | AL46: COL35 | AM46: COL36 | AN46: COL37 | AO46: COL38 | CJ46: 0
A47: 01030300C | B47: SEGUIMIENTO RIESGO DEPENDENCIA | C47: MÉDICO | D47: COL01 | E47: COL02 | F47: COL03 | G47: COL04 | H47: COL05 | I47: COL06 | J47: COL07 | K47: COL08 | L47: COL09 | M47: COL10 | N47: COL11 | O47: COL12 | P47: COL13 | Q47: COL14 | R47: COL15 | S47: COL16 | T47: COL17 | U47: COL18 | V47: COL19 | W47: COL20 | X47: COL21 | Y47: COL22 | Z47: COL23 | AA47: COL24 | AB47: COL25 | AC47: COL26 | AD47: COL27 | AE47: COL28 | AF47: COL29 | AG47: COL30 | AH47: COL31 | AI47: COL32 | AJ47: COL33 | AK47: COL34 | AL47: COL35 | AM47: COL36 | AN47: COL37 | AO47: COL38 | CJ47: 0
A48: 01030400D | C48: ENFERMERA /O | D48: COL01 | E48: COL02 | F48: COL03 | G48: COL04 | H48: COL05 | I48: COL06 | J48: COL07 | K48: COL08 | L48: COL09 | M48: COL10 | N48: COL11 | O48: COL12 | P48: COL13 | Q48: COL14 | R48: COL15 | S48: COL16 | T48: COL17 | U48: COL18 | V48: COL19 | W48: COL20 | X48: COL21 | Y48: COL22 | Z48: COL23 | AA48: COL24 | AB48: COL25 | AC48: COL26 | AD48: COL27 | AE48: COL28 | AF48: COL29 | AG48: COL30 | AH48: COL31 | AI48: COL32 | AJ48: COL33 | AK48: COL34 | AL48: COL35 | AM48: COL36 | AN48: COL37 | AO48: COL38 | CJ48: 0
A49: 01200010 | B49: DE INFECCIÓN TRANSMISIÓN SEXUAL | C49: MÉDICO | D49: COL01 | E49: COL02 | F49: COL03 | G49: COL04 | H49: COL05 | I49: COL06 | J49: COL07 | K49: COL08 | L49: COL09 | M49: COL10 | N49: COL11 | O49: COL12 | P49: COL13 | Q49: COL14 | R49: COL15 | S49: COL16 | T49: COL17 | U49: COL18 | V49: COL19 | W49: COL20 | X49: COL21 | Y49: COL22 | Z49: COL23 | AA49: COL24 | AB49: COL25 | AC49: COL26 | AD49: COL27 | AE49: COL28 | AF49: COL29 | AG49: COL30 | AH49: COL31 | AI49: COL32 | AJ49: COL33 | AK49: COL34 | AL49: COL35 | AM49: COL36 | AN49: COL37 | AO49: COL38 | CJ49: 0
A50: 01200020 | C50: ENFERMERA /O | D50: COL01 | E50: COL02 | F50: COL03 | G50: COL04 | H50: COL05 | I50: COL06 | J50: COL07 | K50: COL08 | L50: COL09 | M50: COL10 | N50: COL11 | O50: COL12 | P50: COL13 | Q50: COL14 | R50: COL15 | S50: COL16 | T50: COL17 | U50: COL18 | V50: COL19 | W50: COL20 | X50: COL21 | Y50: COL22 | Z50: COL23 | AA50: COL24 | AB50: COL25 | AC50: COL26 | AD50: COL27 | AE50: COL28 | AF50: COL29 | AG50: COL30 | AH50: COL31 | AI50: COL32 | AJ50: COL33 | AK50: COL34 | AL50: COL35 | AM50: COL36 | AN50: COL37 | AO50: COL38 | CJ50: 0
A51: 01200030 | C51: MATRONA /ÓN | D51: COL01 | E51: COL02 | F51: COL03 | G51: COL04 | H51: COL05 | I51: COL06 | J51: COL07 | K51: COL08 | L51: COL09 | M51: COL10 | N51: COL11 | O51: COL12 | P51: COL13 | Q51: COL14 | R51: COL15 | S51: COL16 | T51: COL17 | U51: COL18 | V51: COL19 | W51: COL20 | X51: COL21 | Y51: COL22 | Z51: COL23 | AA51: COL24 | AB51: COL25 | AC51: COL26 | AD51: COL27 | AE51: COL28 | AF51: COL29 | AG51: COL30 | AH51: COL31 | AI51: COL32 | AJ51: COL33 | AK51: COL34 | AL51: COL35 | AM51: COL36 | AN51: COL37 | AO51: COL38 | CJ51: 0
A52: 03030140 | B52: OTROS PROBLEMAS DE SALUD | C52: MÉDICO | D52: COL01 | E52: COL02 | F52: COL03 | G52: COL04 | H52: COL05 | I52: COL06 | J52: COL07 | K52: COL08 | L52: COL09 | M52: COL10 | N52: COL11 | O52: COL12 | P52: COL13 | Q52: COL14 | R52: COL15 | S52: COL16 | T52: COL17 | U52: COL18 | V52: COL19 | W52: COL20 | X52: COL21 | Y52: COL22 | Z52: COL23 | AA52: COL24 | AB52: COL25 | AC52: COL26 | AD52: COL27 | AE52: COL28 | AF52: COL29 | AG52: COL30 | AH52: COL31 | AI52: COL32 | AJ52: COL33 | AK52: COL34 | AL52: COL35 | AM52: COL36 | AN52: COL37 | AO52: COL38 | CJ52: 0
A53: 03030150 | C53: ENFERMERA /O | D53: COL01 | E53: COL02 | F53: COL03 | G53: COL04 | H53: COL05 | I53: COL06 | J53: COL07 | K53: COL08 | L53: COL09 | M53: COL10 | N53: COL11 | O53: COL12 | P53: COL13 | Q53: COL14 | R53: COL15 | S53: COL16 | T53: COL17 | U53: COL18 | V53: COL19 | W53: COL20 | X53: COL21 | Y53: COL22 | Z53: COL23 | AA53: COL24 | AB53: COL25 | AC53: COL26 | AD53: COL27 | AE53: COL28 | AF53: COL29 | AG53: COL30 | AH53: COL31 | AI53: COL32 | AJ53: COL33 | AK53: COL34 | AL53: COL35 | AM53: COL36 | AN53: COL37 | AO53: COL38 | CJ53: 0
A54: 03030170 | C54: MATRONA /ÓN | D54: COL01 | E54: COL02 | F54: COL03 | G54: COL04 | H54: COL05 | I54: COL06 | J54: COL07 | K54: COL08 | L54: COL09 | M54: COL10 | N54: COL11 | O54: COL12 | P54: COL13 | Q54: COL14 | R54: COL15 | S54: COL16 | T54: COL17 | U54: COL18 | V54: COL19 | W54: COL20 | X54: COL21 | Y54: COL22 | Z54: COL23 | AA54: COL24 | AB54: COL25 | AC54: COL26 | AD54: COL27 | AE54: COL28 | AF54: COL29 | AG54: COL30 | AH54: COL31 | AI54: COL32 | AJ54: COL33 | AK54: COL34 | AL54: COL35 | AM54: COL36 | AN54: COL37 | AO54: COL38 | CJ54: 0
A55: 03030160 | C55: NUTRICIONISTA | D55: COL01 | E55: COL02 | F55: COL03 | G55: COL04 | H55: COL05 | I55: COL06 | J55: COL07 | K55: COL08 | L55: COL09 | M55: COL10 | N55: COL11 | O55: COL12 | P55: COL13 | Q55: COL14 | R55: COL15 | S55: COL16 | T55: COL17 | U55: COL18 | V55: COL19 | W55: COL20 | X55: COL21 | Y55: COL22 | Z55: COL23 | AA55: COL24 | AB55: COL25 | AC55: COL26 | AD55: COL27 | AE55: COL28 | AF55: COL29 | AG55: COL30 | AH55: COL31 | AI55: COL32 | AJ55: COL33 | AK55: COL34 | AL55: COL35 | AM55: COL36 | AN55: COL37 | AO55: COL38 | CJ55: 0
A56: 03030180 | C56: TÉCNICO PARAMÉDICO | D56: COL01 | E56: COL02 | F56: COL03 | G56: COL04 | H56: COL05 | I56: COL06 | J56: COL07 | K56: COL08 | L56: COL09 | M56: COL10 | N56: COL11 | O56: COL12 | P56: COL13 | Q56: COL14 | R56: COL15 | S56: COL16 | T56: COL17 | U56: COL18 | V56: COL19 | W56: COL20 | X56: COL21 | Y56: COL22 | Z56: COL23 | AA56: COL24 | AB56: COL25 | AC56: COL26 | AD56: COL27 | AE56: COL28 | AF56: COL29 | AG56: COL30 | AH56: COL31 | AI56: COL32 | AJ56: COL33 | AK56: COL34 | AL56: COL35 | AM56: COL36 | AN56: COL37 | AO56: COL38 | CJ56: 0
A57: 01200031 | B57: NIÑOS CON NECESIDADES ESPECIALES | C57: MÉDICO | D57: COL01 | E57: COL02 | F57: COL03 | G57: COL04 | H57: COL05 | I57: COL06 | J57: COL07 | K57: COL08 | L57: COL09 | M57: COL10 | N57: COL11 | O57: COL12 | P57: COL13 | Q57: COL14 | R57: COL15 | S57: COL16 | T57: COL17 | U57: COL18 | V57: COL19 | W57: COL20 | X57: COL21 | Y57: COL22 | Z57: COL23 | AA57: COL24 | AB57: COL25 | AC57: COL26 | AD57: COL27 | AE57: COL28 | AF57: COL29 | AG57: COL30 | AH57: COL31 | AI57: COL32 | AJ57: COL33 | AK57: COL34 | AL57: COL35 | AM57: COL36 | AN57: COL37 | AO57: COL38 | CJ57: 0
A58: 01200032 | C58: ENFERMERA /O | D58: COL01 | E58: COL02 | F58: COL03 | G58: COL04 | H58: COL05 | I58: COL06 | J58: COL07 | K58: COL08 | L58: COL09 | M58: COL10 | N58: COL11 | O58: COL12 | P58: COL13 | Q58: COL14 | R58: COL15 | S58: COL16 | T58: COL17 | U58: COL18 | V58: COL19 | W58: COL20 | X58: COL21 | Y58: COL22 | Z58: COL23 | AA58: COL24 | AB58: COL25 | AC58: COL26 | AD58: COL27 | AE58: COL28 | AF58: COL29 | AG58: COL30 | AH58: COL31 | AI58: COL32 | AJ58: COL33 | AK58: COL34 | AL58: COL35 | AM58: COL36 | AN58: COL37 | AO58: COL38 | CJ58: 0
A59: 01200033 | C59: MATRONA /ÓN | D59: COL01 | E59: COL02 | F59: COL03 | G59: COL04 | H59: COL05 | I59: COL06 | J59: COL07 | K59: COL08 | L59: COL09 | M59: COL10 | N59: COL11 | O59: COL12 | P59: COL13 | Q59: COL14 | R59: COL15 | S59: COL16 | T59: COL17 | U59: COL18 | V59: COL19 | W59: COL20 | X59: COL21 | Y59: COL22 | Z59: COL23 | AA59: COL24 | AB59: COL25 | AC59: COL26 | AD59: COL27 | AE59: COL28 | AF59: COL29 | AG59: COL30 | AH59: COL31 | AI59: COL32 | AJ59: COL33 | AK59: COL34 | AL59: COL35 | AM59: COL36 | AN59: COL37 | AO59: COL38 | CJ59: 0
A60: 01200034 | C60: NUTRICIONISTA | D60: COL01 | E60: COL02 | F60: COL03 | G60: COL04 | H60: COL05 | I60: COL06 | J60: COL07 | K60: COL08 | L60: COL09 | M60: COL10 | N60: COL11 | O60: COL12 | P60: COL13 | Q60: COL14 | R60: COL15 | S60: COL16 | T60: COL17 | U60: COL18 | V60: COL19 | W60: COL20 | X60: COL21 | Y60: COL22 | Z60: COL23 | AA60: COL24 | AB60: COL25 | AC60: COL26 | AD60: COL27 | AE60: COL28 | AF60: COL29 | AG60: COL30 | AH60: COL31 | AI60: COL32 | AJ60: COL33 | AK60: COL34 | AL60: COL35 | AM60: COL36 | AN60: COL37 | AO60: COL38 | CJ60: 0
A61: 01200035 | C61: TÉCNICO PARAMÉDICO | D61: COL01 | E61: COL02 | F61: COL03 | G61: COL04 | H61: COL05 | I61: COL06 | J61: COL07 | K61: COL08 | L61: COL09 | M61: COL10 | N61: COL11 | O61: COL12 | P61: COL13 | Q61: COL14 | R61: COL15 | S61: COL16 | T61: COL17 | U61: COL18 | V61: COL19 | W61: COL20 | X61: COL21 | Y61: COL22 | Z61: COL23 | AA61: COL24 | AB61: COL25 | AC61: COL26 | AD61: COL27 | AE61: COL28 | AF61: COL29 | AG61: COL30 | AH61: COL31 | AI61: COL32 | AJ61: COL33 | AK61: COL34 | AL61: COL35 | AM61: COL36 | AN61: COL37 | AO61: COL38 | CJ61: 0
B62: SECCIÓN D: CONTROL DE SALUD INTEGRAL DE ADOLESCENTES (incluidos en sección B)
B63: LUGAR DEL CONTROL, SEGÚN EDAD | D63: 10 A 14 AÑOS | G63: 15 A 19 AÑOS
D64: Ambos Sexos | E64: Hombres | F64: Mujeres | G64: Ambos Sexos | H64: Hombres | I64: Mujeres
A65: 01030500 | B65: EN ESPACIO AMIGABLE | D65: COL01 | E65: COL02 | F65: COL03 | G65: COL04 | H65: COL05 | I65: COL06
A66: 01030600 | B66: EN OTROS ESPACIOS DEL ESTABLECIMIENTO DE SALUD | D66: COL01 | E66: COL02 | F66: COL03 | G66: COL04 | H66: COL05 | I66: COL06
A67: 01030700 | B67: EN ESTABLECIMIENTOS EDUCACIONALES | D67: COL01 | E67: COL02 | F67: COL03 | G67: COL04 | H67: COL05 | I67: COL06
A68: 01030800 | B68: EN OTROS LUGARES FUERA DEL ESTABLECIMIENTO DE SALUD | D68: COL01 | E68: COL02 | F68: COL03 | G68: COL04 | H68: COL05 | I68: COL06
B69: TOTAL | D69: =SUM(D65:D68) -> 0 | E69: =SUM(E65:E68) -> 0 | F69: =SUM(F65:F68) -> 0 | G69: =SUM(G65:G68) -> 0 | H69: =SUM(H65:H68) -> 0 | I69: =SUM(I65:I68) -> 0
B70: SECCIÓN E: CONTROLES DE SALUD EN ESTABLECIMIENTO EDUCACIONAL (Los controles individuales deben estar incluídos en la Sección B)
B71: TIPO DE CONTROLES | C71: CURSO | D71: TOTAL* | E71: TOTAL NIÑOS Y NIÑAS | F71: SEXO
F72: Hombres | G72: Mujeres
A73: 01031000 | B73: CONTROLES INDIVIDUALES | C73: KÍNDER | D73: COL01 | E73: COL02 | F73: COL03 | G73: COL04
A74: 01031100 | C74: PRIMERO BÁSICO | D74: COL01 | E74: COL02 | F74: COL03 | G74: COL04
A75: 01031200 | C75: SEGUNDO BÁSICO | D75: COL01 | E75: COL02 | F75: COL03 | G75: COL04
A76: 01031300 | C76: TERCERO BÁSICO | D76: COL01 | E76: COL02 | F76: COL03 | G76: COL04
A77: 01031400 | C77: CUARTO BÁSICO | D77: COL01 | E77: COL02 | F77: COL03 | G77: COL04
A78: 01031500 | B78: CONTROLES GRUPALES * | C78: KÍNDER | D78: COL01 | E78: COL02 | F78: COL03 | G78: COL04
A79: 01031600 | C79: PRIMERO BÁSICO | D79: COL01 | E79: COL02 | F79: COL03 | G79: COL04
A80: 01031700 | C80: SEGUNDO BÁSICO | D80: COL01 | E80: COL02 | F80: COL03 | G80: COL04
A81: 01031800 | C81: TERCERO BÁSICO | D81: COL01 | E81: COL02 | F81: COL03 | G81: COL04
A82: 01031900 | C82: CUARTO BÁSICO | D82: COL01 | E82: COL02 | F82: COL03 | G82: COL04
B83: En Total* se registra el número de controles grupales
B84: SECCIÓN F: CONTROLES INTEGRALES DE PERSONAS CON CONDICIONES CRÓNICAS
B85: TIPO DE CONTROL | C85: TOTAL | F85: POR EDAD | AH85: Beneficiarios | AI85: Migrantes | AJ85: Pueblos Originarios
F86: 15 a 19 | H86: 20 - 24 | J86: 25 - 29 | L86: 30 - 34 | N86: 35 - 39 | P86: 40 - 44 | R86: 45 - 49 | T86: 50 - 54 | V86: 55 - 59 | X86: 60 - 64 | Z86: 65 - 69 | AB86: 70 - 74 | AD86: 75 - 79 | AF86: 80 y mas
C87: Ambos Sexos | D87: Hombres | E87: Mujeres | F87: Hombres | G87: Mujeres | H87: Hombres | I87: Mujeres | J87: Hombres | K87: Mujeres | L87: Hombres | M87: Mujeres | N87: Hombres | O87: Mujeres | P87: Hombres | Q87: Mujeres | R87: Hombres | S87: Mujeres | T87: Hombres | U87: Mujeres | V87: Hombres | W87: Mujeres | X87: Hombres | Y87: Mujeres | Z87: Hombres | AA87: Mujeres | AB87: Hombres | AC87: Mujeres | AD87: Hombres | AE87: Mujeres | AF87: Hombres | AG87: Mujeres
A88: 01501010 | B88: CONTROL INTEGRAL CON RIESGO LEVE (G1) | C88: COL01 | D88: COL02 | E88: COL03 | F88: COL04 | G88: COL05 | H88: COL06 | I88: COL07 | J88: COL08 | K88: COL09 | L88: COL10 | M88: COL11 | N88: COL12 | O88: COL13 | P88: COL14 | Q88: COL15 | R88: COL16 | S88: COL17 | T88: COL18 | U88: COL19 | V88: COL20 | W88: COL21 | X88: COL22 | Y88: COL23 | Z88: COL24 | AA88: COL25 | AB88: COL26 | AC88: COL27 | AD88: COL28 | AE88: COL29 | AF88: COL30 | AG88: COL31 | AH88: COL32 | AI88: COL33 | AJ88: COL34
A89: 01501020 | B89: CONTROL INTEGRAL CON RIESGO MODERADO (G2) | C89: COL01 | D89: COL02 | E89: COL03 | F89: COL04 | G89: COL05 | H89: COL06 | I89: COL07 | J89: COL08 | K89: COL09 | L89: COL10 | M89: COL11 | N89: COL12 | O89: COL13 | P89: COL14 | Q89: COL15 | R89: COL16 | S89: COL17 | T89: COL18 | U89: COL19 | V89: COL20 | W89: COL21 | X89: COL22 | Y89: COL23 | Z89: COL24 | AA89: COL25 | AB89: COL26 | AC89: COL27 | AD89: COL28 | AE89: COL29 | AF89: COL30 | AG89: COL31 | AH89: COL32 | AI89: COL33 | AJ89: COL34
A90: 01501030 | B90: CONTROL INTEGRAL CON RIESGO ALTO (G3) | C90: COL01 | D90: COL02 | E90: COL03 | F90: COL04 | G90: COL05 | H90: COL06 | I90: COL07 | J90: COL08 | K90: COL09 | L90: COL10 | M90: COL11 | N90: COL12 | O90: COL13 | P90: COL14 | Q90: COL15 | R90: COL16 | S90: COL17 | T90: COL18 | U90: COL19 | V90: COL20 | W90: COL21 | X90: COL22 | Y90: COL23 | Z90: COL24 | AA90: COL25 | AB90: COL26 | AC90: COL27 | AD90: COL28 | AE90: COL29 | AF90: COL30 | AG90: COL31 | AH90: COL32 | AI90: COL33 | AJ90: COL34
A91: 01501040 | B91: SEGUIMIENTO A DISTANCIA CON RIESGO ALTO (G3) | C91: COL01 | D91: COL02 | E91: COL03 | F91: COL04 | G91: COL05 | H91: COL06 | I91: COL07 | J91: COL08 | K91: COL09 | L91: COL10 | M91: COL11 | N91: COL12 | O91: COL13 | P91: COL14 | Q91: COL15 | R91: COL16 | S91: COL17 | T91: COL18 | U91: COL19 | V91: COL20 | W91: COL21 | X91: COL22 | Y91: COL23 | Z91: COL24 | AA91: COL25 | AB91: COL26 | AC91: COL27 | AD91: COL28 | AE91: COL29 | AF91: COL30 | AG91: COL31 | AH91: COL32 | AI91: COL33 | AJ91: COL34
A97: CODIGOS NUEVOS
A98: 01501010
A99: 01501020
A100: 01501030
A101: 01501040
B186: =SUM(D12:D27,W12:W27,U26:V27,Y18:AB21,X14:X15,D31:D34,E31:F34,AJ31:AJ34,D39:F61,D65:D69,G65:G69,D73:D77,E78:E82) -> 0 | C186: =SUM(CH1:CV82) -> 4

Sheet A02
B1: SERVICIO DE SALUD
B2: =CONCATENATE("COMUNA: ",NOMBRE!B2," - ","( ",NOMBRE!C2,NOMBRE!D2,NOMBRE!E2,NOMBRE!F2,NOMBRE!G2," )") -> COMUNA: - ( )
B3: =CONCATENATE("ESTABLECIMIENTO/ESTRATEGIA: ",NOMBRE!B3," - ","( ",NOMBRE!C3,NOMBRE!D3,NOMBRE!E3,NOMBRE!F3,NOMBRE!G3,NOMBRE!H3," )") -> ESTABLECIMIENTO/ESTRATEGIA: - ( )
B4: =CONCATENATE("MES: ",NOMBRE!B6," - ","( ",NOMBRE!C6,NOMBRE!D6," )") -> MES: - ( )
B5: =CONCATENATE("AÑO: ",NOMBRE!B7) -> AÑO: 2020
B6: REM-A02. EXAMEN DE MEDICINA PREVENTIVA EN MAYORES DE 15 AÑOS
B8: SECCIÓN A: EMP REALIZADO POR PROFESIONAL
A9: CODIGO DICCIONARIO | B9: PROFESIONAL | C9: TOTAL
C10: Ambos Sexos | D10: Hombres | E10: Mujeres
B11: TOTAL | C11: =SUM(C12:C17) -> 0 | D11: =SUM(D12:D17) -> 0 | E11: =SUM(E12:E17) -> 0
A12: 03030101 | B12: MÉDICO | C12: COL01 | D12: COL02 | E12: COL03
A13: 03030102 | B13: ENFERMERA /O | C13: COL01 | D13: COL02 | E13: COL03
A14: 03030103 | B14: MATRONA /ÓN | C14: COL01 | D14: COL02 | E14: COL03
A15: 03030104 | B15: NUTRICIONISTA | C15: COL01 | D15: COL02 | E15: COL03
A16: 03030350 | B16: OTRO PROFESIONAL | C16: COL01 | D16: COL02 | E16: COL03
A17: 03030110 | B17: TÉCNICO PARAMÉDICO | C17: COL01 | D17: COL02 | E17: COL03
B18: SECCIÓN B: EMP SEGÚN RESULTADO DEL ESTADO NUTRICIONAL
B19: ESTADO NUTRICIONAL | C19: TOTAL | F19: 15 a 19 | H19: 20 a 24 | J19: 25 a 29 | L19: 30 a 34 | N19: 35 a 39 | P19: 40 a 44 | R19: 45 a 49 | T19: 50 a 54 | V19: 55 a 59 | X19: 60 a 64 | Z19: 65 a 69 | AB19: 70 a 74 | AD19: 75 a 79 | AF19: 80 y más
C20: Ambos Sexos | D20: Hombres | E20: Mujeres | F20: Hombres | G20: Mujeres | H20: Hombres | I20: Mujeres | J20: Hombres | K20: Mujeres | L20: Hombres | M20: Mujeres | N20: Hombres | O20: Mujeres | P20: Hombres | Q20: Mujeres | R20: Hombres | S20: Mujeres | T20: Hombres | U20: Mujeres | V20: Hombres | W20: Mujeres | X20: Hombres | Y20: Mujeres | Z20: Hombres | AA20: Mujeres | AB20: Hombres | AC20: Mujeres | AD20: Hombres | AE20: Mujeres | AF20: Hombres | AG20: Mujeres
B21: TOTAL | C21: =SUM(C22:C25) -> 0 | D21: =SUM(D22:D25) -> 0 | E21: =SUM(E22:E25) -> 0 | F21: =SUM(F22:F25) -> 0 | G21: =SUM(G22:G25) -> 0 | H21: =SUM(H22:H25) -> 0 | I21: =SUM(I22:I25) -> 0 | J21: =SUM(J22:J25) -> 0 | ... AG21: =SUM(AG22:AG25) -> 0 | CJ21: 0
A22: 03030330 | B22: NORMAL | C22: COL01 | D22: COL02 | E22: COL03 | F22: COL04 | G22: COL05 | H22: COL06 | I22: COL07 | J22: COL08 | K22: COL09 | L22: COL10 | M22: COL11 | N22: COL12 | O22: COL13 | P22: COL14 | Q22: COL15 | R22: COL16 | S22: COL17 | T22: COL18 | U22: COL19 | V22: COL20 | W22: COL21 | X22: COL22 | Y22: COL23 | Z22: COL24 | AA22: COL25 | AB22: COL26 | AC22: COL27 | AD22: COL28 | AE22: COL29 | AF22: COL30 | AG22: COL31
A23: 03030340 | B23: BAJO PESO | C23: COL01 | D23: COL02 | E23: COL03 | F23: COL04 | G23: COL05 | H23: COL06 | I23: COL07 | J23: COL08 | K23: COL09 | L23: COL10 | M23: COL11 | N23: COL12 | O23: COL13 | P23: COL14 | Q23: COL15 | R23: COL16 | S23: COL17 | T23: COL18 | U23: COL19 | V23: COL20 | W23: COL21 | X23: COL22 | Y23: COL23 | Z23: COL24 | AA23: COL25 | AB23: COL26 | AC23: COL27 | AD23: COL28 | AE23: COL29 | AF23: COL30 | AG23: COL31
A24: 03030120 | B24: SOBREPESO | C24: COL01 | D24: COL02 | E24: COL03 | F24: COL04 | G24: COL05 | H24: COL06 | I24: COL07 | J24: COL08 | K24: COL09 | L24: COL10 | M24: COL11 | N24: COL12 | O24: COL13 | P24: COL14 | Q24: COL15 | R24: COL16 | S24: COL17 | T24: COL18 | U24: COL19 | V24: COL20 | W24: COL21 | X24: COL22 | Y24: COL23 | Z24: COL24 | AA24: COL25 | AB24: COL26 | AC24: COL27 | AD24: COL28 | AE24: COL29 | AF24: COL30 | AG24: COL31
A25: 03030130 | B25: OBESOS | C25: COL01 | D25: COL02 | E25: COL03 | F25: COL04 | G25: COL05 | H25: COL06 | I25: COL07 | J25: COL08 | K25: COL09 | L25: COL10 | M25: COL11 | N25: COL12 | O25: COL13 | P25: COL14 | Q25: COL15 | R25: COL16 | S25: COL17 | T25: COL18 | U25: COL19 | V25: COL20 | W25: COL21 | X25: COL22 | Y25: COL23 | Z25: COL24 | AA25: COL25 | AB25: COL26 | AC25: COL27 | AD25: COL28 | AE25: COL29 | AF25: COL30 | AG25: COL31
B26: SECCIÓN C: RESULTADOS DE EMP SEGÚN ESTADO DE SALUD
B27: ESTADO DE SALUD | C27: TOTAL | F27: 15 a 19 | H27: 20 a 24 | J27: 25 a 29 | L27: 30 a 34 | N27: 35 a 39 | P27: 40 a 44 | R27: 45 a 49 | T27: 50 a 54 | V27: 55 a 59 | X27: 60 a 64 | Z27: 65 a 69 | AB27: 70 a 74 | AD27: 75 a 79 | AF27: 80 y más
C28: Ambos Sexos | D28: Hombres | E28: Mujeres | F28: Hombres | G28: Mujeres | H28: Hombres | I28: Mujeres | J28: Hombres | K28: Mujeres | L28: Hombres | M28: Mujeres | N28: Hombres | O28: Mujeres | P28: Hombres | Q28: Mujeres | R28: Hombres | S28: Mujeres | T28: Hombres | U28: Mujeres | V28: Hombres | W28: Mujeres | X28: Hombres | Y28: Mujeres | Z28: Hombres | AA28: Mujeres | AB28: Hombres | AC28: Mujeres | AD28: Hombres | AE28: Mujeres | AF28: Hombres | AG28: Mujeres
A29: 02200010 | B29: TABAQUISMO | C29: COL01 | D29: COL02 | E29: COL03 | F29: COL04 | G29: COL05 | H29: COL06 | I29: COL07 | J29: COL08 | K29: COL09 | L29: COL10 | M29: COL11 | N29: COL12 | O29: COL13 | P29: COL14 | Q29: COL15 | R29: COL16 | S29: COL17 | T29: COL18 | U29: COL19 | V29: COL20 | W29: COL21 | X29: COL22 | Y29: COL23 | Z29: COL24 | AA29: COL25 | AB29: COL26 | AC29: COL27 | AD29: COL28 | AE29: COL29 | AF29: COL30 | AG29: COL31 | CH29: 0
A30: 02200020 | B30: PRESIÓN ARTERIAL ELEVADA (= >140/90 mmHg) | C30: COL01 | D30: COL02 | E30: COL03 | F30: COL04 | G30: COL05 | H30: COL06 | I30: COL07 | J30: COL08 | K30: COL09 | L30: COL10 | M30: COL11 | N30: COL12 | O30: COL13 | P30: COL14 | Q30: COL15 | R30: COL16 | S30: COL17 | T30: COL18 | U30: COL19 | V30: COL20 | W30: COL21 | X30: COL22 | Y30: COL23 | Z30: COL24 | AA30: COL25 | AB30: COL26 | AC30: COL27 | AD30: COL28 | AE30: COL29 | AF30: COL30 | AG30: COL31 | CH30: 0
B31: SECCIÓN D: RESULTADOS DE EMP SEGÚN ESTADO DE SALUD (EXÁMENES DE LABORATORIO)
B32: ESTADO DE SALUD | C32: TOTAL | F32: 15 a 19 años | H32: 20 a 24 años | J32: 25 a 29 | L32: 30 a 34 | N32: 35 a 39 | P32: 40 a 44 | R32: 45 a 49 | T32: 50 a 54 | V32: 55 a 59 | X32: 60 a 64 | Z32: 65 a 69 | AB32: 70 a 74 | AD32: 75 a 79 | AF32: 80 y más
C33: Ambos Sexos | D33: Hombres | E33: Mujeres | F33: Hombres | G33: Mujeres | H33: Hombres | I33: Mujeres | J33: Hombres | K33: Mujeres | L33: Hombres | M33: Mujeres | N33: Hombres | O33: Mujeres | P33: Hombres | Q33: Mujeres | R33: Hombres | S33: Mujeres | T33: Hombres | U33: Mujeres | V33: Hombres | W33: Mujeres | X33: Hombres | Y33: Mujeres | Z33: Hombres | AA33: Mujeres | AB33: Hombres | AC33: Mujeres | AD33: Hombres | AE33: Mujeres | AF33: Hombres | AG33: Mujeres
A34: 02200030 | B34: GLICEMIA ALTERADA (= > a 100 mg/dl) | C34: COL01 | D34: COL02 | E34: COL03 | F34: COL04 | G34: COL05 | H34: COL06 | I34: COL07 | J34: COL08 | K34: COL09 | L34: COL10 | M34: COL11 | N34: COL12 | O34: COL13 | P34: COL14 | Q34: COL15 | R34: COL16 | S34: COL17 | T34: COL18 | U34: COL19 | V34: COL20 | W34: COL21 | X34: COL22 | Y34: COL23 | Z34: COL24 | AA34: COL25 | AB34: COL26 | AC34: COL27 | AD34: COL28 | AE34: COL29 | AF34: COL30 | AG34: COL31
A35: 02200040 | B35: COLESTEROL ELEVADO (= > 200 mg/dl) | C35: COL01 | D35: COL02 | E35: COL03 | F35: COL04 | G35: COL05 | H35: COL06 | I35: COL07 | J35: COL08 | K35: COL09 | L35: COL10 | M35: COL11 | N35: COL12 | O35: COL13 | P35: COL14 | Q35: COL15 | R35: COL16 | S35: COL17 | T35: COL18 | U35: COL19 | V35: COL20 | W35: COL21 | X35: COL22 | Y35: COL23 | Z35: COL24 | AA35: COL25 | AB35: COL26 | AC35: COL27 | AD35: COL28 | AE35: COL29 | AF35: COL30 | AG35: COL31
B195: =SUM(C12:C17,C21:C25,C29:C30,C34:C35) -> 0 | C195: =SUM(CH7:CN52) -> 0

Sheet A03
B1: SERVICIO DE SALUD
B2: =CONCATENATE("COMUNA:",NOMBRE!B2," - ","( ",NOMBRE!C2,NOMBRE!D2,NOMBRE!E2,NOMBRE!F2,NOMBRE!G2," )") -> COMUNA: - ( )
B3: =CONCATENATE("ESTABLECIMIENTO/ESTRATEGIA: ",NOMBRE!B3," - ","( ",NOMBRE!C3,NOMBRE!D3,NOMBRE!E3,NOMBRE!F3,NOMBRE!G3,NOMBRE!H3," )") -> ESTABLECIMIENTO/ESTRATEGIA: - ( )
B4: =CONCATENATE("MES: ",NOMBRE!B6," - ","( ",NOMBRE!C6,NOMBRE!D6," )") -> MES: - ( )
B5: =CONCATENATE("AÑO: ",NOMBRE!B7) -> AÑO: 2020
B6: REM-A03. APLICACIÓN Y RESULTADOS DE ESCALAS DE EVALUACIÓN
B7: SECCIÓN A: APLICACIÓN DE INSTRUMENTO Y RESULTADO EN EL NIÑO (A)
B8: SECCIÓN A.1: APLICACIÓN Y RESULTADOS DE PAUTA BREVE
A9: CODIGO DICCIONARIO | B9: EVALUACIONES POR EDAD DEL NIÑO | D9: TOTAL | G9: GRUPO DE EDAD
G10: Menor de 1 mes | I10: 1 mes | K10: 2 meses | M10: 3 meses | O10: 4 meses | Q10: 5 meses | S10: 6 meses | U10: 7 - 11 meses | W10: 12 - 17 meses | Y10: 18 - 24 meses
D11: Ambos Sexos | E11: Hombres | F11: Mujeres | G11: Hombres | H11: Mujeres | I11: Hombres | J11: Mujeres | K11: Hombres | L11: Mujeres | M11: Hombres | N11: Mujeres | O11: Hombres | P11: Mujeres | Q11: Hombres | R11: Mujeres | S11: Hombres | T11: Mujeres | U11: Hombres | V11: Mujeres | W11: Hombres | X11: Mujeres | Y11: Hombres | Z11: Mujeres
A12: 02021730 | B12: APLICACIÓN PAUTA BREVE | D12: COL01 | E12: COL02 | F12: COL03 | G12: COL04 | H12: COL05 | I12: COL06 | J12: COL07 | K12: COL08 | L12: COL09 | M12: COL10 | N12: COL11 | O12: COL12 | P12: COL13 | Q12: COL14 | R12: COL15 | S12: COL16 | T12: COL17 | U12: COL18 | V12: COL19 | W12: COL20 | X12: COL21 | Y12: COL22 | Z12: COL23
A13: 03500020 | B13: RESULTADOS | C13: NORMAL | D13: COL01 | E13: COL02 | F13: COL03 | G13: COL04 | H13: COL05 | I13: COL06 | J13: COL07 | K13: COL08 | L13: COL09 | M13: COL10 | N13: COL11 | O13: COL12 | P13: COL13 | Q13: COL14 | R13: COL15 | S13: COL16 | T13: COL17 | U13: COL18 | V13: COL19 | W13: COL20 | X13: COL21 | Y13: COL22 | Z13: COL23 | DG13: 0 | DH13: 0 | DI13: 0 | DJ13: 0 | DK13: 0 | DL13: 0 | DM13: 0 | DN13: 0 | DO13: 0 | DP13: 0 | DQ13: 0 | DR13: 0 | DS13: 0 | DT13: 0 | DU13: 0 | DV13: 0 | DW13: 0 | DX13: 0 | DY13: 0 | DZ13: 0
A14: 03500030 | C14: ALTERADO | D14: COL01 | E14: COL02 | F14: COL03 | G14: COL04 | H14: COL05 | I14: COL06 | J14: COL07 | K14: COL08 | L14: COL09 | M14: COL10 | N14: COL11 | O14: COL12 | P14: COL13 | Q14: COL14 | R14: COL15 | S14: COL16 | T14: COL17 | U14: COL18 | V14: COL19 | W14: COL20 | X14: COL21 | Y14: COL22 | Z14: COL23
B16: SECCIÓN A.2: RESULTADOS DE LA APLICACIÓN DE ESCALA DE EVALUACIÓN DEL DESARROLLO PSICOMOTOR
B17: ACTIVIDAD | C17: RESULTADO | D17: TOTAL | G17: POR EDAD | S17: MIGRANTES
G18: Menor 7 meses | I18: 7 - 11 meses | K18: 12 - 17 meses | M18: 18 - 23 meses | O18: 24 - 47 meses | Q18: 48 - 59 meses
D19: Ambos Sexos | E19: Hombres | F19: Mujeres | G19: Hombres | H19: Mujeres | I19: Hombres | J19: Mujeres | K19: Hombres | L19: Mujeres | M19: Hombres | N19: Mujeres | O19: Hombres | P19: Mujeres | Q19: Hombres | R19: Mujeres
A20: 02021740 | B20: APLICACIÓN TEST DE DESARROLLO PSICOMOTOR | D20: COL01 | E20: COL02 | F20: COL03 | G20: COL04 | H20: COL05 | I20: COL06 | J20: COL07 | K20: COL08 | L20: COL09 | M20: COL10 | N20: COL11 | O20: COL12 | P20: COL13 | Q20: COL14 | R20: COL15 | S20: COL16 | CH20: 0 | CI20: 0 | CJ20: 0 | CK20: 0 | CL20: 0 | CM20: 0 | CN20: 0 | CO20: 0
A21: 02010320 | B21: PRIMERA EVALUACIÓN | C21: NORMAL | D21: COL01 | E21: COL02 | F21: COL03 | G21: COL04 | H21: COL05 | I21: COL06 | J21: COL07 | K21: COL08 | L21: COL09 | M21: COL10 | N21: COL11 | O21: COL12 | P21: COL13 | Q21: COL14 | R21: COL15 | S21: COL16
A22: 05225303 | C22: NORMAL CON REZAGO | D22: COL01 | E22: COL02 | F22: COL03 | G22: COL04 | H22: COL05 | I22: COL06 | J22: COL07 | K22: COL08 | L22: COL09 | M22: COL10 | N22: COL11 | O22: COL12 | P22: COL13 | Q22: COL14 | R22: COL15 | S22: COL16
A23: 02010321 | C23: RIESGO | D23: COL01 | E23: COL02 | F23: COL03 | G23: COL04 | H23: COL05 | I23: COL06 | J23: COL07 | K23: COL08 | L23: COL09 | M23: COL10 | N23: COL11 | O23: COL12 | P23: COL13 | Q23: COL14 | R23: COL15 | S23: COL16
A24: 02010322 | C24: RETRASO | D24: COL01 | E24: COL02 | F24: COL03 | G24: COL04 | H24: COL05 | I24: COL06 | J24: COL07 | K24: COL08 | L24: COL09 | M24: COL10 | N24: COL11 | O24: COL12 | P24: COL13 | Q24: COL14 | R24: COL15 | S24: COL16
A25: 05225304 | B25: REEVALUACIÓN | C25: NORMAL (desde normal con rezago) | D25: COL01 | E25: COL02 | F25: COL03 | G25: COL04 | H25: COL05 | I25: COL06 | J25: COL07 | K25: COL08 | L25: COL09 | M25: COL10 | N25: COL11 | O25: COL12 | P25: COL13 | Q25: COL14 | R25: COL15 | S25: COL16
A26: 02010420 | C26: NORMAL (desde riesgo) | D26: COL01 | E26: COL02 | F26: COL03 | G26: COL04 | H26: COL05 | I26: COL06 | J26: COL07 | K26: COL08 | L26: COL09 | M26: COL10 | N26: COL11 | O26: COL12 | P26: COL13 | Q26: COL14 | R26: COL15 | S26: COL16
A27: 05225305 | C27: NORMAL (desde retraso) | D27: COL01 | E27: COL02 | F27: COL03 | G27: COL04 | H27: COL05 | I27: COL06 | J27: COL07 | K27: COL08 | L27: COL09 | M27: COL10 | N27: COL11 | O27: COL12 | P27: COL13 | Q27: COL14 | R27: COL15 | S27: COL16
A28: 03500366 | C28: NORMAL CON REZAGO (desde riesgo) | D28: COL01 | E28: COL02 | F28: COL03 | G28: COL04 | H28: COL05 | I28: COL06 | J28: COL07 | K28: COL08 | L28: COL09 | M28: COL10 | N28: COL11 | O28: COL12 | P28: COL13 | Q28: COL14 | R28: COL15 | S28: COL16
A29: 03500400 | C29: NORMAL CON REZAGO (desde retraso) | D29: COL01 | E29: COL02 | F29: COL03 | G29: COL04 | H29: COL05 | I29: COL06 | J29: COL07 | K29: COL08 | L29: COL09 | M29: COL10 | N29: COL11 | O29: COL12 | P29: COL13 | Q29: COL14 | R29: COL15 | S29: COL16
A30: 03500401 | C30: RIESGO (desde retraso) | D30: COL01 | E30: COL02 | F30: COL03 | G30: COL04 | H30: COL05 | I30: COL06 | J30: COL07 | K30: COL08 | L30: COL09 | M30: COL10 | N30: COL11 | O30: COL12 | P30: COL13 | Q30: COL14 | R30: COL15 | S30: COL16
A31: 05225306 | C31: NORMAL CON REZAGO (desde normal con rezago) | D31: COL01 | E31: COL02 | F31: COL03 | G31: COL04 | H31: COL05 | I31: COL06 | J31: COL07 | K31: COL08 | L31: COL09 | M31: COL10 | N31: COL11 | O31: COL12 | P31: COL13 | Q31: COL14 | R31: COL15 | S31: COL16
A32: 02010421 | C32: RIESGO (desde riesgo) | D32: COL01 | E32: COL02 | F32: COL03 | G32: COL04 | H32: COL05 | I32: COL06 | J32: COL07 | K32: COL08 | L32: COL09 | M32: COL10 | N32: COL11 | O32: COL12 | P32: COL13 | Q32: COL14 | R32: COL15 | S32: COL16
A33: 02010422 | C33: RETRASO (desde retraso) | D33: COL01 | E33: COL02 | F33: COL03 | G33: COL04 | H33: COL05 | I33: COL06 | J33: COL07 | K33: COL08 | L33: COL09 | M33: COL10 | N33: COL11 | O33: COL12 | P33: COL13 | Q33: COL14 | R33: COL15 | S33: COL16
A34: 03500331 | B34: DERIVADOS A ESPECIALIDAD | C34: RIESGO | D34: COL01 | E34: COL02 | F34: COL03 | G34: COL04 | H34: COL05 | I34: COL06 | J34: COL07 | K34: COL08 | L34: COL09 | M34: COL10 | N34: COL11 | O34: COL12 | P34: COL13 | Q34: COL14 | R34: COL15 | S34: COL16
A35: 03500332 | C35: RETRASO | D35: COL01 | E35: COL02 | F35: COL03 | G35: COL04 | H35: COL05 | I35: COL06 | J35: COL07 | K35: COL08 | L35: COL09 | M35: COL10 | N35: COL11 | O35: COL12 | P35: COL13 | Q35: COL14 | R35: COL15 | S35: COL16
A36: 03500333 | B36: TRASLADO DE ESTABLECIMIENTO | C36: NORMAL CON REZAGO | D36: COL01 | E36: COL02 | F36: COL03 | G36: COL04 | H36: COL05 | I36: COL06 | J36: COL07 | K36: COL08 | L36: COL09 | M36: COL10 | N36: COL11 | O36: COL12 | P36: COL13 | Q36: COL14 | R36: COL15 | S36: COL16
A37: 03500334 | C37: RIESGO | D37: COL01 | E37: COL02 | F37: COL03 | G37: COL04 | H37: COL05 | I37: COL06 | J37: COL07 | K37: COL08 | L37: COL09 | M37: COL10 | N37: COL11 | O37: COL12 | P37: COL13 | Q37: COL14 | R37: COL15 | S37: COL16
A38: 03500335 | C38: RETRASO | D38: COL01 | E38: COL02 | F38: COL03 | G38: COL04 | H38: COL05 | I38: COL06 | J38: COL07 | K38: COL08 | L38: COL09 | M38: COL10 | N38: COL11 | O38: COL12 | P38: COL13 | Q38: COL14 | R38: COL15 | S38: COL16
B39: SECCIÓN A.3: NIÑOS Y NIÑAS CON REZAGO, DÉFICIT U OTRA VULNERABILIDAD DERIVADOS A ALGUNA MODALIDAD DE ESTIMULACIÓN EN LA PRIMERA EVALUACIÓN
B40: NIÑO / A | D40: TOTAL | G40: POR EDAD
G41: Menor 7 meses | I41: 7 - 11 meses | K41: 12 - 17 meses | M41: 18 - 23 meses | O41: 24 - 47 meses | Q41: 48 - 59 meses
D42: Ambos Sexos | E42: Hombres | F42: Mujeres | G42: Hombres | H42: Mujeres | I42: Hombres | J42: Mujeres | K42: Hombres | L42: Mujeres | M42: Hombres | N42: Mujeres | O42: Hombres | P42: Mujeres | Q42: Hombres | R42: Mujeres
A43: 02021790 | B43: NORMAL CON REZAGO | D43: COL01 | E43: COL02 | F43: COL03 | G43: COL04 | H43: COL05 | I43: COL06 | J43: COL07 | K43: COL08 | L43: COL09 | M43: COL10 | N43: COL11 | O43: COL12 | P43: COL13 | Q43: COL14 | R43: COL15 | S43: =CB43 | CB43: =IF(D43<>'A05'!D63,"* Niños derivados deben ser iguales al ingreso de niños(as) Normal con Rezago a salas de estimulación REM A05 sección F. ","")
A44: 02021810 | B44: RIESGO | D44: COL01 | E44: COL02 | F44: COL03 | G44: COL04 | H44: COL05 | I44: COL06 | J44: COL07 | K44: COL08 | L44: COL09 | M44: COL10 | N44: COL11 | O44: COL12 | P44: COL13 | Q44: COL14 | R44: COL15 | S44: =CB44 | CB44: =IF(D44<>'A05'!D64,"* Niños derivados deben ser iguales al ingreso de niños(as) con Riesgo a salas de estimulación REM A05 sección F. ","")
A45: 02021820 | B45: RETRASO | D45: COL01 | E45: COL02 | F45: COL03 | G45: COL04 | H45: COL05 | I45: COL06 | J45: COL07 | K45: COL08 | L45: COL09 | M45: COL10 | N45: COL11 | O45: COL12 | P45: COL13 | Q45: COL14 | R45: COL15 | S45: =CB45 | CB45: =IF(D45<>'A05'!D65,"* Niños derivados deben ser iguales al ingreso de niños(as) con Retraso a salas de estimulación REM A05 sección F. ","")
A46: 05225307 | B46: OTRA VULNERABILIDAD | D46: COL01 | E46: COL02 | F46: COL03 | G46: COL04 | H46: COL05 | I46: COL06 | J46: COL07 | K46: COL08 | L46: COL09 | M46: COL10 | N46: COL11 | O46: COL12 | P46: COL13 | Q46: COL14 | R46: COL15 | S46: =CB46 | CB46: =IF(D46<>'A05'!D66,"* Niños derivados deben ser iguales al ingreso de niños(as) con Otras Vulnerabilidad a salas de estimulación REM A05 sección F. ","")
B47: SECCIÓN A.4: RESULTADOS DE LA APLICACIÓN DE PROTOCOLO NEUROSENSORIAL
B48: RESULTADOS | D48: TOTAL | G48: POR EDAD
G49: 1 mes | I49: 2 meses
D50: Ambos Sexos | E50: Hombres | F50: Mujeres | G50: Hombres | H50: Mujeres | I50: Hombres | J50: Mujeres
A51: 02021760 | B51: APLICACIÓN DE PROTOCOLO NEUROSENSORIAL (1-2 MESES) | D51: =SUM(E51+F51) -> 0 | E51: =SUM(G51+I51) -> 0 | F51: =SUM(H51+J51) -> 0 | G51: =SUM(G52:G54) -> 0 | H51: =SUM(H52:H54) -> 0 | I51: =SUM(I52:I54) -> 0 | J51: =SUM(J52:J54) -> 0
A52: 03500040 | B52: NORMAL | D52: COL01 | E52: COL02 | F52: COL03 | G52: COL04 | H52: COL05 | I52: COL06 | J52: COL07
A53: 03500050 | B53: ANORMAL | D53: COL01 | E53: COL02 | F53: COL03 | G53: COL04 | H53: COL05 | I53: COL06 | J53: COL07
A54: 03500060 | B54: MUY ANORMAL | D54: COL01 | E54: COL02 | F54: COL03 | G54: COL04 | H54: COL05 | I54: COL06 | J54: COL07
B55: SECCIÓN A.5: LACTANCIA MATERNA EN MENORES CONTROLADOS
B56: TIPO DE ALIMENTACIÓN | D56: TOTAL | G56: SEGÚN CONTROL PROGRAMÁTICO
G57: Del 1° mes | I57: Del 3° mes | K57: Del 6° mes | M57: Del 12° mes | O57: Del 24° mes
D58: Ambos Sexos | E58: Hombres | F58: Mujeres | G58: Hombres | H58: Mujeres | I58: Hombres | J58: Mujeres | K58: Hombres | L58: Mujeres | M58: Hombres | N58: Mujeres | O58: Hombres | P58: Mujeres
A59: A0200001 | B59: MENORES CONTROLADOS | D59: COL01 | E59: COL02 | F59: COL03 | G59: COL04 | H59: COL05 | I59: COL06 | J59: COL07 | K59: COL08 | L59: COL09 | M59: COL10 | N59: COL11 | O59: COL12 | P59: COL13 | CH59: 0 | CI59: 0 | CJ59: 0 | CK59: 0 | CL59: 0
A60: A0200002 | B60: LACTANCIA MATERNA EXCLUSIVA | D60: COL01 | E60: COL02 | F60: COL03 | G60: COL04 | H60: COL05 | I60: COL06 | J60: COL07 | K60: COL08 | L60: COL09 | M60: COL10 | N60: COL11 | O60: COL12 | P60: COL13
A61: 03500359 | B61: LACTANCIA MATERNA / FORMULA LACTEA | D61: COL01 | E61: COL02 | F61: COL03 | G61: COL04 | H61: COL05 | I61: COL06 | J61: COL07 | K61: COL08 | L61: COL09 | M61: COL10 | N61: COL11 | O61: COL12 | P61: COL13
A62: 03500360 | B62: FORMULA LACTEA | D62: COL01 | E62: COL02 | F62: COL03 | G62: COL04 | H62: COL05 | I62: COL06 | J62: COL07 | K62: COL08 | L62: COL09 | M62: COL10 | N62: COL11 | O62: COL12 | P62: COL13
A63: A0200003 | B63: LACTANCIA MATERNA MAS SÓLIDOS | D63: COL01 | E63: COL02 | F63: COL03 | G63: COL04 | H63: COL05 | I63: COL06 | J63: COL07 | K63: COL08 | L63: COL09 | M63: COL10 | N63: COL11 | O63: COL12 | P63: COL13
B64: SECCION B: EVALUACIÓN, APLICACIÓN Y RESULTADOS DE ESCALAS EN LA MUJER
B65: SECCIÓN B.1: EVALUACIÓN DEL ESTADO NUTRICIONAL A MUJERES CONTROLADAS AL OCTAVO MES POST PARTO
B66: ESTADO NUTRICIONAL | D66: TOTAL
B68: TOTAL | D68: =SUM(D69:D72) -> 0
A69: 03500120 | B69: OBESA | D69: COL01
A70: 03500130 | B70: SOBREPESO | D70: COL01
A71: 03500140 | B71: NORMAL | D71: COL01
A72: 03500150 | B72: BAJO PESO | D72: COL01
B73: SECCIÓN B.2: APLICACIÓN DE ESCALA SEGÚN EVALUACIÓN DE RIESGO PSICOSOCIAL ABREVIADA A GESTANTES
B74: TIPO | D74: TOTAL DE APLICACIONES | E74: RIESGO | F74: DERIVADAS A EQUIPO DE CABECERA
A75: 02021830 | B75: EVALUACIÓN AL INGRESO | D75: COL01 | E75: COL02 | F75: COL03 | CD75: =IF(D75<='A05'!D11,"", "* Total de aplicaciones EPSA NO DEBE ser MAYOR que el Total de Gestantes ingresadas en REM A05 Secci„n A. ") | CH75: 0 | CI75: 0
B76: SECCIÓN B.3: APLICACIÓN DE ESCALA DE EDIMBURGO A GESTANTES Y MUJERES POST PARTO | CH76: 0
B77: CONCEPTO | D77: TOTAL DE APLICACIONES | E77: RESULTADOS 10 O MÁS PTOS. O RESULTADO DISTINTO DE 0 EN PREG 10 . (PUERPERAS) | F77: RESULTADOS 13 O MÁS PTOS O RESULTADO DISTINTO DE 0 EN PREG 10. (GESTANTES) | G77: TOTAL DE CASOS ALTERADOS DERIVADOS A SALUD MENTAL | CH77: 0
A78: 03500160 | B78: EVALUACIÓN A GESTANTES | C78: PRIMERA EVALUACIÓN (2º control prenatal) | D78: COL01 | E78: COL02 | F78: COL03 | G78: COL04 | CH78: 0
A79: 03500170 | C79: REEVALUACIÓN (con puntaje elevado en la primera evaluación) | D79: COL01 | E79: COL02 | F79: COL03 | G79: COL04 | CH79: 0
A80: 03500200 | B80: EVALUACIÓN A MUJERES POST PARTO O SÍNTOMAS DE DEPRESIÓN | C80: A los 2 meses | D80: COL01 | E80: COL02 | F80: COL03 | G80: COL04 | CH80: 0
A81: 03500210 | C81: A los 6 meses | D81: COL01 | E81: COL02 | F81: COL03 | G81: COL04 | CH81: 0
B82: SECCIÓN C: RESULTADOS DE LA EVALUACIÓN DEL ESTADO NUTRICIONAL DEL ADOLESCENTE CON CONTROL SALUD INTEGRAL
B83: ESTADO NUTRICIONAL | D83: TOTAL | G83: 10 A 14 | I83: 15 A 19
D84: Ambos Sexos | E84: Hombres | F84: Mujeres | G84: Hombres | H84: Mujeres | I84: Hombres | J84: Mujeres
B85: TOTAL | D85: =SUM(D86:D90) -> 0 | E85: =SUM(E86:E90) -> 0 | F85: =SUM(F86:F90) -> 0 | G85: =SUM(G86:G90) -> 0 | H85: =SUM(H86:H90) -> 0 | I85: =SUM(I86:I90) -> 0 | J85: =SUM(J86:J90) -> 0
A86: 03050400 | B86: NORMAL | D86: COL01 | E86: COL02 | F86: COL03 | G86: COL04 | H86: COL05 | I86: COL06 | J86: COL07
A87: 03050500 | B87: BAJO PESO | D87: COL01 | E87: COL02 | F87: COL03 | G87: COL04 | H87: COL05 | I87: COL06 | J87: COL07
A88: 03050600 | B88: SOBREPESO | D88: COL01 | E88: COL02 | F88: COL03 | G88: COL04 | H88: COL05 | I88: COL06 | J88: COL07
A89: 03050700 | B89: OBESOS | D89: COL01 | E89: COL02 | F89: COL03 | G89: COL04 | H89: COL05 | I89: COL06 | J89: COL07
A90: 03050710 | B90: OBESOS SEVEROS | D90: COL01 | E90: COL02 | F90: COL03 | G90: COL04 | H90: COL05 | I90: COL06 | J90: COL07
B91: SECCIÓN D: OTRAS EVALUACIONES, APLICACIONES Y RESULTADOS DE ESCALAS EN TODAS LAS EDADES
B92: SECCIÓN D.1: APLICACIÓN DE TAMIZAJE PARA EVALUAR EL NIVEL DE RIESGO DE CONSUMO DE ALCOHOL, TABACO Y OTRAS DROGAS
B93: COMPONENTE | D93: TOTAL | G93: POR EDAD
G94: 10-14 años | I94: 15-19 años | K94: 20-24 años | M94: 25-44 años | O94: 45-64 años | Q94: 65 o más
D95: Ambos Sexos | E95: Hombres | F95: Mujeres | G95: Hombres | H95: Mujeres | I95: Hombres | J95: Mujeres | K95: Hombres | L95: Mujeres | M95: Hombres | N95: Mujeres | O95: Hombres | P95: Mujeres | Q95: Hombres | R95: Mujeres
A96: 03500346 | B96: Nº DE AUDIT (EMP/EMPAM) | D96: COL01 | E96: COL02 | F96: COL03 | G96: COL04 | H96: COL05 | I96: COL06 | J96: COL07 | K96: COL08 | L96: COL09 | M96: COL10 | N96: COL11 | O96: COL12 | P96: COL13 | Q96: COL14 | R96: COL15
A97: 03500347 | B97: Nº DE AUDIT APLICADO | D97: COL01 | E97: COL02 | F97: COL03 | G97: COL04 | H97: COL05 | I97: COL06 | J97: COL07 | K97: COL08 | L97: COL09 | M97: COL10 | N97: COL11 | O97: COL12 | P97: COL13 | Q97: COL14 | R97: COL15
A98: 03500402 | B98: Nº DE ASSIST (EMP/EMPAM) | D98: COL01 | E98: COL02 | F98: COL03 | G98: COL04 | H98: COL05 | I98: COL06 | J98: COL07 | K98: COL08 | L98: COL09 | M98: COL10 | N98: COL11 | O98: COL12 | P98: COL13 | Q98: COL14 | R98: COL15
A99: 03500348 | B99: N° DE ASSIST APLICADO | D99: COL01 | E99: COL02 | F99: COL03 | G99: COL04 | H99: COL05 | I99: COL06 | J99: COL07 | K99: COL08 | L99: COL09 | M99: COL10 | N99: COL11 | O99: COL12 | P99: COL13 | Q99: COL14 | R99: COL15
A100: 03600100 | B100: N° DE CRAFFT EN CONTROL DE SALUD INTEGRAL DEL ADOLESCENTE | D100: COL01 | E100: COL02 | F100: COL03 | G100: COL04 | H100: COL05 | I100: COL06 | J100: COL07 | K100: COL08 | L100: COL09 | M100: COL10 | N100: COL11 | O100: COL12 | P100: COL13 | Q100: COL14 | R100: COL15
A101: 03500367 | B101: N° DE CRAFFT APLICADO | D101: COL01 | E101: COL02 | F101: COL03 | G101: COL04 | H101: COL05 | I101: COL06 | J101: COL07 | K101: COL08 | L101: COL09 | M101: COL10 | N101: COL11 | O101: COL12 | P101: COL13 | Q101: COL14 | R101: COL15
A102: 03500349 | B102: RESULTADOS DE EVALUACIÓN | C102: BAJO RIESGO | D102: COL01 | E102: COL02 | F102: COL03 | G102: COL04 | H102: COL05 | I102: COL06 | J102: COL07 | K102: COL08 | L102: COL09 | M102: COL10 | N102: COL11 | O102: COL12 | P102: COL13 | Q102: COL14 | R102: COL15
...

Sheet A04
B1: SERVICIO DE SALUD
B2: =CONCATENATE("COMUNA: ",NOMBRE!B2," - ","( ",NOMBRE!C2,NOMBRE!D2,NOMBRE!E2,NOMBRE!F2,NOMBRE!G2," )") -> COMUNA: - ( )
B3: =CONCATENATE("ESTABLECIMIENTO/ESTRATEGIA: ",NOMBRE!B3," - ","( ",NOMBRE!C3,NOMBRE!D3,NOMBRE!E3,NOMBRE!F3,NOMBRE!G3,NOMBRE!H3," )") -> ESTABLECIMIENTO/ESTRATEGIA: - ( )
B4: =CONCATENATE("MES: ",NOMBRE!B6," - ","( ",NOMBRE!C6,NOMBRE!D6," )") -> MES: - ( )
B5: =CONCATENATE("AÑO: ",NOMBRE!B7) -> AÑO: 2020
B6: REM-A04. CONSULTAS Y OTRAS ATENCIONES EN LA RED
B8: SECCIÓN A: CONSULTAS MÉDICAS
A9: CODIGO DICCIONARIO | B9: TIPO DE CONSULTA | C9: TOTAL | F9: POR DE EDAD (en años) | AP9: Beneficiarios | AQ9: Pueblos Originarios | AR9: Migrantes | AS9: Niños, Niñas, Adolescentes y Jóvenes Población SENAME | AT9: Por Campaña de Invierno
F10: Menor de 1 | H10: 1 a 4 | J10: 5 a 9 | L10: 10 a 14 | N10: 15 a 19 | P10: 20 a 24 | R10: 25 - 29 | T10: 30 - 34 | V10: 35 - 39 | X10: 40 - 44 | Z10: 45 - 49 | AB10: 50 - 54 | AD10: 55 - 59 | AF10: 60 - 64 | AH10: 65 - 69 | AJ10: 70 - 74 | AL10: 75 - 79 | AN10: 80 y mas
C11: Ambos Sexos | D11: Hombres | E11: Mujeres | F11: Hombres | G11: Mujeres | H11: Hombres | I11: Mujeres | J11: Hombres | K11: Mujeres | L11: Hombres | M11: Mujeres | N11: Hombres | O11: Mujeres | P11: Hombres | Q11: Mujeres | R11: Hombres | S11: Mujeres | T11: Hombres | U11: Mujeres | V11: Hombres | W11: Mujeres | X11: Hombres | Y11: Mujeres | Z11: Hombres | AA11: Mujeres | AB11: Hombres | AC11: Mujeres | AD11: Hombres | AE11: Mujeres | AF11: Hombres | AG11: Mujeres | AH11: Hombres | AI11: Mujeres | AJ11: Hombres | AK11: Mujeres | AL11: Hombres | AM11: Mujeres | AN11: Hombres | AO11: Mujeres
B12: TOTAL | C12: =SUM(C13:C26) -> 0 | D12: =SUM(D13:D26) -> 0 | E12: =SUM(E13:E26) -> 0 | F12: =SUM(F13:F26) -> 0 | G12: =SUM(G13:G26) -> 0 | H12: =SUM(H13:H26) -> 0 | I12: =SUM(I13:I26) -> 0 | J12: =SUM(J13:J26) -> 0 | ... AT12: =SUM(AT13:AT26) -> 0
A13: 03020101 | B13: IRA ALTA | C13: COL01 | D13: COL02 | E13: COL03 | F13: COL04 | G13: COL05 | H13: COL06 | I13: COL07 | J13: COL08 | K13: COL09 | L13: COL10 | M13: COL11 | N13: COL12 | O13: COL13 | P13: COL14 | Q13: COL15 | R13: COL16 | S13: COL17 | T13: COL18 | U13: COL19 | V13: COL20 | W13: COL21 | X13: COL22 | Y13: COL23 | Z13: COL24 | AA13: COL25 | AB13: COL26 | AC13: COL27 | AD13: COL28 | AE13: COL29 | AF13: COL30 | AG13: COL31 | AH13: COL32 | AI13: COL33 | AJ13: COL34 | AK13: COL35 | AL13: COL36 | AM13: COL37 | AN13: COL38 | AO13: COL39 | AP13: COL40 | AQ13: COL41 | AR13: COL42 | AS13: COL43 | AT13: COL44 | CG13: 0 | CH13: 0 | CI13: 0 | CJ13: 0 | CK13: 0
A14: 03020201 | B14: SÍNDROME BRONQUIAL OBSTRUCTIVO | C14: COL01 | D14: COL02 | E14: COL03 | F14: COL04 | G14: COL05 | H14: COL06 | I14: COL07 | J14: COL08 | K14: COL09 | L14: COL10 | M14: COL11 | N14: COL12 | O14: COL13 | P14: COL14 | Q14: COL15 | R14: COL16 | S14: COL17 | T14: COL18 | U14: COL19 | V14: COL20 | W14: COL21 | X14: COL22 | Y14: COL23 | Z14: COL24 | AA14: COL25 | AB14: COL26 | AC14: COL27 | AD14: COL28 | AE14: COL29 | AF14: COL30 | AG14: COL31 | AH14: COL32 | AI14: COL33 | AJ14: COL34 | AK14: COL35 | AL14: COL36 | AM14: COL37 | AN14: COL38 | AO14: COL39 | AP14: COL40 | AQ14: COL41 | AR14: COL42 | AS14: COL43 | AT14: COL44 | CG14: 0 | CH14: 0 | CI14: 0 | CJ14: 0 | CK14: 0
A15: 03020301 | B15: NEUMONÍA | C15: COL01 | D15: COL02 | E15: COL03 | F15: COL04 | G15: COL05 | H15: COL06 | I15: COL07 | J15: COL08 | K15: COL09 | L15: COL10 | M15: COL11 | N15: COL12 | O15: COL13 | P15: COL14 | Q15: COL15 | R15: COL16 | S15: COL17 | T15: COL18 | U15: COL19 | V15: COL20 | W15: COL21 | X15: COL22 | Y15: COL23 | Z15: COL24 | AA15: COL25 | AB15: COL26 | AC15: COL27 | AD15: COL28 | AE15: COL29 | AF15: COL30 | AG15: COL31 | AH15: COL32 | AI15: COL33 | AJ15: COL34 | AK15: COL35 | AL15: COL36 | AM15: COL37 | AN15: COL38 | AO15: COL39 | AP15: COL40 | AQ15: COL41 | AR15: COL42 | AS15: COL43 | AT15: COL44 | CG15: 0 | CH15: 0 | CI15: 0 | CJ15: 0 | CK15: 0
A16: 03020402 | B16: ASMA | C16: COL01 | D16: COL02 | E16: COL03 | F16: COL04 | G16: COL05 | H16: COL06 | I16: COL07 | J16: COL08 | K16: COL09 | L16: COL10 | M16: COL11 | N16: COL12 | O16: COL13 | P16: COL14 | Q16: COL15 | R16: COL16 | S16: COL17 | T16: COL18 | U16: COL19 | V16: COL20 | W16: COL21 | X16: COL22 | Y16: COL23 | Z16: COL24 | AA16: COL25 | AB16: COL26 | AC16: COL27 | AD16: COL28 | AE16: COL29 | AF16: COL30 | AG16: COL31 | AH16: COL32 | AI16: COL33 | AJ16: COL34 | AK16: COL35 | AL16: COL36 | AM16: COL37 | AN16: COL38 | AO16: COL39 | AP16: COL40 | AQ16: COL41 | AR16: COL42 | AS16: COL43 | AT16: COL44 | CG16: 0 | CH16: 0 | CI16: 0 | CJ16: 0 | CK16: 0
A17: 03020403 | B17: ENFERMEDAD PULMONAR OBSTRUCTIVA CRÓNICA | C17: COL01 | D17: COL02 | E17: COL03 | F17: COL04 | G17: COL05 | H17: COL06 | I17: COL07 | J17: COL08 | K17: COL09 | L17: COL10 | M17: COL11 | N17: COL12 | O17: COL13 | P17: COL14 | Q17: COL15 | R17: COL16 | S17: COL17 | T17: COL18 | U17: COL19 | V17: COL20 | W17: COL21 | X17: COL22 | Y17: COL23 | Z17: COL24 | AA17: COL25 | AB17: COL26 | AC17: COL27 | AD17: COL28 | AE17: COL29 | AF17: COL30 | AG17: COL31 | AH17: COL32 | AI17: COL33 | AJ17: COL34 | AK17: COL35 | AL17: COL36 | AM17: COL37 | AN17: COL38 | AO17: COL39 | AP17: COL40 | AQ17: COL41 | AR17: COL42 | AS17: COL43 | AT17: COL44 | CG17: 0 | CH17: 0 | CI17: 0 | CJ17: 0 | CK17: 0
A18: 03020401 | B18: OTRAS RESPIRATORIAS | C18: COL01 | D18: COL02 | E18: COL03 | F18: COL04 | G18: COL05 | H18: COL06 | I18: COL07 | J18: COL08 | K18: COL09 | L18: COL10 | M18: COL11 | N18: COL12 | O18: COL13 | P18: COL14 | Q18: COL15 | R18: COL16 | S18: COL17 | T18: COL18 | U18: COL19 | V18: COL20 | W18: COL21 | X18: COL22 | Y18: COL23 | Z18: COL24 | AA18: COL25 | AB18: COL26 | AC18: COL27 | AD18: COL28 | AE18: COL29 | AF18: COL30 | AG18: COL31 | AH18: COL32 | AI18: COL33 | AJ18: COL34 | AK18: COL35 | AL18: COL36 | AM18: COL37 | AN18: COL38 | AO18: COL39 | AP18: COL40 | AQ18: COL41 | AR18: COL42 | AS18: COL43 | AT18: COL44 | CG18: 0 | CH18: 0 | CI18: 0 | CJ18: 0 | CK18: 0
A19: 03040210 | B19: OBSTETRICA | C19: COL01 | D19: COL02 | E19: COL03 | F19: COL04 | G19: COL05 | H19: COL06 | I19: COL07 | J19: COL08 | K19: COL09 | L19: COL10 | M19: COL11 | N19: COL12 | O19: COL13 | P19: COL14 | Q19: COL15 | R19: COL16 | S19: COL17 | T19: COL18 | U19: COL19 | V19: COL20 | W19: COL21 | X19: COL22 | Y19: COL23 | Z19: COL24 | AA19: COL25 | AB19: COL26 | AC19: COL27 | AD19: COL28 | AE19: COL29 | AF19: COL30 | AG19: COL31 | AH19: COL32 | AI19: COL33 | AJ19: COL34 | AK19: COL35 | AL19: COL36 | AM19: COL37 | AN19: COL38 | AO19: COL39 | AP19: COL40 | AQ19: COL41 | AR19: COL42 | AS19: COL43 | AT19: COL44 | CG19: 0 | CH19: 0 | CI19: 0 | CJ19: 0 | CK19: 0
A20: 03040220 | B20: GINECOLÓGICA | C20: COL01 | D20: COL02 | E20: COL03 | F20: COL04 | G20: COL05 | H20: COL06 | I20: COL07 | J20: COL08 | K20: COL09 | L20: COL10 | M20: COL11 | N20: COL12 | O20: COL13 | P20: COL14 | Q20: COL15 | R20: COL16 | S20: COL17 | T20: COL18 | U20: COL19 | V20: COL20 | W20: COL21 | X20: COL22 | Y20: COL23 | Z20: COL24 | AA20: COL25 | AB20: COL26 | AC20: COL27 | AD20: COL28 | AE20: COL29 | AF20: COL30 | AG20: COL31 | AH20: COL32 | AI20: COL33 | AJ20: COL34 | AK20: COL35 | AL20: COL36 | AM20: COL37 | AN20: COL38 | AO20: COL39 | AP20: COL40 | AQ20: COL41 | AR20: COL42 | AS20: COL43 | AT20: COL44 | CG20: 0 | CH20: 0 | CI20: 0 | CJ20: 0 | CK20: 0
A21: 04040100 | B21: GINECOLÓGICA POR INFERTILIDAD | C21: COL01 | D21: COL02 | E21: COL03 | F21: COL04 | G21: COL05 | H21: COL06 | I21: COL07 | J21: COL08 | K21: COL09 | L21: COL10 | M21: COL11 | N21: COL12 | O21: COL13 | P21: COL14 | Q21: COL15 | R21: COL16 | S21: COL17 | T21: COL18 | U21: COL19 | V21: COL20 | W21: COL21 | X21: COL22 | Y21: COL23 | Z21: COL24 | AA21: COL25 | AB21: COL26 | AC21: COL27 | AD21: COL28 | AE21: COL29 | AF21: COL30 | AG21: COL31 | AH21: COL32 | AI21: COL33 | AJ21: COL34 | AK21: COL35 | AL21: COL36 | AM21: COL37 | AN21: COL38 | AO21: COL39 | AP21: COL40 | AQ21: COL41 | AR21: COL42 | AS21: COL43 | AT21: COL44 | CG21: 0 | CH21: 0 | CI21: 0 | CJ21: 0 | CK21: 0
A22: 04025010 | B22: INFECCIÓN TRANSMISIÓN SEXUAL | C22: COL01 | D22: COL02 | E22: COL03 | F22: COL04 | G22: COL05 | H22: COL06 | I22: COL07 | J22: COL08 | K22: COL09 | L22: COL10 | M22: COL11 | N22: COL12 | O22: COL13 | P22: COL14 | Q22: COL15 | R22: COL16 | S22: COL17 | T22: COL18 | U22: COL19 | V22: COL20 | W22: COL21 | X22: COL22 | Y22: COL23 | Z22: COL24 | AA22: COL25 | AB22: COL26 | AC22: COL27 | AD22: COL28 | AE22: COL29 | AF22: COL30 | AG22: COL31 | AH22: COL32 | AI22: COL33 | AJ22: COL34 | AK22: COL35 | AL22: COL36 | AM22: COL37 | AN22: COL38 | AO22: COL39 | AP22: COL40 | AQ22: COL41 | AR22: COL42 | AS22: COL43 | AT22: COL44 | CG22: 0 | CH22: 0 | CI22: 0 | CJ22: 0 | CK22: 0
A23: 04025020 | B23: VIH-SIDA | C23: COL01 | D23: COL02 | E23: COL03 | F23: COL04 | G23: COL05 | H23: COL06 | I23: COL07 | J23: COL08 | K23: COL09 | L23: COL10 | M23: COL11 | N23: COL12 | O23: COL13 | P23: COL14 | Q23: COL15 | R23: COL16 | S23: COL17 | T23: COL18 | U23: COL19 | V23: COL20 | W23: COL21 | X23: COL22 | Y23: COL23 | Z23: COL24 | AA23: COL25 | AB23: COL26 | AC23: COL27 | AD23: COL28 | AE23: COL29 | AF23: COL30 | AG23: COL31 | AH23: COL32 | AI23: COL33 | AJ23: COL34 | AK23: COL35 | AL23: COL36 | AM23: COL37 | AN23: COL38 | AO23: COL39 | AP23: COL40 | AQ23: COL41 | AR23: COL42 | AS23: COL43 | AT23: COL44 | CG23: 0 | CH23: 0 | CI23: 0 | CJ23: 0 | CK23: 0
A24: 04025025 | B24: SALUD MENTAL | C24: COL01 | D24: COL02 | E24: COL03 | F24: COL04 | G24: COL05 | H24: COL06 | I24: COL07 | J24: COL08 | K24: COL09 | L24: COL10 | M24: COL11 | N24: COL12 | O24: COL13 | P24: COL14 | Q24: COL15 | R24: COL16 | S24: COL17 | T24: COL18 | U24: COL19 | V24: COL20 | W24: COL21 | X24: COL22 | Y24: COL23 | Z24: COL24 | AA24: COL25 | AB24: COL26 | AC24: COL27 | AD24: COL28 | AE24: COL29 | AF24: COL30 | AG24: COL31 | AH24: COL32 | AI24: COL33 | AJ24: COL34 | AK24: COL35 | AL24: COL36 | AM24: COL37 | AN24: COL38 | AO24: COL39 | AP24: COL40 | AQ24: COL41 | AR24: COL42 | AS24: COL43 | AT24: COL44 | CG24: 0 | CH24: 0 | CI24: 0 | CJ24: 0 | CK24: 0
... A26: 03020501 | B26: OTRAS MORBILIDADES | C26: COL01 | D26: COL02 | E26: COL03 | F26: COL04 | G26: COL05 | H26: COL06 | I26: COL07 | J26: COL08 | K26: COL09 | L26: COL10 | M26: COL11 | N26: COL12 | O26: COL13 | P26: COL14 | Q26: COL15 | R26: COL16 | S26: COL17 | T26: COL18 | U26: COL19 | V26: COL20 | W26: COL21 | X26: COL22 | Y26: COL23 | Z26: COL24 | AA26: COL25 | AB26: COL26 | AC26: COL27 | AD26: COL28 | AE26: COL29 | AF26: COL30 | AG26: COL31 | AH26: COL32 | AI26: COL33 | AJ26: COL34 | AK26: COL35 | AL26: COL36 | AM26: COL37 | AN26: COL38 | AO26: COL39 | AP26: COL40 | AQ26: COL41 | AR26: COL42 | AS26: COL43 | AT26: COL44 | CG26: 0 | CH26: 0 | CI26: 0 | CJ26: 0 | CK26: 0
B27: SECCIÓN B: CONSULTAS DE PROFESIONALES NO MÉDICOS
B28: PROFESIONAL | C28: TOTAL | F28: POR DE EDAD (en años) | AP28: Beneficiarios | AQ28: Pueblos Originarios | AR28: Migrantes | AS28: Espacios Amigables | AT28: Niños, Niñas, Adolescentes y Jóvenes Población SENAME
F29: Menor de 1 | H29: 1 a 4 | J29: 5 a 9 | L29: 10 a 14 | N29: 15 a 19 | P29: 20 a 24 | R29: 25 - 29 | T29: 30 - 34 | V29: 35 - 39 | X29: 40 - 44 | Z29: 45 - 49 | AB29: 50 - 54 | AD29: 55 - 59 | AF29: 60 - 64 | AH29: 65 - 69 | AJ29: 70 - 74 | AL29: 75 - 79 | AN29: 80 y mas
C30: Ambos Sexos | D30: Hombres | E30: Mujeres | F30: Hombres | G30: Mujeres | H30: Hombres | I30: Mujeres | J30: Hombres | K30: Mujeres | L30: Hombres | M30: Mujeres | N30: Hombres | O30: Mujeres | P30: Hombres | Q30: Mujeres | R30: Hombres | S30: Mujeres | T30: Hombres | U30: Mujeres | V30: Hombres | W30: Mujeres | X30: Hombres | Y30: Mujeres | Z30: Hombres | AA30: Mujeres | AB30: Hombres | AC30: Mujeres | AD30: Hombres | AE30: Mujeres | AF30: Hombres | AG30: Mujeres | AH30: Hombres | AI30: Mujeres | AJ30: Hombres | AK30: Mujeres | AL30: Hombres | AM30: Mujeres | AN30: Hombres | AO30: Mujeres
A31: 03020702 | B31: ENFERMERA /O | C31: COL01 | D31: COL02 | E31: COL03 | F31: COL04 | G31: COL05 | H31: COL06 | I31: COL07 | J31: COL08 | K31: COL09 | L31: COL10 | M31: COL11 | N31: COL12 | O31: COL13 | P31: COL14 | Q31: COL15 | R31: COL16 | S31: COL17 | T31: COL18 | U31: COL19 | V31: COL20 | W31: COL21 | X31: COL22 | Y31: COL23 | Z31: COL24 | AA31: COL25 | AB31: COL26 | AC31: COL27 | AD31: COL28 | AE31: COL29 | AF31: COL30 | AG31: COL31 | AH31: COL32 | AI31: COL33 | AJ31: COL34 | AK31: COL35 | AL31: COL36 | AM31: COL37 | AN31: COL38 | AO31: COL39 | AP31: COL40 | AQ31: COL41 | AR31: COL42 | AS31: COL43 | AT31: COL44 | CH31: 0 | CI31: 0
A32: 04025030 | B32: MATRONA /ÓN (MORB.GINECOLÓGICA) | C32: COL01 | D32: COL02 | E32: COL03 | F32: COL04 | G32: COL05 | H32: COL06 | I32: COL07 | J32: COL08 | K32: COL09 | L32: COL10 | M32: COL11 | N32: COL12 | O32: COL13 | P32: COL14 | Q32: COL15 | R32: COL16 | S32: COL17 | T32: COL18 | U32: COL19 | V32: COL20 | W32: COL21 | X32: COL22 | Y32: COL23 | Z32: COL24 | AA32: COL25 | AB32: COL26 | AC32: COL27 | AD32: COL28 | AE32: COL29 | AF32: COL30 | AG32: COL31 | AH32: COL32 | AI32: COL33 | AJ32: COL34 | AK32: COL35 | AL32: COL36 | AM32: COL37 | AN32: COL38 | AO32: COL39 | AP32: COL40 | AQ32: COL41 | AR32: COL42 | AS32: COL43 | AT32: COL44 | CH32: 0 | CI32: 0
A33: 04025040 | B33: MATRONA /ÓN (ITS) | C33: COL01 | D33: COL02 | E33: COL03 | F33: COL04 | G33: COL05 | H33: COL06 | I33: COL07 | J33: COL08 | K33: COL09 | L33: COL10 | M33: COL11 | N33: COL12 | O33: COL13 | P33: COL14 | Q33: COL15 | R33: COL16 | S33: COL17 | T33: COL18 | U33: COL19 | V33: COL20 | W33: COL21 | X33: COL22 | Y33: COL23 | Z33: COL24 | AA33: COL25 | AB33: COL26 | AC33: COL27 | AD33: COL28 | AE33: COL29 | AF33: COL30 | AG33: COL31 | AH33: COL32 | AI33: COL33 | AJ33: COL34 | AK33: COL35 | AL33: COL36 | AM33: COL37 | AN33: COL38 | AO33: COL39 | AP33: COL40 | AQ33: COL41 | AR33: COL42 | AS33: COL43 | AT33: COL44 | CH33: 0 | CI33: 0
A34: 04040200 | B34: MATRONA /ÓN (INFERTILIDAD) | C34: COL01 | D34: COL02 | E34: COL03 | F34: COL04 | G34: COL05 | H34: COL06 | I34: COL07 | J34: COL08 | K34: COL09 | L34: COL10 | M34: COL11 | N34: COL12 | O34: COL13 | P34: COL14 | Q34: COL15 | R34: COL16 | S34: COL17 | T34: COL18 | U34: COL19 | V34: COL20 | W34: COL21 | X34: COL22 | Y34: COL23 | Z34: COL24 | AA34: COL25 | AB34: COL26 | AC34: COL27 | AD34: COL28 | AE34: COL29 | AF34: COL30 | AG34: COL31 | AH34: COL32 | AI34: COL33 | AJ34: COL34 | AK34: COL35 | AL34: COL36 | AM34: COL37 | AN34: COL38 | AO34: COL39 | AP34: COL40 | AQ34: COL41 | AR34: COL42 | AS34: COL43 | AT34: COL44 | CH34: 0 | CI34: 0
A35: 04025050 | B35: MATRONA /ÓN (OTRAS CONSULTAS) | C35: COL01 | D35: COL02 | E35: COL03 | F35: COL04 | G35: COL05 | H35: COL06 | I35: COL07 | J35: COL08 | K35: COL09 | L35: COL10 | M35: COL11 | N35: COL12 | O35: COL13 | P35: COL14 | Q35: COL15 | R35: COL16 | S35: COL17 | T35: COL18 | U35: COL19 | V35: COL20 | W35: COL21 | X35: COL22 | Y35: COL23 | Z35: COL24 | AA35: COL25 | AB35: COL26 | AC35: COL27 | AD35: COL28 | AE35: COL29 | AF35: COL30 | AG35: COL31 | AH35: COL32 | AI35: COL33 | AJ35: COL34 | AK35: COL35 | AL35: COL36 | AM35: COL37 | AN35: COL38 | AO35: COL39 | AP35: COL40 | AQ35: COL41 | AR35: COL42 | AS35: COL43 | AT35: COL44 | CH35: 0 | CI35: 0
A36: 04050100 | B36: MATRONA /ÓN (SALUD SEXUAL) | C36: COL01 | D36: COL02 | E36: COL03 | F36: COL04 | G36: COL05 | H36: COL06 | I36: COL07 | J36: COL08 | K36: COL09 | L36: COL10 | M36: COL11 | N36: COL12 | O36: COL13 | P36: COL14 | Q36: COL15 | R36: COL16 | S36: COL17 | T36: COL18 | U36: COL19 | V36: COL20 | W36: COL21 | X36: COL22 | Y36: COL23 | Z36: COL24 | AA36: COL25 | AB36: COL26 | AC36: COL27 | AD36: COL28 | AE36: COL29 | AF36: COL30 | AG36: COL31 | AH36: COL32 | AI36: COL33 | AJ36: COL34 | AK36: COL35 | AL36: COL36 | AM36: COL37 | AN36: COL38 | AO36: COL39 | AP36: COL40 | AQ36: COL41 | AR36: COL42 | AS36: COL43 | AT36: COL44 | CH36: 0 | CI36: 0
A37: 03020604 | B37: NUTRICIONISTA (OTRAS CONSULTAS) | C37: COL01 | D37: COL02 | E37: COL03 | F37: COL04 | G37: COL05 | H37: COL06 | I37: COL07 | J37: COL08 | K37: COL09 | L37: COL10 | M37: COL11 | N37: COL12 | O37: COL13 | P37: COL14 | Q37: COL15 | R37: COL16 | S37: COL17 | T37: COL18 | U37: COL19 | V37: COL20 | W37: COL21 | X37: COL22 | Y37: COL23 | Z37: COL24 | AA37: COL25 | AB37: COL26 | AC37: COL27 | AD37: COL28 | AE37: COL29 | AF37: COL30 | AG37: COL31 | AH37: COL32 | AI37: COL33 | AJ37: COL34 | AK37: COL35 | AL37: COL36 | AM37: COL37 | AN37: COL38 | AO37: COL39 | AP37: COL40 | AQ37: COL41 | AR37: COL42 | AS37: COL43 | AT37: COL44 | CH37: 0 | CI37: 0
A38: 04050110 | B38: NUTRICIONISTA MAULNUTRICIÓN POR EXCESO | C38: COL01 | D38: COL02 | E38: COL03 | F38: COL04 | G38: COL05 | H38: COL06 | I38: COL07 | J38: COL08 | K38: COL09 | L38: COL10 | M38: COL11 | N38: COL12 | O38: COL13 | P38: COL14 | Q38: COL15 | R38: COL16 | S38: COL17 | T38: COL18 | U38: COL19 | V38: COL20 | W38: COL21 | X38: COL22 | Y38: COL23 | Z38: COL24 | AA38: COL25 | AB38: COL26 | AC38: COL27 | AD38: COL28 | AE38: COL29 | AF38: COL30 | AG38: COL31 | AH38: COL32 | AI38: COL33 | AJ38: COL34 | AK38: COL35 | AL38: COL36 | AM38: COL37 | AN38: COL38 | AO38: COL39 | AP38: COL40 | AQ38: COL41 | AR38: COL42 | AS38: COL43 | AT38: COL44 | CH38: 0 | CI38: 0
A39: 04050120 | B39: NUTRICIONISTA MALNUTRICIÓN POR DÉFICIT | C39: COL01 | D39: COL02 | E39: COL03 | F39: COL04 | G39: COL05 | H39: COL06 | I39: COL07 | J39: COL08 | K39: COL09 | L39: COL10 | M39: COL11 | N39: COL12 | O39: COL13 | P39: COL14 | Q39: COL15 | R39: COL16 | S39: COL17 | T39: COL18 | U39: COL19 | V39: COL20 | W39: COL21 | X39: COL22 | Y39: COL23 | Z39: COL24 | AA39: COL25 | AB39: COL26 | AC39: COL27 | AD39: COL28 | AE39: COL29 | AF39: COL30 | AG39: COL31 | AH39: COL32 | AI39: COL33 | AJ39: COL34 | AK39: COL35 | AL39: COL36 | AM39: COL37 | AN39: COL38 | AO39: COL39 | AP39: COL40 | AQ39: COL41 | AR39: COL42 | AS39: COL43 | AT39: COL44 | CH39: 0 | CI39: 0
A40: 03020908 | B40: PSICÓLOGO/A | C40: COL01 | D40: COL02 | E40: COL03 | F40: COL04 | G40: COL05 | H40: COL06 | I40: COL07 | J40: COL08 | K40: COL09 | L40: COL10 | M40: COL11 | N40: COL12 | O40: COL13 | P40: COL14 | Q40: COL15 | R40: COL16 | S40: COL17 | T40: COL18 | U40: COL19 | V40: COL20 | W40: COL21 | X40: COL22 | Y40: COL23 | Z40: COL24 | AA40: COL25 | AB40: COL26 | AC40: COL27 | AD40: COL28 | AE40: COL29 | AF40: COL30 | AG40: COL31 | AH40: COL32 | AI40: COL33 | AJ40: COL34 | AK40: COL35 | AL40: COL36 | AM40: COL37 | AN40: COL38 | AO40: COL39 | AP40: COL40 | AQ40: COL41 | AR40: COL42 | AS40: COL43 | AT40: COL44 | CH40: 0 | CI40: 0
A41: 03030250 | B41: FONOAUDIÓLOGO | C41: COL01 | D41: COL02 | E41: COL03 | F41: COL04 | G41: COL05 | H41: COL06 | I41: COL07 | J41: COL08 | K41: COL09 | L41: COL10 | M41: COL11 | N41: COL12 | O41: COL13 | P41: COL14 | Q41: COL15 | R41: COL16 | S41: COL17 | T41: COL18 | U41: COL19 | V41: COL20 | W41: COL21 | X41: COL22 | Y41: COL23 | Z41: COL24 | AA41: COL25 | AB41: COL26 | AC41: COL27 | AD41: COL28 | AE41: COL29 | AF41: COL30 | AG41: COL31 | AH41: COL32 | AI41: COL33 | AJ41: COL34 | AK41: COL35 | AL41: COL36 | AM41: COL37 | AN41: COL38 | AO41: COL39 | AP41: COL40 | AQ41: COL41 | AR41: COL42 | AS41: COL43 | AT41: COL44 | CH41: 0 | CI41: 0
A42: 03030270 | B42: TERAPEUTA OCUPACIONAL | C42: COL01 | D42: COL02 | E42: COL03 | F42: COL04 | G42: COL05 | H42: COL06 | I42: COL07 | J42: COL08 | K42: COL09 | L42: COL10 | M42: COL11 | N42: COL12 | O42: COL13 | P42: COL14 | Q42: COL15 | R42: COL16 | S42: COL17 | T42: COL18 | U42: COL19 | V42: COL20 | W42: COL21 | X42: COL22 | Y42: COL23 | Z42: COL24 | AA42: COL25 | AB42: COL26 | AC42: COL27 | AD42: COL28 | AE42: COL29 | AF42: COL30 | AG42: COL31 | AH42: COL32 | AI42: COL33 | AJ42: COL34 | AK42: COL35 | AL42: COL36 | AM42: COL37 | AN42: COL38 | AO42: COL39 | AP42: COL40 | AQ42: COL41 | AR42: COL42 | AS42: COL43 | AT42: COL44 | CH42: 0 | CI42: 0
... A44: 03020806 | B44: ASISTENTE SOCIAL | C44: COL01 | D44: COL02 | E44: COL03 | F44: COL04 | G44: COL05 | H44: COL06 | I44: COL07 | J44: COL08 | K44: COL09 | L44: COL10 | M44: COL11 | N44: COL12 | O44: COL13 | P44: COL14 | Q44: COL15 | R44: COL16 | S44: COL17 | T44: COL18 | U44: COL19 | V44: COL20 | W44: COL21 | X44: COL22 | Y44: COL23 | Z44: COL24 | AA44: COL25 | AB44: COL26 | AC44: COL27 | AD44: COL28 | AE44: COL29 | AF44: COL30 | AG44: COL31 | AH44: COL32 | AI44: COL33 | AJ44: COL34 | AK44: COL35 | AL44: COL36 | AM44: COL37 | AN44: COL38 | AO44: COL39 | AP44: COL40 | AQ44: COL41 | AR44: COL42 | AS44: COL43 | AT44: COL44 | CH44: 0 | CI44: 0
B45: SECCIÓN C: CONSULTAS ANTICONCEPCIÓN DE EMERGENCIA (Incluidas en Sección A y B, respectivamente.)
B46: PROFESIONAL | C46: TOTAL | D46: CON ENTREGA ANTICONCEPCIÓN EMERGENCIA | H46: SIN ENTREGA ANTICONCEPCIÓN EMERGENCIA
D47: 10 a 14 años | E47: 15 a 19 años | F47: 20 a 24 años | G47: 25 y más años | H47: 10 a 14 años | I47: 15 a 19 años | J47: 20 a 24 años | K47: 25 y más años
A48: 01080003 | B48: MÉDICO | C48: COL01 | D48: COL02 | E48: COL03 | F48: COL04 | G48: COL05 | H48: COL06 | I48: COL07 | J48: COL08 | K48: COL09
A49: 01080004 | B49: MATRONA /ÓN | C49: COL01 | D49: COL02 | E49: COL03 | F49: COL04 | G49: COL05 | H49: COL06 | I49: COL07 | J49: COL08 | K49: COL09
B50: SECCIÓN D: CONSULTAS EN HORARIO CONTINUADO (Incluidas en las consultas de morbilidad de sección A y B)
B51: TIPO JORNADA | C51: TOTAL | F51: POR DE EDAD (en años) | X51: Beneficiarios
F52: Menor de 1 | G52: 1 a 4 | H52: 5 a 9 | I52: 10 a 14 | J52: 15 a 19 | K52: 20 a 24 | L52: 25 - 29 | M52: 30 - 34 | N52: 35 - 39 | O52: 40 - 44 | P52: 45 - 49 | Q52: 50 - 54 | R52: 55 - 59 | S52: 60 - 64 | T52: 65 - 69 | U52: 70 - 74 | V52: 75 - 79 | W52: 80 y mas
C53: Ambos Sexos | D53: Hombres | E53: Mujeres
B54: HORARIO CONTINUADO | C54: =SUM(C55:C56) -> 0 | D54: =SUM(D55:D56) -> 0 | E54: =SUM(E55:E56) -> 0 | F54: =SUM(F55:F56) -> 0 | G54: =SUM(G55:G56) -> 0 | H54: =SUM(H55:H56) -> 0 | I54: =SUM(I55:I56) -> 0 | J54: =SUM(J55:J56) -> 0 | ... X54: =SUM(X55:X56) -> 0
A55: 04021101 | B55: MÉDICO | C55: COL01 | D55: COL02 | E55: COL03 | F55: COL04 | G55: COL05 | H55: COL06 | I55: COL07 | J55: COL08 | K55: COL09 | L55: COL10 | M55: COL11 | N55: COL12 | O55: COL13 | P55: COL14 | Q55: COL15 | R55: COL16 | S55: COL17 | T55: COL18 | U55: COL19 | V55: COL20 | W55: COL21 | X55: COL22 | CH55: 0 | CI55: 0 | CJ55: 0
A56: 04021103 | B56: OTROS PROFESIONALES | C56: COL01 | D56: COL02 | E56: COL03 | F56: COL04 | G56: COL05 | H56: COL06 | I56: COL07 | J56: COL08 | K56: COL09 | L56: COL10 | M56: COL11 | N56: COL12 | O56: COL13 | P56: COL14 | Q56: COL15 | R56: COL16 | S56: COL17 | T56: COL18 | U56: COL19 | V56: COL20 | W56: COL21 | X56: COL22 | CH56: 0 | CI56: 0 | CJ56: 0
B57: SÁBADO, DOMINGO o FESTIVO | C57: =SUM(C58:C59) -> 0 | D57: =SUM(D58:D59) -> 0 | E57: =SUM(E58:E59) -> 0 | F57: =SUM(F58:F59) -> 0 | G57: =SUM(G58:G59) -> 0 | H57: =SUM(H58:H59) -> 0 | I57: =SUM(I58:I59) -> 0 | J57: =SUM(J58:J59) -> 0 | ... X57: =SUM(X58:X59) -> 0
A58: 04021102 | B58: MÉDICO | C58: COL01 | D58: COL02 | E58: COL03 | F58: COL04 | G58: COL05 | H58: COL06 | I58: COL07 | J58: COL08 | K58: COL09 | L58: COL10 | M58: COL11 | N58: COL12 | O58: COL13 | P58: COL14 | Q58: COL15 | R58: COL16 | S58: COL17 | T58: COL18 | U58: COL19 | V58: COL20 | W58: COL21 | X58: COL22 | CH58: 0 | CI58: 0 | CJ58: 0
A59: 04021104 | B59: OTROS PROFESIONALES | C59: COL01 | D59: COL02 | E59: COL03 | F59: COL04 | G59: COL05 | H59: COL06 | I59: COL07 | J59: COL08 | K59: COL09 | L59: COL10 | M59: COL11 | N59: COL12 | O59: COL13 | P59: COL14 | Q59: COL15 | R59: COL16 | S59: COL17 | T59: COL18 | U59: COL19 | V59: COL20 | W59: COL21 | X59: COL22 | CH59: 0 | CI59: 0 | CJ59: 0
B60: SECCIÓN E: CONSULTAS DE MORBILIDAD SOLICITADAS Y RECHAZADAS DENTRO DE LAS 48 HORAS DE SOLICITADA LA ATENCIÓN
B61: TIPO JORNADA | C61: MENOR 5 AÑOS | E61: 65 Y MÁS AÑOS | G61: EMBARAZADAS
C62: TOTAL ATENCIÓN SOLICITADA | D62: RECHAZOS | E62: TOTAL ATENCIÓN SOLICITADA | F62: RECHAZOS | G62: TOTAL ATENCIÓN SOLICITADA | H62: RECHAZOS
A63: 04040300 | B63: HORARIO NORMAL | C63: COL01 | D63: COL02 | E63: COL03 | F63: COL04 | G63: COL05 | H63: COL06 | CH63: =IF(C63<D63,1,0) -> 1 | CI63: =IF(E63<F63,1,0) -> 1 | CJ63: =IF(G63<H63,1,0) -> 1
A64: 02021707 | B64: HORARIO CONTINUADO (Vespertina, Sábado, Domingo o Festivos) | C64: COL01 | D64: COL02 | E64: COL03 | F64: COL04 | G64: COL05 | H64: COL06 | CH64: =IF(C64<D64,1,0) -> 1 | CI64: =IF(E64<F64,1,0) -> 1 | CJ64: =IF(G64<H64,1,0) -> 1
B65: SECCIÓN F: CONSULTA ABREVIADA
B66: PROFESIONAL | C66: TOTAL
A67: 03030290 | B67: MÉDICO | C67: COL01
A68: 04040400 | B68: MATRONA | C68: COL01
B69: SECCIÓN G: ATENCIONES DE MEDICINA INDÍGENA ASOCIADA AL PROGRAMA ESPECIAL DE SALUD Y PUEBLOS ORIGINARIOS
B70: COMPONENTE | C70: TOTAL | D70: PUEBLOS ORIGINARIOS | E70: PUEBLOS NO ORIGINARIOS
A72: 04025070 | B72: ATENCIONES POR AGENTE MEDICINA INDIGENA | C72: COL01 | D72: COL02 | E72: COL03
B73: SECCIÓN H: INTERVENCIÓN INDIVIDUAL DEL USUARIO EN PROGRAMA ELIGE VIDA SANA
B74: PROFESIONAL | C74: PRESTACIÓN | D74: TOTAL | G74: POR DE EDAD (en años) | AK74: Gestantes | AL74: Post Parto
G75: Menor de 2 años | I75: 2 a 4 | K75: 5 a 9 | M75: 10 a 14 | O75: 15 a 18 | Q75: 19 | S75: 20 a 24 | U75: 25 - 29 | W75: 30 - 34 | Y75: 35 - 39 | AA75: 40 - 44 | AC75: 45 - 49 | AE75: 50 - 54 | AG75: 55 - 59 | AI75: 60 - 64
D76: Ambos Sexos | E76: Hombres | F76: Mujeres | G76: Hombres | H76: Mujeres | I76: Hombres | J76: Mujeres | K76: Hombres | L76: Mujeres | M76: Hombres | N76: Mujeres | O76: Hombres | P76: Mujeres | Q76: Hombres | R76: Mujeres | S76: Hombres | T76: Mujeres | U76: Hombres | V76: Mujeres | W76: Hombres | X76: Mujeres | Y76: Hombres | Z76: Mujeres | AA76: Hombres | AB76: Mujeres | AC76: Hombres | AD76: Mujeres | AE76: Hombres | AF76: Mujeres | AG76: Hombres | AH76: Mujeres | AI76: Hombres | AJ76: Mujeres
A77: 04050130 | B77: PROFESIONAL DE LA ACTIVIDAD FISICA | C77: EVALUACIÓN | D77: COL01 | E77: COL02 | F77: COL03 | G77: COL04 | H77: COL05 | I77: COL06 | J77: COL07 | K77: COL08 | L77: COL09 | M77: COL10 | N77: COL11 | O77: COL12 | P77: COL13 | Q77: COL14 | R77: COL15 | S77: COL16 | T77: COL17 | U77: COL18 | V77: COL19 | W77: COL20 | X77: COL21 | Y77: COL22 | Z77: COL23 | AA77: COL24 | AB77: COL25 | AC77: COL26 | AD77: COL27 | AE77: COL28 | AF77: COL29 | AG77: COL30 | AH77: COL31 | AI77: COL32 | AJ77: COL33 | AK77: COL34 | AL77: COL35 | CH77: 0 | CI77: 0
A78: 04040402 | B78: NUTRICIONISTA | C78: CONSULTA NUTRICIONAL | D78: COL01 | E78: COL02 | F78: COL03 | G78: COL04 | H78: COL05 | I78: COL06 | J78: COL07 | K78: COL08 | L78: COL09 | M78: COL10 | N78: COL11 | O78: COL12 | P78: COL13 | Q78: COL14 | R78: COL15 | S78: COL16 | T78: COL17 | U78: COL18 | V78: COL19 | W78: COL20 | X78: COL21 | Y78: COL22 | Z78: COL23 | AA78: COL24 | AB78: COL25 | AC78: COL26 | AD78: COL27 | AE78: COL28 | AF78: COL29 | AG78: COL30 | AH78: COL31 | AI78: COL32 | AJ78: COL33 | AK78: COL34 | AL78: COL35 | CH78: 0 | CI78: 0
A79: 04025073 | C79: CONSULTA NUTRICIONAL DE SEGUIMIENTO | D79: COL01 | E79: COL02 | F79: COL03 | G79: COL04 | H79: COL05 | I79: COL06 | J79: COL07 | K79: COL08 | L79: COL09 | M79: COL10 | N79: COL11 | O79: COL12 | P79: COL13 | Q79: COL14 | R79: COL15 | S79: COL16 | T79: COL17 | U79: COL18 | V79: COL19 | W79: COL20 | X79: COL21 | Y79: COL22 | Z79: COL23 | AA79: COL24 | AB79: COL25 | AC79: COL26 | AD79: COL27 | AE79: COL28 | AF79: COL29 | AG79: COL30 | AH79: COL31 | AI79: COL32 | AJ79: COL33 | AK79: COL34 | AL79: COL35 | CH79: 0 | CI79: 0
A80: 04040407 | B80: PSICÓLOGO/A | C80: CONSULTA | D80: COL01 | E80: COL02 | F80: COL03 | G80: COL04 | H80: COL05 | I80: COL06 | J80: COL07 | K80: COL08 | L80: COL09 | M80: COL10 | N80: COL11 | O80: COL12 | P80: COL13 | Q80: COL14 | R80: COL15 | S80: COL16 | T80: COL17 | U80: COL18 | V80: COL19 | W80: COL20 | X80: COL21 | Y80: COL22 | Z80: COL23 | AA80: COL24 | AB80: COL25 | AC80: COL26 | AD80: COL27 | AE80: COL28 | AF80: COL29 | AG80: COL30 | AH80: COL31 | AI80: COL32 | AJ80: COL33 | AK80: COL34 | AL80: COL35 | CH80: 0 | CI80: 0
B81: SECCIÓN I: SERVICIOS FARMACÉUTICOS
B82: COMPONENTE | C82: TOTAL | D82: ATENCIÓN ABIERTA | E82: ATENCIÓN CERRADA
B84: ATENCIÓN FARMACÉUTICA
A85: 04050140 | B85: REVISIÓN DE LA MEDICACIÓN SIN ENTREVISTA | C85: COL01 | D85: COL02 | E85: COL03
A86: 04050150 | B86: REVISIÓN DE LA MEDICACIÓN CON ENTREVISTA | C86: COL01 | D86: COL02 | E86: COL03
A87: 04050160 | B87: CONCILIACIÓN FARMACÉUTICA | C87: COL01 | D87: COL02 | E87: COL03
A88: 04050170 | B88: EDUCACIÓN FARMACÉUTICA | C88: COL01 | D88: COL02 | E88: COL03
A89: 04050180 | B89: SEGUIMIENTO FARMACOTERAPÉUTICO | C89: COL01 | D89: COL02 | E89: COL03
B90: FARMACOVIGILANCIA
A91: 04040409 | B91: REPORTE REACCIÓN ADVERSA A MEDICAMENTOS | C91: COL01 | D91: COL02 | E91: COL03
A92: 04050190 | B92: REPORTE FALLA DE CALIDAD | C92: COL01 | D92: COL02 | E92: COL03
A93: 04050200 | B93: REPORTE DE EVENTOS ADVERSOS ASOCIADOS A MEDICAMENTOS | C93: COL01 | D93: COL02 | E93: COL03
B94: SECCIÓN J: DESPACHO DE RECETAS DE PACIENTES AMBULATORIOS
B95: TIPO DE RECETA | C95: RECETAS DESPACHADAS | E95: PRESCRIPCIONES | G95: RECETAS DESPACHADAS CON OPORTUNIDAD (Entregado el mismo día) | H95: RECETAS DESPACHADAS A PACIENTES DEL PROGRAMA DE SALUD CARDIOVASCULAR | J95: PRESCRIPCIONES A PACIENTES DEL PROGRAMA DE SALUD CARDIOVASCULAR
C97: DESPACHO TOTAL | D97: DESPACHO PARCIAL | E97: EMITIDAS | F97: RECHAZADAS | H97: DESPACHO TOTAL | I97: DESPACHO PARCIAL | J97: EMITIDAS | K97: RECHA- ZADAS
A98: 04040412 | B98: CRÓNICA | C98: COL01 | D98: COL02 | E98: COL03 | F98: COL04 | G98: COL05 | H98: COL06 | I98: COL07 | J98: COL08 | K98: COL09
A99: 04040413 | B99: MORBILIDAD | C99: COL01 | D99: COL02 | E99: COL03 | F99: COL04 | G99: COL05 | H99: COL06 | I99: COL07 | J99: COL08 | K99: COL09
A100: 04050210 | B100: BAJO CONTROL LEGAL | C100: COL01 | D100: COL02 | E100: COL03 | F100: COL04 | G100: COL05 | H100: COL06 | I100: COL07 | J100: COL08 | K100: COL09 | CH100: 0 | CI100: 0 | CJ100: 0
B101: TOTAL | C101: =SUM(C98:C100) -> 0 | D101: =SUM(D98:D100) -> 0 | E101: =SUM(E98:E100) -> 0 | F101: =SUM(F98:F100) -> 0 | G101: =SUM(G98:G100) -> 0 | H101: =SUM(H98:H100) -> 0 | I101: =SUM(I98:I100) -> 0 | J101: =SUM(J98:J100) -> 0 | K101: =SUM(K98:K100) -> 0 | CH101: 0 | CI101: 0 | CJ101: 0
B102: SECCIÓN K: RONDAS POR TIPO Y PROFESIONAL | CH102: 0 | CI102: 0 | CJ102: 0
B103: TIPO DE RONDA | C103: Nº Rondas | D103: TOTAL DE PROFESIONALES QUE PARTICIPARON EN RONDAS, SEGÚN TIPO DE PROFESIONAL | M103: Compra de Servicio - Nº Traslados profesionales en Ronda
D104: Médico | E104: Dentista | F104: Enfermera | G104: Matrona | H104: Nutricionista | I104: Tec. Paramed. | J104: Asis. Soc | K104: Psicólogo | L104: Otros
A105: 04040414 | B105: TERRESTRE | C105: COL01 | D105: COL02 | E105: COL03 | F105: COL04 | G105: COL05 | H105: COL06 | I105: COL07 | J105: COL08 | K105: COL09 | L105: COL10 | M105: COL11
A106: 04040415 | B106: AÉREA | C106: COL01 | D106: COL02 | E106: COL03 | F106: COL04 | G106: COL05 | H106: COL06 | I106: COL07 | J106: COL08 | K106: COL09 | L106: COL10 | M106: COL11
...

Sheet A05
B1: SERVICIO DE SALUD
B2: =CONCATENATE("COMUNA: ",NOMBRE!B2," - ","( ",NOMBRE!C2,NOMBRE!D2,NOMBRE!E2,NOMBRE!F2,NOMBRE!G2," )") -> COMUNA: - ( )
B3: =CONCATENATE("ESTABLECIMIENTO/ESTRATEGIA: ",NOMBRE!B3," - ","( ",NOMBRE!C3,NOMBRE!D3,NOMBRE!E3,NOMBRE!F3,NOMBRE!G3,NOMBRE!H3," )") -> ESTABLECIMIENTO/ESTRATEGIA: - ( )
B4: =CONCATENATE("MES: ",NOMBRE!B6," - ","( ",NOMBRE!C6,NOMBRE!D6," )") -> MES: - ( )
B5: =CONCATENATE("AÑO: ",NOMBRE!B7) -> AÑO: 2020
B6: REM-A05. INGRESOS Y EGRESOS POR CONDICIÓN Y PROBLEMAS DE SALUD
B8: SECCIÓN A: INGRESOS DE GESTANTES A PROGRAMA PRENATAL
A9: CODIGO DICCIONARIO | B9: CONDICIÓN | D9: TOTAL | E9: POR DE EDAD (en años) | O9: Victima de violencia de genero | P9: Pueblos Originarios | Q9: Migrantes
E10: Menor de 15 | F10: 15 - 19 | G10: 20 - 24 | H10: 25 - 29 | I10: 30 - 34 | J10: 35 - 39 | K10: 40 - 44 | L10: 45 - 49 | M10: 50 - 54 | N10: 55 y más
A11: 01080008 | B11: GESTANTES INGRESADAS | D11: COL01 | E11: COL02 | F11: COL03 | G11: COL04 | H11: COL05 | I11: COL06 | J11: COL07 | K11: COL08 | L11: COL09 | M11: COL10 | N11: COL11 | O11: COL12 | P11: COL13 | Q11: COL14 | R11: =CB11&CC11&CD11&CE11 -> * El número de víctima de Violencia de Género NO DEBE ser diferente al Total. * Pueblo Originario y/o Migrantes NO DEBEN ser Mayor al Total. | CB11: =IF(CI11=1,"* El número de víctima de Violencia de Género NO DEBE ser diferente al Total. ","") -> * El número de víctima de Violencia de Género NO DEBE ser diferente al Total. | CC11: =IF(AND(D11<>0,OR(P11="",Q11="")),"* No olvide digitar los campos Pueblo Originario y/o Migrantes (Digite CEROS si no tiene). ","") | CD11: =IF(CK11=1,"* Pueblo Originario y/o Migrantes NO DEBEN ser Mayor al Total. ","") -> * Pueblo Originario y/o Migrantes NO DEBEN ser Mayor al Total. | CE11: =IF(CL11=1,"* Total Gestantes Ingresadas a control prenatal debe ser Mayor o Igual que el Total de Evaluaciones a Gestantes de REM A03 Sección B2. ","") | CI11: =IF(D11<O11,1,0) -> 1 | CK11: =IF(OR(D11<P11,D11<Q11),1,0) -> 1 | CL11: =IF(D11<'A03'!D75,1,0) -> 0
A12: 01080010 | B12: PRIMIGESTAS INGRESADAS | D12: COL01 | E12: COL02 | F12: COL03 | G12: COL04 | H12: COL05 | I12: COL06 | J12: COL07 | K12: COL08 | L12: COL09 | M12: COL10 | N12: COL11 | O12: COL12 | P12: COL13 | Q12: COL14 | R12: =CB12&CC12&CD12&CE12 -> * El número de víctima de Violencia de Género NO DEBE ser diferente al Total. * Pueblo Originario y/o Migrantes NO DEBEN ser Mayor al Total. | CB12: =IF(CI12=1,"* El número de víctima de Violencia de Género NO DEBE ser diferente al Total. ","") -> * El número de víctima de Violencia de Género NO DEBE ser diferente al Total. | CC12: =IF(AND(D12<>0,OR(P12="",Q12="")),"* No olvide digitar los campos Pueblo Originario y/o Migrantes (Digite CEROS si no tiene). ","") | CD12: =IF(CK12=1,"* Pueblo Originario y/o Migrantes NO DEBEN ser Mayor al Total. ","") -> * Pueblo Originario y/o Migrantes NO DEBEN ser Mayor al Total. | CE12: =IF(CL12=1,"* Total Gestantes debe ser Mayor o Igual a "&B12&".","") | CI12: =IF(D12<O12,1,0) -> 1 | CK12: =IF(OR(D12<P12,D12<Q12),1,0) -> 1 | CL12: =IF($D$11<D12,1,0) -> 0
A13: 01080009 | B13: GESTANTES INGRESADAS ANTES DE LAS 14 SEMANAS | D13: COL01 | E13: COL02 | F13: COL03 | G13: COL04 | H13: COL05 | I13: COL06 | J13: COL07 | K13: COL08 | L13: COL09 | M13: COL10 | N13: COL11 | O13: COL12 | P13: COL13 | Q13: COL14 | R13: =CB13&CC13&CD13&CE13 -> * El número de víctima de Violencia de Género NO DEBE ser diferente al Total. * Pueblo Originario y/o Migrantes NO DEBEN ser Mayor al Total. | CB13: =IF(CI13=1,"* El número de víctima de Violencia de Género NO DEBE ser diferente al Total. ","") -> * El número de víctima de Violencia de Género NO DEBE ser diferente al Total. | CC13: =IF(AND(D13<>0,OR(P13="",Q13="")),"* No olvide digitar los campos Pueblo Originario y/o Migrantes (Digite CEROS si no tiene). ","") | CD13: =IF(CK13=1,"* Pueblo Originario y/o Migrantes NO DEBEN ser Mayor al Total. ","") -> * Pueblo Originario y/o Migrantes NO DEBEN ser Mayor al Total. | CE13: =IF(CL13=1,"* Total Gestantes debe ser Mayor o Igual a "&B13&".","") | CI13: =IF(D13<O13,1,0) -> 1 | CK13: =IF(OR(D13<P13,D13<Q13),1,0) -> 1 | CL13: =IF($D$11<D13,1,0) -> 0
A14: 01090050 | B14: GESTANTES CON EMBARAZO NO PLANIFICADO | D14: COL01 | E14: COL02 | F14: COL03 | G14: COL04 | H14: COL05 | I14: COL06 | J14: COL07 | K14: COL08 | L14: COL09 | M14: COL10 | N14: COL11 | O14: COL12 | P14: COL13 | Q14: COL14 | R14: =CB14&CC14&CD14&CE14 -> * El número de víctima de Violencia de Género NO DEBE ser diferente al Total. * Pueblo Originario y/o Migrantes NO DEBEN ser Mayor al Total. | CB14: =IF(CI14=1,"* El número de víctima de Violencia de Género NO DEBE ser diferente al Total. ","") -> * El número de víctima de Violencia de Género NO DEBE ser diferente al Total. | CC14: =IF(AND(D14<>0,OR(P14="",Q14="")),"* No olvide digitar los campos Pueblo Originario y/o Migrantes (Digite CEROS si no tiene). ","") | CD14: =IF(CK14=1,"* Pueblo Originario y/o Migrantes NO DEBEN ser Mayor al Total. ","") -> * Pueblo Originario y/o Migrantes NO DEBEN ser Mayor al Total. | CE14: =IF(CL14=1,"* Total Gestantes debe ser Mayor o Igual a "&B14&".","") | CI14: =IF(D14<O14,1,0) -> 1 | CK14: =IF(OR(D14<P14,D14<Q14),1,0) -> 1 | CL14: =IF($D$11<D14,1,0) -> 0
A15: 05050100 | B15: GESTANTES CON EXAMEN DE CHAGAS INFORMADO | D15: COL01 | E15: COL02 | F15: COL03 | G15: COL04 | H15: COL05 | I15: COL06 | J15: COL07 | K15: COL08 | L15: COL09 | M15: COL10 | N15: COL11 | O15: COL12 | P15: COL13 | Q15: COL14 | R15: =CB15&CC15&CD15&CE15 -> * El número de víctima de Violencia de Género NO DEBE ser diferente al Total. * Pueblo Originario y/o Migrantes NO DEBEN ser Mayor al Total. | CB15: =IF(CI15=1,"* El número de víctima de Violencia de Género NO DEBE ser diferente al Total. ","") -> * El número de víctima de Violencia de Género NO DEBE ser diferente al Total. | CC15: =IF(AND(D15<>0,OR(P15="",Q15="")),"* No olvide digitar los campos Pueblo Originario y/o Migrantes (Digite CEROS si no tiene). ","") | CD15: =IF(CK15=1,"* Pueblo Originario y/o Migrantes NO DEBEN ser Mayor al Total. ","") -> * Pueblo Originario y/o Migrantes NO DEBEN ser Mayor al Total. | CE15: =IF(CL15=1,"* Total Gestantes debe ser Mayor o Igual a "&B15&".","") | CI15: =IF(D15<O15,1,0) -> 1 | CK15: =IF(OR(D15<P15,D15<Q15),1,0) -> 1 | CL15: =IF($D$11<D15,1,0) -> 0
B16: SECCIÓN B: INGRESO DE GESTANTES CON PATOLOGÍA DE ALTO RIESGO OBSTÉTRICO A LA UNIDAD DE ARO (Nivel Secundario)
B17: PATOLOGÍA | D17: Nº de Ingreso a ARO | E17: Victima de violencia de género | F17: Pueblos Originarios | G17: Migrantes
A19: 05810010 | B19: Nº DE GESTANTES INGRESADAS | D19: COL01 | E19: COL02 | F19: COL03 | G19: COL04 | H19: =CB19&CC19&CD19&CE19 | CE19: =IF(AND(SUM(D20:D29)<>0,D19=0),"* No olvide registrar número de gestantes ingresadas. ","") | CH19: 0 | CJ19: 0
A20: 01090040 | B20: PREECLAMPSIA (PE) | D20: COL01 | E20: COL02 | F20: COL03 | G20: COL04 | H20: =CB20&CC20&CD20&CE20 | CH20: 0 | CJ20: 0
A21: 05810020 | B21: SÍNDROME HIPERTENSIVO DEL EMBARAZO (SHE) | D21: COL01 | E21: COL02 | F21: COL03 | G21: COL04 | H21: =CB21&CC21&CD21&CE21 | CH21: 0 | CJ21: 0
A22: 24100700 | B22: FACTORES DE RIESGO Y CONDICIONANTES DE PARTO PREMATURO | D22: COL01 | E22: COL02 | F22: COL03 | G22: COL04 | H22: =CB22&CC22&CD22&CE22 | CH22: 0 | CJ22: 0
A23: 01080017 | B23: RETARDO CRECIMIENTO INTRAUTERINO (RCIU) | D23: COL01 | E23: COL02 | F23: COL03 | G23: COL04 | H23: =CB23&CC23&CD23&CE23 | CH23: 0 | CJ23: 0
A24: 24090050 | B24: SÍFILIS | D24: COL01 | E24: COL02 | F24: COL03 | G24: COL04 | H24: =CB24&CC24&CD24&CE24 | CH24: 0 | CJ24: 0
A25: 24090060 | B25: VIH | D25: COL01 | E25: COL02 | F25: COL03 | G25: COL04 | H25: =CB25&CC25&CD25&CE25 | CH25: 0 | CJ25: 0
A26: 01080018 | B26: DIABETES | D26: COL01 | E26: COL02 | F26: COL03 | G26: COL04 | H26: =CB26&CC26&CD26&CE26 | CH26: 0 | CJ26: 0
A27: 01080019 | B27: CESÁREA ANTERIOR | D27: COL01 | E27: COL02 | F27: COL03 | G27: COL04 | H27: =CB27&CC27&CD27&CE27 | CH27: 0 | CJ27: 0
A28: 05810030 | B28: MALFORMACIÓN CONGÉNITA | D28: COL01 | E28: COL02 | F28: COL03 | G28: COL04 | H28: =CB28&CC28&CD28&CE28 | CH28: 0 | CJ28: 0
A29: 24100800 | B29: OTRAS PATOLOGÍAS DEL EMBARAZO | D29: COL01 | E29: COL02 | F29: COL03 | G29: COL04 | H29: =CB29&CC29&CD29&CE29 | CH29: 0 | CJ29: 0
B30: SECCIÓN C: INGRESOS A PROGRAMA DE REGULACIÓN DE FERTILIDAD Y SALUD SEXUAL.
B31: MÉTODOS | D31: TOTAL | E31: POR DE EDAD (en años)
E32: Menor de 15 | F32: 15 - 19 | G32: 20 - 24 | H32: 25 - 29 | I32: 30 - 34 | J32: 35 - 39 | K32: 40 - 44 | L32: 45 - 49 | M32: 50 - 54 | N32: 55 y más | O32: Espacios Amigables
B33: TOTAL REGULACIÓN DE FERTILIDAD | D33: =SUM(E33:N33) -> 0 | E33: =SUM(E34:E45,E48:E49,E52) -> 0 | F33: =SUM(F34:F45,F48:F49,F52) -> 0 | G33: =SUM(G34:G45,G48:G49,G52) -> 0 | H33: =SUM(H34:H45,H48:H49,H52) -> 0 | I33: =SUM(I34:I45,I48:I49,I52) -> 0 | J33: =SUM(J34:J45,J48:J49,J52) -> 0 | K33: =SUM(K34:K45,K48:K49,K52) -> 0 | L33: =SUM(L34:L45,L48:L49,L52) -> 0 | ... O33: =SUM(O34:O45,O48:O49,O52) -> 0
A34: 01080011 | B34: D . I . U T con Cobre | D34: COL01 | E34: COL02 | F34: COL03 | G34: COL04 | H34: COL05 | I34: COL06 | J34: COL07 | K34: COL08 | L34: COL09 | M34: COL10 | N34: COL11 | O34: COL12 | P34: =CB34 | CB34: =IF(CH34=1,"* No olvide digitar la columna Espacios Amigables (Digite Cero si no tiene). ","") | CH34: =IF(AND(D34<>0,O34=""),1,0) -> 0
A35: 05810443 | B35: D . I . U con Levonorgestrel | D35: COL01 | E35: COL02 | F35: COL03 | G35: COL04 | H35: COL05 | I35: COL06 | J35: COL07 | K35: COL08 | L35: COL09 | M35: COL10 | N35: COL11 | O35: COL12 | P35: =CB35 | CB35: =IF(CH35=1,"* No olvide digitar la columna Espacios Amigables (Digite Cero si no tiene). ","") | CH35: =IF(AND(D35<>0,O35=""),1,0) -> 0
A36: 01080021 | B36: HORMONAL | C36: Oral Combinado | D36: COL01 | E36: COL02 | F36: COL03 | G36: COL04 | H36: COL05 | I36: COL06 | J36: COL07 | K36: COL08 | L36: COL09 | M36: COL10 | N36: COL11 | O36: COL12 | P36: =CB36 | CB36: =IF(CH36=1,"* No olvide digitar la columna Espacios Amigables (Digite Cero si no tiene). ","") | CH36: =IF(AND(D36<>0,O36=""),1,0) -> 0
A37: 01080022 | C37: Oral Progestágeno | D37: COL01 | E37: COL02 | F37: COL03 | G37: COL04 | H37: COL05 | I37: COL06 | J37: COL07 | K37: COL08 | L37: COL09 | M37: COL10 | N37: COL11 | O37: COL12 | P37: =CB37 | CB37: =IF(CH37=1,"* No olvide digitar la columna Espacios Amigables (Digite Cero si no tiene). ","") | CH37: =IF(AND(D37<>0,O37=""),1,0) -> 0
A38: 01080023 | C38: Inyectable Combinado | D38: COL01 | E38: COL02 | F38: COL03 | G38: COL04 | H38: COL05 | I38: COL06 | J38: COL07 | K38: COL08 | L38: COL09 | M38: COL10 | N38: COL11 | O38: COL12 | P38: =CB38 | CB38: =IF(CH38=1,"* No olvide digitar la columna Espacios Amigables (Digite Cero si no tiene). ","") | CH38: =IF(AND(D38<>0,O38=""),1,0) -> 0
A39: 01090060 | C39: Inyectable Progestágeno | D39: COL01 | E39: COL02 | F39: COL03 | G39: COL04 | H39: COL05 | I39: COL06 | J39: COL07 | K39: COL08 | L39: COL09 | M39: COL10 | N39: COL11 | O39: COL12 | P39: =CB39 | CB39: =IF(CH39=1,"* No olvide digitar la columna Espacios Amigables (Digite Cero si no tiene). ","") | CH39: =IF(AND(D39<>0,O39=""),1,0) -> 0
A40: 05970038 | C40: Implante Etonogestrel (3 años) | D40: COL01 | E40: COL02 | F40: COL03 | G40: COL04 | H40: COL05 | I40: COL06 | J40: COL07 | K40: COL08 | L40: COL09 | M40: COL10 | N40: COL11 | O40: COL12 | P40: =CB40 | CB40: =IF(CH40=1,"* No olvide digitar la columna Espacios Amigables (Digite Cero si no tiene). ","") | CH40: =IF(AND(D40<>0,O40=""),1,0) -> 0
A41: 05970039 | C41: Implante Levonorgestrel (5 años) | D41: COL01 | E41: COL02 | F41: COL03 | G41: COL04 | H41: COL05 | I41: COL06 | J41: COL07 | K41: COL08 | L41: COL09 | M41: COL10 | N41: COL11 | O41: COL12 | P41: =CB41 | CB41: =IF(CH41=1,"* No olvide digitar la columna Espacios Amigables (Digite Cero si no tiene). ","") | CH41: =IF(AND(D41<>0,O41=""),1,0) -> 0
A42: 01080013 | B42: SÓLO PRESERVATIVO MAC | C42: Mujer | D42: COL01 | E42: COL02 | F42: COL03 | G42: COL04 | H42: COL05 | I42: COL06 | J42: COL07 | K42: COL08 | L42: COL09 | M42: COL10 | N42: COL11 | O42: COL12 | P42: =CB42 | CB42: =IF(CH42=1,"* No olvide digitar la columna Espacios Amigables (Digite Cero si no tiene). ","") | CH42: =IF(AND(D42<>0,O42=""),1,0) -> 0
A43: 01080014 | C43: Hombres | D43: COL01 | E43: COL02 | F43: COL03 | G43: COL04 | H43: COL05 | I43: COL06 | J43: COL07 | K43: COL08 | L43: COL09 | M43: COL10 | N43: COL11 | O43: COL12 | P43: =CB43 | CB43: =IF(CH43=1,"* No olvide digitar la columna Espacios Amigables (Digite Cero si no tiene). ","") | CH43: =IF(AND(D43<>0,O43=""),1,0) -> 0
A44: 05970040 | B44: ESTERILIZACIÓN QUIRÚRGICA | C44: Mujer | D44: COL01 | E44: COL02 | F44: COL03 | G44: COL04 | H44: COL05 | I44: COL06 | J44: COL07 | K44: COL08 | L44: COL09 | M44: COL10 | N44: COL11 | O44: COL12 | P44: =CB44 | CB44: =IF(CH44=1,"* No olvide digitar la columna Espacios Amigables (Digite Cero si no tiene). ","") | CH44: =IF(AND(D44<>0,O44=""),1,0) -> 0
A45: 05970041 | C45: Hombres | D45: COL01 | E45: COL02 | F45: COL03 | G45: COL04 | H45: COL05 | I45: COL06 | J45: COL07 | K45: COL08 | L45: COL09 | M45: COL10 | N45: COL11 | O45: COL12 | P45: =CB45 | CB45: =IF(CH45=1,"* No olvide digitar la columna Espacios Amigables (Digite Cero si no tiene). ","") | CH45: =IF(AND(D45<>0,O45=""),1,0) -> 0
A46: 05050100A | B46: Método de Regulación de Fertilidad más Preservativos | D46: COL01 | E46: COL02 | F46: COL03 | G46: COL04 | H46: COL05 | I46: COL06 | J46: COL07 | K46: COL08 | L46: COL09 | M46: COL10 | N46: COL11 | O46: COL12 | P46: =CB46 | CB46: =IF(CH46=1,"* No olvide digitar la columna Espacios Amigables (Digite Cero si no tiene). ","") | CH46: =IF(AND(D46<>0,O46=""),1,0) -> 0
A47: 05970042 | B47: Gestantes que reciben preservativo | D47: COL01 | E47: COL02 | F47: COL03 | G47: COL04 | H47: COL05 | I47: COL06 | J47: COL07 | K47: COL08 | L47: COL09 | M47: COL10 | N47: COL11 | O47: COL12 | P47: =CB47 | CB47: =IF(CH47=1,"* No olvide digitar la columna Espacios Amigables (Digite Cero si no tiene). ","") | CH47: =IF(AND(D47<>0,O47=""),1,0) -> 0
A48: 05970043 | B48: PRESERVATIVO/PRACTICA SEXUAL SEGURA | C48: Mujer | D48: COL01 | E48: COL02 | F48: COL03 | G48: COL04 | H48: COL05 | I48: COL06 | J48: COL07 | K48: COL08 | L48: COL09 | M48: COL10 | N48: COL11 | O48: COL12 | P48: =CB48 | CB48: =IF(CH48=1,"* No olvide digitar la columna Espacios Amigables (Digite Cero si no tiene). ","") | CH48: =IF(AND(D48<>0,O48=""),1,0) -> 0
A49: 05970044 | C49: Hombres | D49: COL01 | E49: COL02 | F49: COL03 | G49: COL04 | H49: COL05 | I49: COL06 | J49: COL07 | K49: COL08 | L49: COL09 | M49: COL10 | N49: COL11 | O49: COL12 | P49: =CB49 | CB49: =IF(CH49=1,"* No olvide digitar la columna Espacios Amigables (Digite Cero si no tiene). ","") | CH49: =IF(AND(D49<>0,O49=""),1,0) -> 0
A50: 05970045 | B50: LUBRICANTES | C50: Mujer | D50: COL01 | E50: COL02 | F50: COL03 | G50: COL04 | H50: COL05 | I50: COL06 | J50: COL07 | K50: COL08 | L50: COL09 | M50: COL10 | N50: COL11 | O50: COL12 | P50: =CB50 | CB50: =IF(CH50=1,"* No olvide digitar la columna Espacios Amigables (Digite Cero si no tiene). ","") | CH50: =IF(AND(D50<>0,O50=""),1,0) -> 0
A51: 05970046 | C51: Hombres | D51: COL01 | E51: COL02 | F51: COL03 | G51: COL04 | H51: COL05 | I51: COL06 | J51: COL07 | K51: COL08 | L51: COL09 | M51: COL10 | N51: COL11 | O51: COL12 | P51: =CB51 | CB51: =IF(CH51=1,"* No olvide digitar la columna Espacios Amigables (Digite Cero si no tiene). ","") | CH51: =IF(AND(D51<>0,O51=""),1,0) -> 0
A52: 05970047 | B52: CONDÓN FEMENINO | D52: COL01 | E52: COL02 | F52: COL03 | G52: COL04 | H52: COL05 | I52: COL06 | J52: COL07 | K52: COL08 | L52: COL09 | M52: COL10 | N52: COL11 | O52: COL12 | P52: =CB52 | CB52: =IF(CH52=1,"* No olvide digitar la columna Espacios Amigables (Digite Cero si no tiene). ","") | CH52: =IF(AND(D52<>0,O52=""),1,0) -> 0
B53: SECCIÓN D: INGRESOS A PROGRAMA CONTROL DE CLIMATERIO | CB53: =IF(AND(('A01'!$D18+'A01'!$D19+'A01'!$D20+'A01'!$D21+'A01'!$G31+'A01'!$G32+'A01'!$G33)<>0,E53=0,F53=""),"* Observacion : En A01 existen contoles no ingresados, Revisar. ","") -> #VALUE!
B54: CONCEPTO | C54: TOTAL | CH54: 0 | CI54: 0
A55: 01080090 | B55: INGRESOS | C55: COL01 | CH55: 0 | CI55: 0
B56: SECCIÓN E: INGRESOS A CONTROL DE SALUD DE RECIÉN NACIDOS | CH56: 0 | CI56: 0
B57: EDAD | D57: TOTAL | E57: NIÑOS | F57: NIÑAS | CH57: 0 | CI57: 0
A58: 05225100 | B58: MENORES DE 28 DÍAS | D58: COL01 | E58: COL02 | F58: COL03 | CB58: =IF(AND(('A01'!$D18+'A01'!$D19+'A01'!$D20+'A01'!$D21+'A01'!$G31+'A01'!$G32+'A01'!$G33)<>0,E58=0,F58=""),"* Observacion : En A01 existen controles no ingresados, Revisar. ","") -> #VALUE! | CH58: 0 | CI58: 0
B59: SECCIÓN F: INGRESOS Y EGRESOS A SALA DE ESTIMULACIÓN SERVICIO ITINERANTE Y ATENCIÓN DOMICILIARIA | CB59: =IF(AND(('A01'!$D18+'A01'!$D19+'A01'!$D20+'A01'!$D21+'A01'!$G31+'A01'!$G32+'A01'!$G33)<>0,E59=0,F59=""),"* Observacion : En A01 existen controles no ingresados, Revisar. ","") -> #VALUE!
B60: NIÑO / A (CON) | D60: TOTAL | G60: INGRESOS SALA DE ESTIMULACIÓN | S60: SERVICIO ITINERANTE EN CENTRO DE SALUD | U60: ATENCIÓN DOMICILIARIA | W60: EGRESOS Y RESULTADOS DE LA REEVALUACIÓN POST EGRESO
G61: Menor 7 meses | I61: 7 - 11 meses | K61: 12 - 17 meses | M61: 18 - 23 meses | O61: 24 - 47 meses | Q61: 48 - 59 meses | S61: 7 a 59 meses | U61: 7 a 59 meses | W61: MOTIVO EGRESO | Y61: INASISTENTE | Z61: RESULTADO DE REEVALUACIÓN
D62: Ambos Sexos | E62: Hombres | F62: Mujeres | G62: Hombres | H62: Mujeres | I62: Hombres | J62: Mujeres | K62: Hombres | L62: Mujeres | M62: Hombres | N62: Mujeres | O62: Hombres | P62: Mujeres | Q62: Hombres | R62: Mujeres | S62: Hombres | T62: Mujeres | U62: Hombres | V62: Mujeres | W62: Cumplimiento de tratamiento | X62: Otros | Z62: Recuperado | AA62: No Recuperado
A63: 06902601 | B63: NORMAL CON REZAGO | D63: COL01 | E63: COL02 | F63: COL03 | G63: COL04 | H63: COL05 | I63: COL06 | J63: COL07 | K63: COL08 | L63: COL09 | M63: COL10 | N63: COL11 | O63: COL12 | P63: COL13 | Q63: COL14 | R63: COL15 | S63: COL16 | T63: COL17 | U63: COL18 | V63: COL19 | W63: COL20 | X63: COL21 | Y63: COL22 | Z63: COL23 | AA63: COL24 | CH63: 0 | CI63: 0
A64: 06902602 | B64: RIESGO | D64: COL01 | E64: COL02 | F64: COL03 | G64: COL04 | H64: COL05 | I64: COL06 | J64: COL07 | K64: COL08 | L64: COL09 | M64: COL10 | N64: COL11 | O64: COL12 | P64: COL13 | Q64: COL14 | R64: COL15 | S64: COL16 | T64: COL17 | U64: COL18 | V64: COL19 | W64: COL20 | X64: COL21 | Y64: COL22 | Z64: COL23 | AA64: COL24
A65: 06902603 | B65: RETRASO | D65: COL01 | E65: COL02 | F65: COL03 | G65: COL04 | H65: COL05 | I65: COL06 | J65: COL07 | K65: COL08 | L65: COL09 | M65: COL10 | N65: COL11 | O65: COL12 | P65: COL13 | Q65: COL14 | R65: COL15 | S65: COL16 | T65: COL17 | U65: COL18 | V65: COL19 | W65: COL20 | X65: COL21 | Y65: COL22 | Z65: COL23 | AA65: COL24
A66: 06902604 | B66: OTRA VULNERABILIDAD | D66: COL01 | E66: COL02 | F66: COL03 | G66: COL04 | H66: COL05 | I66: COL06 | J66: COL07 | K66: COL08 | L66: COL09 | M66: COL10 | N66: COL11 | O66: COL12 | P66: COL13 | Q66: COL14 | R66: COL15 | S66: COL16 | T66: COL17 | U66: COL18 | V66: COL19 | W66: COL20 | X66: COL21 | Y66: COL22 | Z66: COL23 | AA66: COL24
B67: SECCIÓN F.1: REINGRESOS Y EGRESOS POR SEGUNDA VEZ A MODALIDAD DE ESTIMULACIÓN EN EL CENTRO DE SALUD
B68: NIÑO / A (CON) | D68: TOTAL | G68: REINGRESOS A MODALIDAD DE ESTIMULACIÓN EN CENTRO DE SALUD | S68: EGRESOS POR SEGUNDA VEZ Y RESULTADOS DE LA REEVALUACIÓN POST EGRESO
G69: Menor 7 meses | I69: 7 - 11 meses | K69: 12 - 17 meses | M69: 18 - 23 meses | O69: 24 - 47 meses | Q69: 48 - 59 meses | S69: MOTIVO EGRESO | U69: INASISTENTE | V69: RESULTADO DE REEVALUACIÓN
D70: Ambos Sexos | E70: Hombres | F70: Mujeres | G70: Hombres | H70: Mujeres | I70: Hombres | J70: Mujeres | K70: Hombres | L70: Mujeres | M70: Hombres | N70: Mujeres | O70: Hombres | P70: Mujeres | Q70: Hombres | R70: Mujeres | S70: Cumplimiento de tratamiento | T70: Otros | V70: Recuperado | W70: No Recuperado
A71: 05970010 | B71: NORMAL CON REZAGO | D71: COL01 | E71: COL02 | F71: COL03 | G71: COL04 | H71: COL05 | I71: COL06 | J71: COL07 | K71: COL08 | L71: COL09 | M71: COL10 | N71: COL11 | O71: COL12 | P71: COL13 | Q71: COL14 | R71: COL15 | S71: COL16 | T71: COL17 | U71: COL18 | V71: COL19 | W71: COL20
A72: 05970011 | B72: RIESGO | D72: COL01 | E72: COL02 | F72: COL03 | G72: COL04 | H72: COL05 | I72: COL06 | J72: COL07 | K72: COL08 | L72: COL09 | M72: COL10 | N72: COL11 | O72: COL12 | P72: COL13 | Q72: COL14 | R72: COL15 | S72: COL16 | T72: COL17 | U72: COL18 | V72: COL19 | W72: COL20
A73: 05970012 | B73: RETRASO | D73: COL01 | E73: COL02 | F73: COL03 | G73: COL04 | H73: COL05 | I73: COL06 | J73: COL07 | K73: COL08 | L73: COL09 | M73: COL10 | N73: COL11 | O73: COL12 | P73: COL13 | Q73: COL14 | R73: COL15 | S73: COL16 | T73: COL17 | U73: COL18 | V73: COL19 | W73: COL20
A74: 05970013 | B74: OTRA VULNERABILIDAD | D74: COL01 | E74: COL02 | F74: COL03 | G74: COL04 | H74: COL05 | I74: COL06 | J74: COL07 | K74: COL08 | L74: COL09 | M74: COL10 | N74: COL11 | O74: COL12 | P74: COL13 | Q74: COL14 | R74: COL15 | S74: COL16 | T74: COL17 | U74: COL18 | V74: COL19 | W74: COL20
B75: SECCIÓN G: INGRESOS DE NIÑOS Y NIÑAS CON NECESIDADES ESPECIALES DE BAJA COMPLEJIDAD A CONTROL DE SALUD INFANTIL EN APS
B76: NANEAS | D76: TOTAL | G76: POR EDAD
G77: 0 - 4 Meses | I77: 5 - 9 Meses | K77: 10 - 14 Meses | M77: 15 a 19 Meses | O77: 20 - 24 Meses
D78: Ambos Sexos | E78: Hombres | F78: Mujeres | G78: Hombres | H78: Mujeres | I78: Hombres | J78: Mujeres | K78: Hombres | L78: Mujeres | M78: Hombres | N78: Mujeres | O78: Hombres | P78: Mujeres
A79: 05225102 | B79: INGRESOS | D79: COL01 | E79: COL02 | F79: COL03 | G79: COL04 | H79: COL05 | I79: COL06 | J79: COL07 | K79: COL08 | L79: COL09 | M79: COL10 | N79: COL11 | O79: COL12 | P79: COL13
B80: SECCIÓN H: INGRESOS AL PSCV
B81: CONCEPTO | D81: TOTAL | G81: INGRESOS
G82: 15 - 19 | I82: 20-24 | K82: 25 a 29 | M82: 30 a 34 | O82: 35 a 39 | Q82: 40 a 44 | S82: 45 a 49 | U82: 50 a 54 | W82: 55 a 59 | Y82: 60 a 64 | AA82: 65 a 69 | AC82: 70 a 74 | AE82: 75 a 79 | AG82: 80 y más
D83: Ambos Sexos | E83: Hombres | F83: Mujeres | G83: Hombres | H83: Mujeres | I83: Hombres | J83: Mujeres | K83: Hombres | L83: Mujeres | M83: Hombres | N83: Mujeres | O83: Hombres | P83: Mujeres | Q83: Hombres | R83: Mujeres | S83: Hombres | T83: Mujeres | U83: Hombres | V83: Mujeres | W83: Hombres | X83: Mujeres | Y83: Hombres | Z83: Mujeres | AA83: Hombres | AB83: Mujeres | AC83: Hombres | AD83: Mujeres | AE83: Hombres | AF83: Mujeres | AG83: Hombres | AH83: Mujeres
A84: 03030360 | B84: INGRESOS AL PSCV | D84: COL01 | E84: COL02 | F84: COL03 | G84: COL04 | H84: COL05 | I84: COL06 | J84: COL07 | K84: COL08 | L84: COL09 | M84: COL10 | N84: COL11 | O84: COL12 | P84: COL13 | Q84: COL14 | R84: COL15 | S84: COL16 | T84: COL17 | U84: COL18 | V84: COL19 | W84: COL20 | X84: COL21 | Y84: COL22 | Z84: COL23 | AA84: COL24 | AB84: COL25 | AC84: COL26 | AD84: COL27 | AE84: COL28 | AF84: COL29 | AG84: COL30 | AH84: COL31
A85: 03021106 | B85: PROGRAMA DE SALUD CARDIOVASCULAR | C85: HIPERTENSIÓN ARTERIAL | D85: COL01 | E85: COL02 | F85: COL03 | G85: COL04 | H85: COL05 | I85: COL06 | J85: COL07 | K85: COL08 | L85: COL09 | M85: COL10 | N85: COL11 | O85: COL12 | P85: COL13 | Q85: COL14 | R85: COL15 | S85: COL16 | T85: COL17 | U85: COL18 | V85: COL19 | W85: COL20 | X85: COL21 | Y85: COL22 | Z85: COL23 | AA85: COL24 | AB85: COL25 | AC85: COL26 | AD85: COL27 | AE85: COL28 | AF85: COL29 | AG85: COL30 | AH85: COL31 | CH85: 0
A86: 03021107 | C86: DIABETES MELLITUS | D86: COL01 | E86: COL02 | F86: COL03 | G86: COL04 | H86: COL05 | I86: COL06 | J86: COL07 | K86: COL08 | L86: COL09 | M86: COL10 | N86: COL11 | O86: COL12 | P86: COL13 | Q86: COL14 | R86: COL15 | S86: COL16 | T86: COL17 | U86: COL18 | V86: COL19 | W86: COL20 | X86: COL21 | Y86: COL22 | Z86: COL23 | AA86: COL24 | AB86: COL25 | AC86: COL26 | AD86: COL27 | AE86: COL28 | AF86: COL29 | AG86: COL30 | AH86: COL31 | CH86: 0
A87: 03021108 | C87: DISLIPIDEMIA | D87: COL01 | E87: COL02 | F87: COL03 | G87: COL04 | H87: COL05 | I87: COL06 | J87: COL07 | K87: COL08 | L87: COL09 | M87: COL10 | N87: COL11 | O87: COL12 | P87: COL13 | Q87: COL14 | R87: COL15 | S87: COL16 | T87: COL17 | U87: COL18 | V87: COL19 | W87: COL20 | X87: COL21 | Y87: COL22 | Z87: COL23 | AA87: COL24 | AB87: COL25 | AC87: COL26 | AD87: COL27 | AE87: COL28 | AF87: COL29 | AG87: COL30 | AH87: COL31 | CH87: 0
A88: 05810431 | C88: ANTECEDENTES ENF. CARDIOVASCULAR ATEROSCLERÓTICA | D88: COL01 | E88: COL02 | F88: COL03 | G88: COL04 | H88: COL05 | I88: COL06 | J88: COL07 | K88: COL08 | L88: COL09 | M88: COL10 | N88: COL11 | O88: COL12 | P88: COL13 | Q88: COL14 | R88: COL15 | S88: COL16 | T88: COL17 | U88: COL18 | V88: COL19 | W88: COL20 | X88: COL21 | Y88: COL22 | Z88: COL23 | AA88: COL24 | AB88: COL25 | AC88: COL26 | AD88: COL27 | AE88: COL28 | AF88: COL29 | AG88: COL30 | AH88: COL31 | CH88: 0
A89: 05810432 | C89: TABAQUISMO | D89: COL01 | E89: COL02 | F89: COL03 | G89: COL04 | H89: COL05 | I89: COL06 | J89: COL07 | K89: COL08 | L89: COL09 | M89: COL10 | N89: COL11 | O89: COL12 | P89: COL13 | Q89: COL14 | R89: COL15 | S89: COL16 | T89: COL17 | U89: COL18 | V89: COL19 | W89: COL20 | X89: COL21 | Y89: COL22 | Z89: COL23 | AA89: COL24 | AB89: COL25 | AC89: COL26 | AD89: COL27 | AE89: COL28 | AF89: COL29 | AG89: COL30 | AH89: COL31 | CH89: 0
B90: SECCIÓN I: EGRESOS DEL PSCV | CH90: 0
B91: CONCEPTO | D91: TOTAL | G91: EGRESOS | AI91: CAUSAL DE EGRESO | CH91: 0
G92: 15 - 19 | I92: 20-24 | K92: 25 a 29 | M92: 30 a 34 | O92: 35 a 39 | Q92: 40 a 44 | S92: 45 a 49 | U92: 50 a 54 | W92: 55 a 59 | Y92: 60 a 64 | AA92: 65 a 69 | AC92: 70 a 74 | AE92: 75 a 79 | AG92: 80 y más | AI92: Abandono | AJ92: Traslado | AK92: Fallecimiento | AL92: No cumple criterio | CH92: 0
D93: Ambos Sexos | E93: Hombres | F93: Mujeres | G93: Hombres | H93: Mujeres | I93: Hombres | J93: Mujeres | K93: Hombres | L93: Mujeres | M93: Hombres | N93: Mujeres | O93: Hombres | P93: Mujeres | Q93: Hombres | R93: Mujeres | S93: Hombres | T93: Mujeres | U93: Hombres | V93: Mujeres | W93: Hombres | X93: Mujeres | Y93: Hombres | Z93: Mujeres | AA93: Hombres | AB93: Mujeres | AC93: Hombres | AD93: Mujeres | AE93: Hombres | AF93: Mujeres | AG93: Hombres | AH93: Mujeres | CH93: 0
A94: 05810040 | B94: EGRESOS DEL PSCV | D94: COL01 | E94: COL02 | F94: COL03 | G94: COL04 | H94: COL05 | I94: COL06 | J94: COL07 | K94: COL08 | L94: COL09 | M94: COL10 | N94: COL11 | O94: COL12 | P94: COL13 | Q94: COL14 | R94: COL15 | S94: COL16 | T94: COL17 | U94: COL18 | V94: COL19 | W94: COL20 | X94: COL21 | Y94: COL22 | Z94: COL23 | AA94: COL24 | AB94: COL25 | AC94: COL26 | AD94: COL27 | AE94: COL28 | AF94: COL29 | AG94: COL30 | AH94: COL31 | AI94: COL32 | AJ94: COL33 | AK94: COL34 | AL94: COL35 | CH94: 0
A95: 05225400 | B95: PROGRAMA DE SALUD CARDIOVASCULAR | C95: HIPERTENSIÓN ARTERIAL | D95: COL01 | E95: COL02 | F95: COL03 | G95: COL04 | H95: COL05 | I95: COL06 | J95: COL07 | K95: COL08 | L95: COL09 | M95: COL10 | N95: COL11 | O95: COL12 | P95: COL13 | Q95: COL14 | R95: COL15 | S95: COL16 | T95: COL17 | U95: COL18 | V95: COL19 | W95: COL20 | X95: COL21 | Y95: COL22 | Z95: COL23 | AA95: COL24 | AB95: COL25 | AC95: COL26 | AD95: COL27 | AE95: COL28 | AF95: COL29 | AG95: COL30 | AH95: COL31 | AI95: COL32 | AJ95: COL33 | AK95: COL34 | AL95: COL35 | CH95: 0
A96: 05225401 | C96: DIABETES MELLITUS | D96: COL01 | E96: COL02 | F96: COL03 | G96: COL04 | H96: COL05 | I96: COL06 | J96: COL07 | K96: COL08 | L96: COL09 | M96: COL10 | N96: COL11 | O96: COL12 | P96: COL13 | Q96: COL14 | R96: COL15 | S96: COL16 | T96: COL17 | U96: COL18 | V96: COL19 | W96: COL20 | X96: COL21 | Y96: COL22 | Z96: COL23 | AA96: COL24 | AB96: COL25 | AC96: COL26 | AD96: COL27 | AE96: COL28 | AF96: COL29 | AG96: COL30 | AH96: COL31 | AI96: COL32 | AJ96: COL33 | AK96: COL34 | AL96: COL35 | CH96: 0
A97: 05225402 | C97: DISLIPIDEMIA | D97: COL01 | E97: COL02 | F97: COL03 | G97: COL04 | H97: COL05 | I97: COL06 | J97: COL07 | K97: COL08 | L97: COL09 | M97: COL10 | N97: COL11 | O97: COL12 | P97: COL13 | Q97: COL14 | R97: COL15 | S97: COL16 | T97: COL17 | U97: COL18 | V97: COL19 | W97: COL20 | X97: COL21 | Y97: COL22 | Z97: COL23 | AA97: COL24 | AB97: COL25 | AC97: COL26 | AD97: COL27 | AE97: COL28 | AF97: COL29 | AG97: COL30 | AH97: COL31 | AI97: COL32 | AJ97: COL33 | AK97: COL34 | AL97: COL35
A98: 05810433 | C98: ANTECEDENTES ENF. CARDIOVASCULAR ATEROSCLERÓTICA | D98: COL01 | E98: COL02 | F98: COL03 | G98: COL04 | H98: COL05 | I98: COL06 | J98: COL07 | K98: COL08 | L98: COL09 | M98: COL10 | N98: COL11 | O98: COL12 | P98: COL13 | Q98: COL14 | R98: COL15 | S98: COL16 | T98: COL17 | U98: COL18 | V98: COL19 | W98: COL20 | X98: COL21 | Y98: COL22 | Z98: COL23 | AA98: COL24 | AB98: COL25 | AC98: COL26 | AD98: COL27 | AE98: COL28 | AF98: COL29 | AG98: COL30 | AH98: COL31 | AI98: COL32 | AJ98: COL33 | AK98: COL34 | AL98: COL35
A99: 05810434 | C99: TABAQUISMO | D99: COL01 | E99: COL02 | F99: COL03 | G99: COL04 | H99: COL05 | I99: COL06 | J99: COL07 | K99: COL08 | L99: COL09 | M99: COL10 | N99: COL11 | O99: COL12 | P99: COL13 | Q99: COL14 | R99: COL15 | S99: COL16 | T99: COL17 | U99: COL18 | V99: COL19 | W99: COL20 | X99: COL21 | Y99: COL22 | Z99: COL23 | AA99: COL24 | AB99: COL25 | AC99: COL26 | AD99: COL27 | AE99: COL28 | AF99: COL29 | AG99: COL30 | AH99: COL31 | AI99: COL32 | AJ99: COL33 | AK99: COL34 | AL99: COL35 | CB99: =IF(D99>D98+D97,"* Los Ingresos de pacientes dependientes severos con escaras DEBEN estar incluidos en los Ingresos de pacientes dependientes severos Oncológicos o No Oncológicos. ","") -> #VALUE!
B100: SECCIÓN J: INGRESOS Y EGRESOS AL PROGRAMA DE PACIENTES CON DEPENDENCIA LEVE, MODERADA Y SEVERA
B101: CONCEPTO | D101: TOTAL | G101: INGRESOS | AI101: CAUSAL DE EGRESO
G102: < 20 años | I102: 20-24 | K102: 25 a 29 | M102: 30 a 34 | O102: 35 a 39 | Q102: 40 a 44 | S102: 45 a 49 | U102: 50 a 54 | W102: 55 a 59 | Y102: 60 a 64 | AA102: 65 a 69 | AC102: 70 a 74 | AE102: 75 a 79 | AG102: 80 y más | AI102: Altas | AJ102: Abandono/ Traslado | AK102: Fallecimiento
...

Sheet A06
B1: SERVICIO DE SALUD
B2: =CONCATENATE("COMUNA: ",NOMBRE!B2," - ","( ",NOMBRE!C2,NOMBRE!D2,NOMBRE!E2,NOMBRE!F2,NOMBRE!G2," )") -> COMUNA: - ( )
B3: =CONCATENATE("ESTABLECIMIENTO/ESTRATEGIA: ",NOMBRE!B3," - ","( ",NOMBRE!C3,NOMBRE!D3,NOMBRE!E3,NOMBRE!F3,NOMBRE!G3,NOMBRE!H3," )") -> ESTABLECIMIENTO/ESTRATEGIA: - ( )
B4: =CONCATENATE("MES: ",NOMBRE!B6," - ","( ",NOMBRE!C6,NOMBRE!D6," )") -> MES: - ( )
B5: =CONCATENATE("AÑO: ",NOMBRE!B7) -> AÑO: 2020
B6: REM-06. PROGRAMA DE SALUD MENTAL ATENCIÓN PRIMARIA Y ESPECIALIDADES
B9: SECCIÓN A.1: CONTROLES DE ATENCIÓN PRIMARIA / ESPECIALIDADES
A10: CODIGO DICCIONARIO | B10: ACTIVIDAD | C10: PROFESIONAL | D10: TOTAL | G10: GRUPOS DE EDAD (en años) | AO10: Beneficiarios | AP10: Niños, Niñas, Adolescentes y Jóvenes Población SENAME | AQ10: Pueblos Originarios | AR10: Migrantes | AS10: Demencia
G11: 0 - 4 | I11: 5 - 9 | K11: 10 - 14 | M11: 15 - 19 | O11: 20 - 24 | Q11: 25 - 29 | S11: 30 - 34 | U11: 35 - 39 | W11: 40 - 44 | Y11: 45 - 49 | AA11: 50 - 54 | AC11: 55 - 59 | AE11: 60 - 64 | AG11: 65 - 69 | AI11: 70 - 74 | AK11: 75 - 79 | AM11: 80 y mas
D12: Ambos Sexos | E12: Hombres | F12: Mujeres | G12: Hombres | H12: Mujeres | I12: Hombres | J12: Mujeres | K12: Hombres | L12: Mujeres | M12: Hombres | N12: Mujeres | O12: Hombres | P12: Mujeres | Q12: Hombres | R12: Mujeres | S12: Hombres | T12: Mujeres | U12: Hombres | V12: Mujeres | W12: Hombres | X12: Mujeres | Y12: Hombres | Z12: Mujeres | AA12: Hombres | AB12: Mujeres | AC12: Hombres | AD12: Mujeres | AE12: Hombres | AF12: Mujeres | AG12: Hombres | AH12: Mujeres | AI12: Hombres | AJ12: Mujeres | AK12: Hombres | AL12: Mujeres | AM12: Hombres | AN12: Mujeres
A13: 06020201 | B13: CONTROLES SALUD MENTAL | C13: MÉDICO | D13: COL01 | E13: COL02 | F13: COL03 | G13: COL04 | H13: COL05 | I13: COL06 | J13: COL07 | K13: COL08 | L13: COL09 | M13: COL10 | N13: COL11 | O13: COL12 | P13: COL13 | Q13: COL14 | R13: COL15 | S13: COL16 | T13: COL17 | U13: COL18 | V13: COL19 | W13: COL20 | X13: COL21 | Y13: COL22 | Z13: COL23 | AA13: COL24 | AB13: COL25 | AC13: COL26 | AD13: COL27 | AE13: COL28 | AF13: COL29 | AG13: COL30 | AH13: COL31 | AI13: COL32 | AJ13: COL33 | AK13: COL34 | AL13: COL35 | AM13: COL36 | AN13: COL37 | AO13: COL38 | AP13: COL39 | AQ13: COL40 | AR13: COL41 | AS13: COL42 | AT13: =CONCATENATE(CB13,CC13,CD13,CE13,CF13,CG13) -> * El número de Beneficiarios NO DEBE ser mayor que el Total. * Los Niños, Niñas, Adolescentes y Jóvenes de Programa SENAME NO DEBE ser mayor que el Total. * El número de personas pertenecientes a Pueblos Originarios NO DEBE ser mayor que el Total. * El número de personas Migrantes NO DEBE ser mayor que el Total. * El número de personas con Demencia NO DEBE ser mayor que el Total. | CB13: =IF(CH13=1,"* El número de Beneficiarios NO DEBE ser mayor que el Total. ","") -> * El número de Beneficiarios NO DEBE ser mayor que el Total. | CC13: =IF(CI13=1,"* Los Niños, Niñas, Adolescentes y Jóvenes de Programa SENAME NO DEBE ser mayor que el Total. ","") -> * Los Niños, Niñas, Adolescentes y Jóvenes de Programa SENAME NO DEBE ser mayor que el Total. | CD13: =IF(CJ13=1,"* El número de personas pertenecientes a Pueblos Originarios NO DEBE ser mayor que el Total. ","") -> * El número de personas pertenecientes a Pueblos Originarios NO DEBE ser mayor que el Total. | CE13: =IF(CK13=1,"* El número de personas Migrantes NO DEBE ser mayor que el Total. ","") -> * El número de personas Migrantes NO DEBE ser mayor que el Total. | CF13: =IF(CL13=1,"* El número de personas con Demencia NO DEBE ser mayor que el Total. ","") -> * El número de personas con Demencia NO DEBE ser mayor que el Total. | CG13: =IF(CM13=1,"* No olvide digitar la columna Beneficiarios y/o Niños, Niñas, Adolescentes y Jóvenes de Programa SENAME y/o Pueblos Originarios y/o Migrantes y/o Demencia (Digite CEROS si no tiene). ","") | CH13: =IF($D13<AO13,1,0) -> 1 | CI13: =IF($D13<AP13,1,0) -> 1 | CJ13: =IF($D13<AQ13,1,0) -> 1 | CK13: =IF($D13<AR13,1,0) -> 1 | CL13: =IF($D13<AS13,1,0) -> 1 | CM13: =IF(AND(D13<>0,OR(AO13="",AP13="",AQ13="",AR13="",AS13="")),1,0) -> 0
A14: 06020208 | C14: PSICÓLOGO/A | D14: COL01 | E14: COL02 | F14: COL03 | G14: COL04 | H14: COL05 | I14: COL06 | J14: COL07 | K14: COL08 | L14: COL09 | M14: COL10 | N14: COL11 | O14: COL12 | P14: COL13 | Q14: COL14 | R14: COL15 | S14: COL16 | T14: COL17 | U14: COL18 | V14: COL19 | W14: COL20 | X14: COL21 | Y14: COL22 | Z14: COL23 | AA14: COL24 | AB14: COL25 | AC14: COL26 | AD14: COL27 | AE14: COL28 | AF14: COL29 | AG14: COL30 | AH14: COL31 | AI14: COL32 | AJ14: COL33 | AK14: COL34 | AL14: COL35 | AM14: COL36 | AN14: COL37 | AO14: COL38 | AP14: COL39 | AQ14: COL40 | AR14: COL41 | AS14: COL42 | AT14: =CONCATENATE(CB14,CC14,CD14,CE14,CF14,CG14) -> * El número de Beneficiarios NO DEBE ser mayor que el Total. * Los Niños, Niñas, Adolescentes y Jóvenes de Programa SENAME NO DEBE ser mayor que el Total. * El total de personas pertenecientes a Pueblos Originarios NO DEBE ser mayor que el Total. * El número de personas Migrantes NO DEBE ser mayor que el Total. * El número de personas con Demencia NO DEBE ser mayor que el Total. | CB14: =IF(CH14=1,"* El número de Beneficiarios NO DEBE ser mayor que el Total. ","") -> * El número de Beneficiarios NO DEBE ser mayor que el Total. | CC14: =IF(CI14=1,"* Los Niños, Niñas, Adolescentes y Jóvenes de Programa SENAME NO DEBE ser mayor que el Total. ","") -> * Los Niños, Niñas, Adolescentes y Jóvenes de Programa SENAME NO DEBE ser mayor que el Total. | CD14: =IF(CJ14=1,"* El total de personas pertenecientes a Pueblos Originarios NO DEBE ser mayor que el Total. ","") -> * El total de personas pertenecientes a Pueblos Originarios NO DEBE ser mayor que el Total. | CE14: =IF(CK14=1,"* El número de personas Migrantes NO DEBE ser mayor que el Total. ","") -> * El número de personas Migrantes NO DEBE ser mayor que el Total. | CF14: =IF(CL14=1,"* El número de personas con Demencia NO DEBE ser mayor que el Total. ","") -> * El número de personas con Demencia NO DEBE ser mayor que el Total. | CG14: =IF(CM14=1,"* No olvide digitar la columna Beneficiarios y/o Niños, Niñas, Adolescentes y Jóvenes de Programa SENAME y/o Pueblos Originarios y/o Migrantes y/o Demencia (Digite CEROS si no tiene). ","") | CH14: =IF($D14<AO14,1,0) -> 1 | CI14: =IF($D14<AP14,1,0) -> 1 | CJ14: =IF($D14<AQ14,1,0) -> 1 | CK14: =IF($D14<AR14,1,0) -> 1 | CL14: =IF($D14<AS14,1,0) -> 1 | CM14: =IF(AND(D14<>0,OR(AO14="",AP14="",AQ14="",AR14="",AS14="")),1,0) -> 0
A15: 06020202 | C15: ENFERMERA /O | D15: COL01 | E15: COL02 | F15: COL03 | G15: COL04 | H15: COL05 | I15: COL06 | J15: COL07 | K15: COL08 | L15: COL09 | M15: COL10 | N15: COL11 | O15: COL12 | P15: COL13 | Q15: COL14 | R15: COL15 | S15: COL16 | T15: COL17 | U15: COL18 | V15: COL19 | W15: COL20 | X15: COL21 | Y15: COL22 | Z15: COL23 | AA15: COL24 | AB15: COL25 | AC15: COL26 | AD15: COL27 | AE15: COL28 | AF15: COL29 | AG15: COL30 | AH15: COL31 | AI15: COL32 | AJ15: COL33 | AK15: COL34 | AL15: COL35 | AM15: COL36 | AN15: COL37 | AO15: COL38 | AP15: COL39 | AQ15: COL40 | AR15: COL41 | AS15: COL42 | AT15: =CONCATENATE(CB15,CC15,CD15,CE15,CF15,CG15) -> * El número de Beneficiarios NO DEBE ser mayor que el Total. * Los Niños, Niñas, Adolescentes y Jóvenes de Programa SENAME NO DEBE ser mayor que el Total. * El total de personas pertenecientes a Pueblos Originarios NO DEBE ser mayor que el Total. * El número de personas Migrantes NO DEBE ser mayor que el Total. * El número de personas con Demencia NO DEBE ser mayor que el Total. | CB15: =IF(CH15=1,"* El número de Beneficiarios NO DEBE ser mayor que el Total. ","") -> * El número de Beneficiarios NO DEBE ser mayor que el Total. | CC15: =IF(CI15=1,"* Los Niños, Niñas, Adolescentes y Jóvenes de Programa SENAME NO DEBE ser mayor que el Total. ","") -> * Los Niños, Niñas, Adolescentes y Jóvenes de Programa SENAME NO DEBE ser mayor que el Total. | CD15: =IF(CJ15=1,"* El total de personas pertenecientes a Pueblos Originarios NO DEBE ser mayor que el Total. ","") -> * El total de personas pertenecientes a Pueblos Originarios NO DEBE ser mayor que el Total. | CE15: =IF(CK15=1,"* El número de personas Migrantes NO DEBE ser mayor que el Total. ","") -> * El número de personas Migrantes NO DEBE ser mayor que el Total. | CF15: =IF(CL15=1,"* El número de personas con Demencia NO DEBE ser mayor que el Total. ","") -> * El número de personas con Demencia NO DEBE ser mayor que el Total. | CG15: =IF(CM15=1,"* No olvide digitar la columna Beneficiarios y/o Niños, Niñas, Adolescentes y Jóvenes de Programa SENAME y/o Pueblos Originarios y/o Migrantes y/o Demencia (Digite CEROS si no tiene). ","") | CH15: =IF($D15<AO15,1,0) -> 1 | CI15: =IF($D15<AP15,1,0) -> 1 | CJ15: =IF($D15<AQ15,1,0) -> 1 | CK15: =IF($D15<AR15,1,0) -> 1 | CL15: =IF($D15<AS15,1,0) -> 1 | CM15: =IF(AND(D15<>0,OR(AO15="",AP15="",AQ15="",AR15="",AS15="")),1,0) -> 0
A16: 06020602 | C16: MATRONA /ÓN | D16: COL01 | E16: COL02 | F16: COL03 | G16: COL04 | H16: COL05 | I16: COL06 | J16: COL07 | K16: COL08 | L16: COL09 | M16: COL10 | N16: COL11 | O16: COL12 | P16: COL13 | Q16: COL14 | R16: COL15 | S16: COL16 | T16: COL17 | U16: COL18 | V16: COL19 | W16: COL20 | X16: COL21 | Y16: COL22 | Z16: COL23 | AA16: COL24 | AB16: COL25 | AC16: COL26 | AD16: COL27 | AE16: COL28 | AF16: COL29 | AG16: COL30 | AH16: COL31 | AI16: COL32 | AJ16: COL33 | AK16: COL34 | AL16: COL35 | AM16: COL36 | AN16: COL37 | AO16: COL38 | AP16: COL39 | AQ16: COL40 | AR16: COL41 | AS16: COL42 | AT16: =CONCATENATE(CB16,CC16,CD16,CE16,CF16,CG16) -> * El número de Beneficiarios NO DEBE ser mayor que el Total. * Los Niños, Niñas, Adolescentes y Jóvenes de Programa SENAME NO DEBE ser mayor que el Total. * El total de personas pertenecientes a Pueblos Originarios NO DEBE ser mayor que el Total. * El número de personas Migrantes NO DEBE ser mayor que el Total. * El número de personas con Demencia NO DEBE ser mayor que el Total. | CB16: =IF(CH16=1,"* El número de Beneficiarios NO DEBE ser mayor que el Total. ","") -> * El número de Beneficiarios NO DEBE ser mayor que el Total. | CC16: =IF(CI16=1,"* Los Niños, Niñas, Adolescentes y Jóvenes de Programa SENAME NO DEBE ser mayor que el Total. ","") -> * Los Niños, Niñas, Adolescentes y Jóvenes de Programa SENAME NO DEBE ser mayor que el Total. | CD16: =IF(CJ16=1,"* El total de personas pertenecientes a Pueblos Originarios NO DEBE ser mayor que el Total. ","") -> * El total de personas pertenecientes a Pueblos Originarios NO DEBE ser mayor que el Total. | CE16: =IF(CK16=1,"* El número de personas Migrantes NO DEBE ser mayor que el Total. ","") -> * El número de personas Migrantes NO DEBE ser mayor que el Total. | CF16: =IF(CL16=1,"* El número de personas con Demencia NO DEBE ser mayor que el Total. ","") -> * El número de personas con Demencia NO DEBE ser mayor que el Total. | CG16: =IF(CM16=1,"* No olvide digitar la columna Beneficiarios y/o Niños, Niñas, Adolescentes y Jóvenes de Programa SENAME y/o Pueblos Originarios y/o Migrantes y/o Demencia (Digite CEROS si no tiene). ","") | CH16: =IF($D16<AO16,1,0) -> 1 | CI16: =IF($D16<AP16,1,0) -> 1 | CJ16: =IF($D16<AQ16,1,0) -> 1 | CK16: =IF($D16<AR16,1,0) -> 1 | CL16: =IF($D16<AS16,1,0) -> 1 | CM16: =IF(AND(D16<>0,OR(AO16="",AP16="",AQ16="",AR16="",AS16="")),1,0) -> 0
A17: 06020206 | C17: ASISTENTE SOCIAL | D17: COL01 | E17: COL02 | F17: COL03 | G17: COL04 | H17: COL05 | I17: COL06 | J17: COL07 | K17: COL08 | L17: COL09 | M17: COL10 | N17: COL11 | O17: COL12 | P17: COL13 | Q17: COL14 | R17: COL15 | S17: COL16 | T17: COL17 | U17: COL18 | V17: COL19 | W17: COL20 | X17: COL21 | Y17: COL22 | Z17: COL23 | AA17: COL24 | AB17: COL25 | AC17: COL26 | AD17: COL27 | AE17: COL28 | AF17: COL29 | AG17: COL30 | AH17: COL31 | AI17: COL32 | AJ17: COL33 | AK17: COL34 | AL17: COL35 | AM17: COL36 | AN17: COL37 | AO17: COL38 | AP17: COL39 | AQ17: COL40 | AR17: COL41 | AS17: COL42 | AT17: =CONCATENATE(CB17,CC17,CD17,CE17,CF17,CG17) -> * El número de Beneficiarios NO DEBE ser mayor que el Total. * Los Niños, Niñas, Adolescentes y Jóvenes de Programa SENAME NO DEBE ser mayor que el Total. * El total de personas pertenecientes a Pueblos Originarios NO DEBE ser mayor que el Total. * El número de personas Migrantes NO DEBE ser mayor que el Total. * El número de personas con Demencia NO DEBE ser mayor que el Total. | CB17: =IF(CH17=1,"* El número de Beneficiarios NO DEBE ser mayor que el Total. ","") -> * El número de Beneficiarios NO DEBE ser mayor que el Total. | CC17: =IF(CI17=1,"* Los Niños, Niñas, Adolescentes y Jóvenes de Programa SENAME NO DEBE ser mayor que el Total. ","") -> * Los Niños, Niñas, Adolescentes y Jóvenes de Programa SENAME NO DEBE ser mayor que el Total. | CD17: =IF(CJ17=1,"* El total de personas pertenecientes a Pueblos Originarios NO DEBE ser mayor que el Total. ","") -> * El total de personas pertenecientes a Pueblos Originarios NO DEBE ser mayor que el Total. | CE17: =IF(CK17=1,"* El número de personas Migrantes NO DEBE ser mayor que el Total. ","") -> * El número de personas Migrantes NO DEBE ser mayor que el Total. | CF17: =IF(CL17=1,"* El número de personas con Demencia NO DEBE ser mayor que el Total. ","") -> * El número de personas con Demencia NO DEBE ser mayor que el Total. | CG17: =IF(CM17=1,"* No olvide digitar la columna Beneficiarios y/o Niños, Niñas, Adolescentes y Jóvenes de Programa SENAME y/o Pueblos Originarios y/o Migrantes y/o Demencia (Digite CEROS si no tiene). ","") | CH17: =IF($D17<AO17,1,0) -> 1 | CI17: =IF($D17<AP17,1,0) -> 1 | CJ17: =IF($D17<AQ17,1,0) -> 1 | CK17: =IF($D17<AR17,1,0) -> 1 | CL17: =IF($D17<AS17,1,0) -> 1 | CM17: =IF(AND(D17<>0,OR(AO17="",AP17="",AQ17="",AR17="",AS17="")),1,0) -> 0
A18: 06200400 | C18: OTROS PROFESIONALES | D18: COL01 | E18: COL02 | F18: COL03 | G18: COL04 | H18: COL05 | I18: COL06 | J18: COL07 | K18: COL08 | L18: COL09 | M18: COL10 | N18: COL11 | O18: COL12 | P18: COL13 | Q18: COL14 | R18: COL15 | S18: COL16 | T18: COL17 | U18: COL18 | V18: COL19 | W18: COL20 | X18: COL21 | Y18: COL22 | Z18: COL23 | AA18: COL24 | AB18: COL25 | AC18: COL26 | AD18: COL27 | AE18: COL28 | AF18: COL29 | AG18: COL30 | AH18: COL31 | AI18: COL32 | AJ18: COL33 | AK18: COL34 | AL18: COL35 | AM18: COL36 | AN18: COL37 | AO18: COL38 | AP18: COL39 | AQ18: COL40 | AR18: COL41 | AS18: COL42 | AT18: =CONCATENATE(CB18,CC18,CD18,CE18,CF18,CG18) -> * El número de Beneficiarios NO DEBE ser mayor que el Total. * Los Niños, Niñas, Adolescentes y Jóvenes de Programa SENAME NO DEBE ser mayor que el Total. * El total de personas pertenecientes a Pueblos Originarios NO DEBE ser mayor que el Total. * El número de personas Migrantes NO DEBE ser mayor que el Total. * El número de personas con Demencia NO DEBE ser mayor que el Total. | CB18: =IF(CH18=1,"* El número de Beneficiarios NO DEBE ser mayor que el Total. ","") -> * El número de Beneficiarios NO DEBE ser mayor que el Total. | CC18: =IF(CI18=1,"* Los Niños, Niñas, Adolescentes y Jóvenes de Programa SENAME NO DEBE ser mayor que el Total. ","") -> * Los Niños, Niñas, Adolescentes y Jóvenes de Programa SENAME NO DEBE ser mayor que el Total. | CD18: =IF(CJ18=1,"* El total de personas pertenecientes a Pueblos Originarios NO DEBE ser mayor que el Total. ","") -> * El total de personas pertenecientes a Pueblos Originarios NO DEBE ser mayor que el Total. | CE18: =IF(CK18=1,"* El número de personas Migrantes NO DEBE ser mayor que el Total. ","") -> * El número de personas Migrantes NO DEBE ser mayor que el Total. | CF18: =IF(CL18=1,"* El número de personas con Demencia NO DEBE ser mayor que el Total. ","") -> * El número de personas con Demencia NO DEBE ser mayor que el Total. | CG18: =IF(CM18=1,"* No olvide digitar la columna Beneficiarios y/o Niños, Niñas, Adolescentes y Jóvenes de Programa SENAME y/o Pueblos Originarios y/o Migrantes y/o Demencia (Digite CEROS si no tiene). ","") | CH18: =IF($D18<AO18,1,0) -> 1 | CI18: =IF($D18<AP18,1,0) -> 1 | CJ18: =IF($D18<AQ18,1,0) -> 1 | CK18: =IF($D18<AR18,1,0) -> 1 | CL18: =IF($D18<AS18,1,0) -> 1 | CM18: =IF(AND(D18<>0,OR(AO18="",AP18="",AQ18="",AR18="",AS18="")),1,0) -> 0
A19: 06904900 | C19: TERAPEUTA OCUPACIONAL | D19: COL01 | E19: COL02 | F19: COL03 | G19: COL04 | H19: COL05 | I19: COL06 | J19: COL07 | K19: COL08 | L19: COL09 | M19: COL10 | N19: COL11 | O19: COL12 | P19: COL13 | Q19: COL14 | R19: COL15 | S19: COL16 | T19: COL17 | U19: COL18 | V19: COL19 | W19: COL20 | X19: COL21 | Y19: COL22 | Z19: COL23 | AA19: COL24 | AB19: COL25 | AC19: COL26 | AD19: COL27 | AE19: COL28 | AF19: COL29 | AG19: COL30 | AH19: COL31 | AI19: COL32 | AJ19: COL33 | AK19: COL34 | AL19: COL35 | AM19: COL36 | AN19: COL37 | AO19: COL38 | AP19: COL39 | AQ19: COL40 | AR19: COL41 | AS19: COL42 | AT19: =CONCATENATE(CB19,CC19,CD19,CE19,CF19,CG19) -> * El número de Beneficiarios NO DEBE ser mayor que el Total. * Los Niños, Niñas, Adolescentes y Jóvenes de Programa SENAME NO DEBE ser mayor que el Total. * El total de personas pertenecientes a Pueblos Originarios NO DEBE ser mayor que el Total. * El número de personas Migrantes NO DEBE ser mayor que el Total. * El número de personas con Demencia NO DEBE ser mayor que el Total. | CB19: =IF(CH19=1,"* El número de Beneficiarios NO DEBE ser mayor que el Total. ","") -> * El número de Beneficiarios NO DEBE ser mayor que el Total. | CC19: =IF(CI19=1,"* Los Niños, Niñas, Adolescentes y Jóvenes de Programa SENAME NO DEBE ser mayor que el Total. ","") -> * Los Niños, Niñas, Adolescentes y Jóvenes de Programa SENAME NO DEBE ser mayor que el Total. | CD19: =IF(CJ19=1,"* El total de personas pertenecientes a Pueblos Originarios NO DEBE ser mayor que el Total. ","") -> * El total de personas pertenecientes a Pueblos Originarios NO DEBE ser mayor que el Total. | CE19: =IF(CK19=1,"* El número de personas Migrantes NO DEBE ser mayor que el Total. ","") -> * El número de personas Migrantes NO DEBE ser mayor que el Total. | CF19: =IF(CL19=1,"* El número de personas con Demencia NO DEBE ser mayor que el Total. ","") -> * El número de personas con Demencia NO DEBE ser mayor que el Total. | CG19: =IF(CM19=1,"* No olvide digitar la columna Beneficiarios y/o Niños, Niñas, Adolescentes y Jóvenes de Programa SENAME y/o Pueblos Originarios y/o Migrantes y/o Demencia (Digite CEROS si no tiene). ","") | CH19: =IF($D19<AO19,1,0) -> 1 | CI19: =IF($D19<AP19,1,0) -> 1 | CJ19: =IF($D19<AQ19,1,0) -> 1 | CK19: =IF($D19<AR19,1,0) -> 1 | CL19: =IF($D19<AS19,1,0) -> 1 | CM19: =IF(AND(D19<>0,OR(AO19="",AP19="",AQ19="",AR19="",AS19="")),1,0) -> 0
A20: 06200500 | C20: TÉCNICO PARAMÉDICO y EN SALUD MENTAL | D20: COL01 | E20: COL02 | F20: COL03 | G20: COL04 | H20: COL05 | I20: COL06 | J20: COL07 | K20: COL08 | L20: COL09 | M20: COL10 | N20: COL11 | O20: COL12 | P20: COL13 | Q20: COL14 | R20: COL15 | S20: COL16 | T20: COL17 | U20: COL18 | V20: COL19 | W20: COL20 | X20: COL21 | Y20: COL22 | Z20: COL23 | AA20: COL24 | AB20: COL25 | AC20: COL26 | AD20: COL27 | AE20: COL28 | AF20: COL29 | AG20: COL30 | AH20: COL31 | AI20: COL32 | AJ20: COL33 | AK20: COL34 | AL20: COL35 | AM20: COL36 | AN20: COL37 | AO20: COL38 | AP20: COL39 | AQ20: COL40 | AR20: COL41 | AS20: COL42 | AT20: =CONCATENATE(CB20,CC20,CD20,CE20,CF20,CG20) -> * El número de Beneficiarios NO DEBE ser mayor que el Total. * Los Niños, Niñas, Adolescentes y Jóvenes de Programa SENAME NO DEBE ser mayor que el Total. * El total de personas pertenecientes a Pueblos Originarios NO DEBE ser mayor que el Total. * El número de personas Migrantes NO DEBE ser mayor que el Total. * El número de personas con Demencia NO DEBE ser mayor que el Total. | CB20: =IF(CH20=1,"* El número de Beneficiarios NO DEBE ser mayor que el Total. ","") -> * El número de Beneficiarios NO DEBE ser mayor que el Total. | CC20: =IF(CI20=1,"* Los Niños, Niñas, Adolescentes y Jóvenes de Programa SENAME NO DEBE ser mayor que el Total. ","") -> * Los Niños, Niñas, Adolescentes y Jóvenes de Programa SENAME NO DEBE ser mayor que el Total. | CD20: =IF(CJ20=1,"* El total de personas pertenecientes a Pueblos Originarios NO DEBE ser mayor que el Total. ","") -> * El total de personas pertenecientes a Pueblos Originarios NO DEBE ser mayor que el Total. | CE20: =IF(CK20=1,"* El número de personas Migrantes NO DEBE ser mayor que el Total. ","") -> * El número de personas Migrantes NO DEBE ser mayor que el Total. | CF20: =IF(CL20=1,"* El número de personas con Demencia NO DEBE ser mayor que el Total. ","") -> * El número de personas con Demencia NO DEBE ser mayor que el Total. | CG20: =IF(CM20=1,"* No olvide digitar la columna Beneficiarios y/o Niños, Niñas, Adolescentes y Jóvenes de Programa SENAME y/o Pueblos Originarios y/o Migrantes y/o Demencia (Digite CEROS si no tiene). ","") | CH20: =IF($D20<AO20,1,0) -> 1 | CI20: =IF($D20<AP20,1,0) -> 1 | CJ20: =IF($D20<AQ20,1,0) -> 1 | CK20: =IF($D20<AR20,1,0) -> 1 | CL20: =IF($D20<AS20,1,0) -> 1 | CM20: =IF(AND(D20<>0,OR(AO20="",AP20="",AQ20="",AR20="",AS20="")),1,0) -> 0
A21: 06200501 | C21: GESTOR COMUNITARIO | D21: COL01 | E21: COL02 | F21: COL03 | G21: COL04 | H21: COL05 | I21: COL06 | J21: COL07 | K21: COL08 | L21: COL09 | M21: COL10 | N21: COL11 | O21: COL12 | P21: COL13 | Q21: COL14 | R21: COL15 | S21: COL16 | T21: COL17 | U21: COL18 | V21: COL19 | W21: COL20 | X21: COL21 | Y21: COL22 | Z21: COL23 | AA21: COL24 | AB21: COL25 | AC21: COL26 | AD21: COL27 | AE21: COL28 | AF21: COL29 | AG21: COL30 | AH21: COL31 | AI21: COL32 | AJ21: COL33 | AK21: COL34 | AL21: COL35 | AM21: COL36 | AN21: COL37 | AO21: COL38 | AP21: COL39 | AQ21: COL40 | AR21: COL41 | AS21: COL42 | AT21: =CONCATENATE(CB21,CC21,CD21,CE21,CF21,CG21) -> * El número de Beneficiarios NO DEBE ser mayor que el Total. * Los Niños, Niñas, Adolescentes y Jóvenes de Programa SENAME NO DEBE ser mayor que el Total. * El total de personas pertenecientes a Pueblos Originarios NO DEBE ser mayor que el Total. * El número de personas Migrantes NO DEBE ser mayor que el Total. * El número de personas con Demencia NO DEBE ser mayor que el Total. | CB21: =IF(CH21=1,"* El número de Beneficiarios NO DEBE ser mayor que el Total. ","") -> * El número de Beneficiarios NO DEBE ser mayor que el Total. | CC21: =IF(CI21=1,"* Los Niños, Niñas, Adolescentes y Jóvenes de Programa SENAME NO DEBE ser mayor que el Total. ","") -> * Los Niños, Niñas, Adolescentes y Jóvenes de Programa SENAME NO DEBE ser mayor que el Total. | CD21: =IF(CJ21=1,"* El total de personas pertenecientes a Pueblos Originarios NO DEBE ser mayor que el Total. ","") -> * El total de personas pertenecientes a Pueblos Originarios NO DEBE ser mayor que el Total. | CE21: =IF(CK21=1,"* El número de personas Migrantes NO DEBE ser mayor que el Total. ","") -> * El número de personas Migrantes NO DEBE ser mayor que el Total. | CF21: =IF(CL21=1,"* El número de personas con Demencia NO DEBE ser mayor que el Total. ","") -> * El número de personas con Demencia NO DEBE ser mayor que el Total. | CG21: =IF(CM21=1,"* No olvide digitar la columna Beneficiarios y/o Niños, Niñas, Adolescentes y Jóvenes de Programa SENAME y/o Pueblos Originarios y/o Migrantes y/o Demencia (Digite CEROS si no tiene). ","") | CH21: =IF($D21<AO21,1,0) -> 1 | CI21: =IF($D21<AP21,1,0) -> 1 | CJ21: =IF($D21<AQ21,1,0) -> 1 | CK21: =IF($D21<AR21,1,0) -> 1 | CL21: =IF($D21<AS21,1,0) -> 1 | CM21: =IF(AND(D21<>0,OR(AO21="",AP21="",AQ21="",AR21="",AS21="")),1,0) -> 0
A22: 06905912 | C22: TÉCNICO REHABILITACIÓN ALCOHOL Y DROGAS | D22: COL01 | E22: COL02 | F22: COL03 | G22: COL04 | H22: COL05 | I22: COL06 | J22: COL07 | K22: COL08 | L22: COL09 | M22: COL10 | N22: COL11 | O22: COL12 | P22: COL13 | Q22: COL14 | R22: COL15 | S22: COL16 | T22: COL17 | U22: COL18 | V22: COL19 | W22: COL20 | X22: COL21 | Y22: COL22 | Z22: COL23 | AA22: COL24 | AB22: COL25 | AC22: COL26 | AD22: COL27 | AE22: COL28 | AF22: COL29 | AG22: COL30 | AH22: COL31 | AI22: COL32 | AJ22: COL33 | AK22: COL34 | AL22: COL35 | AM22: COL36 | AN22: COL37 | AO22: COL38 | AP22: COL39 | AQ22: COL40 | AR22: COL41 | AS22: COL42 | AT22: =CONCATENATE(CB22,CC22,CD22,CE22,CF22,CG22) -> * El número de Beneficiarios NO DEBE ser mayor que el Total. * Los Niños, Niñas, Adolescentes y Jóvenes de Programa SENAME NO DEBE ser mayor que el Total. * El total de personas pertenecientes a Pueblos Originarios NO DEBE ser mayor que el Total. * El número de personas Migrantes NO DEBE ser mayor que el Total. * El número de personas con Demencia NO DEBE ser mayor que el Total. | CB22: =IF(CH22=1,"* El número de Beneficiarios NO DEBE ser mayor que el Total. ","") -> * El número de Beneficiarios NO DEBE ser mayor que el Total. | CC22: =IF(CI22=1,"* Los Niños, Niñas, Adolescentes y Jóvenes de Programa SENAME NO DEBE ser mayor que el Total. ","") -> * Los Niños, Niñas, Adolescentes y Jóvenes de Programa SENAME NO DEBE ser mayor que el Total. | CD22: =IF(CJ22=1,"* El total de personas pertenecientes a Pueblos Originarios NO DEBE ser mayor que el Total. ","") -> * El total de personas pertenecientes a Pueblos Originarios NO DEBE ser mayor que el Total. | CE22: =IF(CK22=1,"* El número de personas Migrantes NO DEBE ser mayor que el Total. ","") -> * El número de personas Migrantes NO DEBE ser mayor que el Total. | CF22: =IF(CL22=1,"* El número de personas con Demencia NO DEBE ser mayor que el Total. ","") -> * El número de personas con Demencia NO DEBE ser mayor que el Total. | CG22: =IF(CM22=1,"* No olvide digitar la columna Beneficiarios y/o Niños, Niñas, Adolescentes y Jóvenes de Programa SENAME y/o Pueblos Originarios y/o Migrantes y/o Demencia (Digite CEROS si no tiene). ","") | CH22: =IF($D22<AO22,1,0) -> 1 | CI22: =IF($D22<AP22,1,0) -> 1 | CJ22: =IF($D22<AQ22,1,0) -> 1 | CK22: =IF($D22<AR22,1,0) -> 1 | CL22: =IF($D22<AS22,1,0) -> 1 | CM22: =IF(AND(D22<>0,OR(AO22="",AP22="",AQ22="",AR22="",AS22="")),1,0) -> 0
C23: TOTAL | D23: =SUM(E23+F23) -> 0 | E23: =SUM(G23+I23+K23+M23+O23+Q23+S23+U23+W23+Y23+AA23+AC23+AE23+AG23+AI23+AK23+AM23) -> 0 | F23: =SUM(H23+J23+L23+N23+P23+R23+T23+V23+X23+Z23+AB23+AD23+AF23+AH23+AJ23+AL23+AN23) -> 0 | G23: =SUM(G13:G22) -> 0 | H23: =SUM(H13:H22) -> 0 | I23: =SUM(I13:I22) -> 0 | J23: =SUM(J13:J22) -> 0 | K23: =SUM(K13:K22) -> 0 | L23: =SUM(L13:L22) -> 0 | M23: =SUM(M13:M22) -> 0 | N23: =SUM(N13:N22) -> 0 | ... AS23: =SUM(AS13:AS22) -> 0 | CD23: =IF(CJ23=1,"* El total de personas pertenecientes a Pueblos Originarios NO DEBE ser mayor que el Total. ","") | CE23: =IF(CK23=1,"* El número de personas Migrantes NO DEBE ser mayor que el Total. ","") | CF23: =IF(CL23=1,"* El número de personas con Demencia NO DEBE ser mayor que el Total. ","") | CG23: =IF(CM23=1,"* No olvide digitar la columna Beneficiarios y/o Niños, Niñas, Adolescentes y Jóvenes de Programa SENAME y/o Pueblos Originarios y/o Migrantes y/o Demencia (Digite CEROS si no tiene). ","") | CH23: =IF($D23<AO23,1,0) -> 0 | CI23: =IF($D23<AP23,1,0) -> 0 | CJ23: =IF($D23<AQ23,1,0) -> 0 | CK23: =IF($D23<AR23,1,0) -> 0 | CL23: =IF($D23<AS23,1,0) -> 0 | CM23: =IF(AND(D23<>0,OR(AO23="",AP23="",AQ23="",AR23="",AS23="")),1,0) -> 0
A24: 06902700 | B24: INTERVENCIÓN PSICOSOCIAL GRUPAL | D24: COL01 | E24: COL02 | F24: COL03 | G24: COL04 | H24: COL05 | I24: COL06 | J24: COL07 | K24: COL08 | L24: COL09 | M24: COL10 | N24: COL11 | O24: COL12 | P24: COL13 | Q24: COL14 | R24: COL15 | S24: COL16 | T24: COL17 | U24: COL18 | V24: COL19 | W24: COL20 | X24: COL21 | Y24: COL22 | Z24: COL23 | AA24: COL24 | AB24: COL25 | AC24: COL26 | AD24: COL27 | AE24: COL28 | AF24: COL29 | AG24: COL30 | AH24: COL31 | AI24: COL32 | AJ24: COL33 | AK24: COL34 | AL24: COL35 | AM24: COL36 | AN24: COL37 | AO24: COL38 | AP24: COL39 | AQ24: COL40 | AR24: COL41 | AS24: COL42 | AT24: =CONCATENATE(CB24,CC24,CD24,CE24,CF24,CG24) -> * El número de Beneficiarios NO DEBE ser mayor que el Total. * Los Niños, Niñas, Adolescentes y Jóvenes de Programa SENAME NO DEBE ser mayor que el Total. * El total de personas pertenecientes a Pueblos Originarios NO DEBE ser mayor que el Total. * El número de personas Migrantes NO DEBE ser mayor que el Total. * El número de personas con Demencia NO DEBE ser mayor que el Total. | CB24: =IF(CH24=1,"* El número de Beneficiarios NO DEBE ser mayor que el Total. ","") -> * El número de Beneficiarios NO DEBE ser mayor que el Total. | CC24: =IF(CI24=1,"* Los Niños, Niñas, Adolescentes y Jóvenes de Programa SENAME NO DEBE ser mayor que el Total. ","") -> * Los Niños, Niñas, Adolescentes y Jóvenes de Programa SENAME NO DEBE ser mayor que el Total. | CD24: =IF(CJ24=1,"* El total de personas pertenecientes a Pueblos Originarios NO DEBE ser mayor que el Total. ","") -> * El total de personas pertenecientes a Pueblos Originarios NO DEBE ser mayor que el Total. | CE24: =IF(CK24=1,"* El número de personas Migrantes NO DEBE ser mayor que el Total. ","") -> * El número de personas Migrantes NO DEBE ser mayor que el Total. | CF24: =IF(CL24=1,"* El número de personas con Demencia NO DEBE ser mayor que el Total. ","") -> * El número de personas con Demencia NO DEBE ser mayor que el Total. | CG24: =IF(CM24=1,"* No olvide digitar la columna Beneficiarios y/o Niños, Niñas, Adolescentes y Jóvenes de Programa SENAME y/o Pueblos Originarios y/o Migrantes y/o Demencia (Digite CEROS si no tiene). ","") | CH24: =IF($D24<AO24,1,0) -> 1 | CI24: =IF($D24<AP24,1,0) -> 1 | CJ24: =IF($D24<AQ24,1,0) -> 1 | CK24: =IF($D24<AR24,1,0) -> 1 | CL24: =IF($D24<AS24,1,0) -> 1 | CM24: =IF(AND(D24<>0,OR(AO24="",AP24="",AQ24="",AR24="",AS24="")),1,0) -> 0
A25: 06200600 | B25: PSICODIAGNOSTICO | C25: PSICÓLOGO/A | D25: COL01 | E25: COL02 | F25: COL03 | G25: COL04 | H25: COL05 | I25: COL06 | J25: COL07 | K25: COL08 | L25: COL09 | M25: COL10 | N25: COL11 | O25: COL12 | P25: COL13 | Q25: COL14 | R25: COL15 | S25: COL16 | T25: COL17 | U25: COL18 | V25: COL19 | W25: COL20 | X25: COL21 | Y25: COL22 | Z25: COL23 | AA25: COL24 | AB25: COL25 | AC25: COL26 | AD25: COL27 | AE25: COL28 | AF25: COL29 | AG25: COL30 | AH25: COL31 | AI25: COL32 | AJ25: COL33 | AK25: COL34 | AL25: COL35 | AM25: COL36 | AN25: COL37 | AO25: COL38 | AP25: COL39 | AQ25: COL40 | AR25: COL41 | AS25: COL42 | AT25: =CONCATENATE(CB25,CC25,CD25,CE25,CF25,CG25) -> * El número de Beneficiarios NO DEBE ser mayor que el Total. * Los Niños, Niñas, Adolescentes y Jóvenes de Programa SENAME NO DEBE ser mayor que el Total. * El total de personas pertenecientes a Pueblos Originarios NO DEBE ser mayor que el Total. * El número de personas Migrantes NO DEBE ser mayor que el Total. * El número de personas con Demencia NO DEBE ser mayor que el Total. | CB25: =IF(CH25=1,"* El número de Beneficiarios NO DEBE ser mayor que el Total. ","") -> * El número de Beneficiarios NO DEBE ser mayor que el Total. | CC25: =IF(CI25=1,"* Los Niños, Niñas, Adolescentes y Jóvenes de Programa SENAME NO DEBE ser mayor que el Total. ","") -> * Los Niños, Niñas, Adolescentes y Jóvenes de Programa SENAME NO DEBE ser mayor que el Total. | CD25: =IF(CJ25=1,"* El total de personas pertenecientes a Pueblos Originarios NO DEBE ser mayor que el Total. ","") -> * El total de personas pertenecientes a Pueblos Originarios NO DEBE ser mayor que el Total. | CE25: =IF(CK25=1,"* El número de personas Migrantes NO DEBE ser mayor que el Total. ","") -> * El número de personas Migrantes NO DEBE ser mayor que el Total. | CF25: =IF(CL25=1,"* El número de personas con Demencia NO DEBE ser mayor que el Total. ","") -> * El número de personas con Demencia NO DEBE ser mayor que el Total. | CG25: =IF(CM25=1,"* No olvide digitar la columna Beneficiarios y/o Niños, Niñas, Adolescentes y Jóvenes de Programa SENAME y/o Pueblos Originarios y/o Migrantes y/o Demencia (Digite CEROS si no tiene). ","") | CH25: =IF($D25<AO25,1,0) -> 1 | CI25: =IF($D25<AP25,1,0) -> 1 | CJ25: =IF($D25<AQ25,1,0) -> 1 | CK25: =IF($D25<AR25,1,0) -> 1 | CL25: =IF($D25<AS25,1,0) -> 1 | CM25: =IF(AND(D25<>0,OR(AO25="",AP25="",AQ25="",AR25="",AS25="")),1,0) -> 0
A26: 06905910 | B26: PSICOTERAPIA INDIVIDUAL | C26: PSICÓLOGO/A | D26: COL01 | E26: COL02 | F26: COL03 | G26: COL04 | H26: COL05 | I26: COL06 | J26: COL07 | K26: COL08 | L26: COL09 | M26: COL10 | N26: COL11 | O26: COL12 | P26: COL13 | Q26: COL14 | R26: COL15 | S26: COL16 | T26: COL17 | U26: COL18 | V26: COL19 | W26: COL20 | X26: COL21 | Y26: COL22 | Z26: COL23 | AA26: COL24 | AB26: COL25 | AC26: COL26 | AD26: COL27 | AE26: COL28 | AF26: COL29 | AG26: COL30 | AH26: COL31 | AI26: COL32 | AJ26: COL33 | AK26: COL34 | AL26: COL35 | AM26: COL36 | AN26: COL37 | AO26: COL38 | AP26: COL39 | AQ26: COL40 | AR26: COL41 | AS26: COL42 | AT26: =CONCATENATE(CB26,CC26,CD26,CE26,CF26,CG26) -> * El número de Beneficiarios NO DEBE ser mayor que el Total. * Los Niños, Niñas, Adolescentes y Jóvenes de Programa SENAME NO DEBE ser mayor que el Total. * El total de personas pertenecientes a Pueblos Originarios NO DEBE ser mayor que el Total. * El número de personas Migrantes NO DEBE ser mayor que el Total. * El número de personas con Demencia NO DEBE ser mayor que el Total. | CB26: =IF(CH26=1,"* El número de Beneficiarios NO DEBE ser mayor que el Total. ","") -> * El número de Beneficiarios NO DEBE ser mayor que el Total. | CC26: =IF(CI26=1,"* Los Niños, Niñas, Adolescentes y Jóvenes de Programa SENAME NO DEBE ser mayor que el Total. ","") -> * Los Niños, Niñas, Adolescentes y Jóvenes de Programa SENAME NO DEBE ser mayor que el Total. | CD26: =IF(CJ26=1,"* El total de personas pertenecientes a Pueblos Originarios NO DEBE ser mayor que el Total. ","") -> * El total de personas pertenecientes a Pueblos Originarios NO DEBE ser mayor que el Total. | CE26: =IF(CK26=1,"* El número de personas Migrantes NO DEBE ser mayor que el Total. ","") -> * El número de personas Migrantes NO DEBE ser mayor que el Total. | CF26: =IF(CL26=1,"* El número de personas con Demencia NO DEBE ser mayor que el Total. ","") -> * El número de personas con Demencia NO DEBE ser mayor que el Total. | CG26: =IF(CM26=1,"* No olvide digitar la columna Beneficiarios y/o Niños, Niñas, Adolescentes y Jóvenes de Programa SENAME y/o Pueblos Originarios y/o Migrantes y/o Demencia (Digite CEROS si no tiene). ","") | CH26: =IF($D26<AO26,1,0) -> 1 | CI26: =IF($D26<AP26,1,0) -> 1 | CJ26: =IF($D26<AQ26,1,0) -> 1 | CK26: =IF($D26<AR26,1,0) -> 1 | CL26: =IF($D26<AS26,1,0) -> 1 | CM26: =IF(AND(D26<>0,OR(AO26="",AP26="",AQ26="",AR26="",AS26="")),1,0) -> 0
A27: 06300900 | C27: MÉDICO PSIQUIATRA | D27: COL01 | E27: COL02 | F27: COL03 | G27: COL04 | H27: COL05 | I27: COL06 | J27: COL07 | K27: COL08 | L27: COL09 | M27: COL10 | N27: COL11 | O27: COL12 | P27: COL13 | Q27: COL14 | R27: COL15 | S27: COL16 | T27: COL17 | U27: COL18 | V27: COL19 | W27: COL20 | X27: COL21 | Y27: COL22 | Z27: COL23 | AA27: COL24 | AB27: COL25 | AC27: COL26 | AD27: COL27 | AE27: COL28 | AF27: COL29 | AG27: COL30 | AH27: COL31 | AI27: COL32 | AJ27: COL33 | AK27: COL34 | AL27: COL35 | AM27: COL36 | AN27: COL37 | AO27: COL38 | AP27: COL39 | AQ27: COL40 | AR27: COL41 | AS27: COL42 | AT27: =CONCATENATE(CB27,CC27,CD27,CE27,CF27,CG27) -> * El número de Beneficiarios NO DEBE ser mayor que el Total. * Los Niños, Niñas, Adolescentes y Jóvenes de Programa SENAME NO DEBE ser mayor que el Total. * El total de personas pertenecientes a Pueblos Originarios NO DEBE ser mayor que el Total. * El número de personas Migrantes NO DEBE ser mayor que el Total. * El número de personas con Demencia NO DEBE ser mayor que el Total. | CB27: =IF(CH27=1,"* El número de Beneficiarios NO DEBE ser mayor que el Total. ","") -> * El número de Beneficiarios NO DEBE ser mayor que el Total. | CC27: =IF(CI27=1,"* Los Niños, Niñas, Adolescentes y Jóvenes de Programa SENAME NO DEBE ser mayor que el Total. ","") -> * Los Niños, Niñas, Adolescentes y Jóvenes de Programa SENAME NO DEBE ser mayor que el Total. | CD27: =IF(CJ27=1,"* El total de personas pertenecientes a Pueblos Originarios NO DEBE ser mayor que el Total. ","") -> * El total de personas pertenecientes a Pueblos Originarios NO DEBE ser mayor que el Total. | CE27: =IF(CK27=1,"* El número de personas Migrantes NO DEBE ser mayor que el Total. ","") -> * El número de personas Migrantes NO DEBE ser mayor que el Total. | CF27: =IF(CL27=1,"* El número de personas con Demencia NO DEBE ser mayor que el Total. ","") -> * El número de personas con Demencia NO DEBE ser mayor que el Total. | CG27: =IF(CM27=1,"* No olvide digitar la columna Beneficiarios y/o Niños, Niñas, Adolescentes y Jóvenes de Programa SENAME y/o Pueblos Originarios y/o Migrantes y/o Demencia (Digite CEROS si no tiene). ","") | CH27: =IF($D27<AO27,1,0) -> 1 | CI27: =IF($D27<AP27,1,0) -> 1 | CJ27: =IF($D27<AQ27,1,0) -> 1 | CK27: =IF($D27<AR27,1,0) -> 1 | CL27: =IF($D27<AS27,1,0) -> 1 | CM27: =IF(AND(D27<>0,OR(AO27="",AP27="",AQ27="",AR27="",AS27="")),1,0) -> 0
B28: SECCIÓN A.2: CONSULTORÍAS DE SALUD MENTAL EN APS
B29: ACTIVIDAD | C29: TOTAL CONSULTORÍAS RECIBIDAS | D29: CONSULTORÍAS RECIBIDAS | F29: TOTAL Nº DE CASOS REVISADOS | I29: 0 - 4 | K29: 5 - 9 | M29: 10 - 14 | O29: 15 - 19 | Q29: 20 - 24 | S29: 25 - 29 | U29: 30 - 34 | W29: 35 - 39 | Y29: 40 - 44 | AA29: 45 - 49 | AC29: 50 - 54 | AE29: 55 - 59 | AG29: 60 - 64 | AI29: 65 - 69 | AK29: 70 - 74 | AM29: 75 - 79 | AO29: 80 y mas
D30: CONSULTORÍAS DE SALUD MENTAL INFANTO ADOLESCENTE | E30: CONSULTORÍAS DE SALUD MENTAL ADULTO | F30: Ambos Sexos | G30: Hombres | H30: Mujeres | I30: Hombres | J30: Mujeres | K30: Hombres | L30: Mujeres | M30: Hombres | N30: Mujeres | O30: Hombres | P30: Mujeres | Q30: Hombres | R30: Mujeres | S30: Hombres | T30: Mujeres | U30: Hombres | V30: Mujeres | W30: Hombres | X30: Mujeres | Y30: Hombres | Z30: Mujeres | AA30: Hombres | AB30: Mujeres | AC30: Hombres | AD30: Mujeres | AE30: Hombres | AF30: Mujeres | AG30: Hombres | AH30: Mujeres | AI30: Hombres | AJ30: Mujeres | AK30: Hombres | AL30: Mujeres | AM30: Hombres | AN30: Mujeres | AO30: Hombres | AP30: Mujeres
A31: 06300100 | B31: CONSULTORÍAS DE SALUD MENTAL | C31: COL01 | D31: COL02 | E31: COL03 | F31: COL04 | G31: COL05 | H31: COL06 | I31: COL07 | J31: COL08 | K31: COL09 | L31: COL10 | M31: COL11 | N31: COL12 | O31: COL13 | P31: COL14 | Q31: COL15 | R31: COL16 | S31: COL17 | T31: COL18 | U31: COL19 | V31: COL20 | W31: COL21 | X31: COL22 | Y31: COL23 | Z31: COL24 | AA31: COL25 | AB31: COL26 | AC31: COL27 | AD31: COL28 | AE31: COL29 | AF31: COL30 | AG31: COL31 | AH31: COL32 | AI31: COL33 | AJ31: COL34 | AK31: COL35 | AL31: COL36 | AM31: COL37 | AN31: COL38 | AO31: COL39 | AP31: COL40
B32: SECCIÓN A.3: CONSULTORÍAS DE SALUD MENTAL OTORGADA POR EL NIVEL DE ESPECIALIDAD
B33: ACTIVIDAD | C33: TOTAL CONSULTORÍAS OTORGADAS | D33: TOTAL Nº DE CASOS REVISADOS | G33: PARTICIPANTES
D34: Ambos Sexos | E34: Hombres | F34: Mujeres | G34: Médico Psiquiatría más un profesional | H34: Médico Psiquiatría más dos Profesionales | I34: Uniprofesional | J34: Dos profesionales | K34: tres o más profesionales
A35: 06907001 | B35: CONSULTORÍAS DE SALUD MENTAL | C35: COL01 | D35: COL02 | E35: COL03 | F35: COL04 | G35: COL05 | H35: COL06 | I35: COL07 | J35: COL08 | K35: COL09
B36: SECCIÓN B.1: ACTIVIDADES GRUPALES (NÚMERO DE SESIONES)
B37: ACTIVIDAD | C37: PROFESIONAL | D37: TOTAL
A39: 06400200 | B39: PSICOTERAPIA GRUPAL | C39: MÉDICO PSIQUIATRA | D39: COL01
A40: 06400300 | C40: PSICÓLOGO | D40: COL01
A41: 06400400 | B41: PSICOTERAPIA FAMILIAR | C41: MÉDICO PSIQUIATRA | D41: COL01
A42: 06400500 | C42: PSICÓLOGO | D42: COL01
B43: SECCIÓN B.2: PROGRAMA DE REHABILITACIÓN (PERSONAS CON TRASTORNOS PSIQUIÁTRICOS)
B44: TIPO | D44: TOTAL | G44: GRUPOS DE EDAD (en años) | AO44: Beneficiarios
G45: 0 - 4 | I45: 5 - 9 | K45: 10 - 14 | M45: 15 - 19 | O45: 20 - 24 | Q45: 25 - 29 | S45: 30 - 34 | U45: 35 - 39 | W45: 40 - 44 | Y45: 45 - 49 | AA45: 50 - 54 | AC45: 55 - 59 | AE45: 60 - 64 | AG45: 65 - 69 | AI45: 70 - 74 | AK45: 75 - 79 | AM45: 80 y mas
D46: Ambos Sexos | E46: Hombres | F46: Mujeres | G46: Hombres | H46: Mujeres | I46: Hombres | J46: Mujeres | K46: Hombres | L46: Mujeres | M46: Hombres | N46: Mujeres | O46: Hombres | P46: Mujeres | Q46: Hombres | R46: Mujeres | S46: Hombres | T46: Mujeres | U46: Hombres | V46: Mujeres | W46: Hombres | X46: Mujeres | Y46: Hombres | Z46: Mujeres | AA46: Hombres | AB46: Mujeres | AC46: Hombres | AD46: Mujeres | AE46: Hombres | AF46: Mujeres | AG46: Hombres | AH46: Mujeres | AI46: Hombres | AJ46: Mujeres | AK46: Hombres | AL46: Mujeres | AM46: Hombres | AN46: Mujeres
A47: 06500700 | B47: PROGRAMA DE REHABILITACIÓN TIPO I | C47: DÍAS PERSONA | D47: COL01 | E47: COL02 | F47: COL03 | G47: COL04 | H47: COL05 | I47: COL06 | J47: COL07 | K47: COL08 | L47: COL09 | M47: COL10 | N47: COL11 | O47: COL12 | P47: COL13 | Q47: COL14 | R47: COL15 | S47: COL16 | T47: COL17 | U47: COL18 | V47: COL19 | W47: COL20 | X47: COL21 | Y47: COL22 | Z47: COL23 | AA47: COL24 | AB47: COL25 | AC47: COL26 | AD47: COL27 | AE47: COL28 | AF47: COL29 | AG47: COL30 | AH47: COL31 | AI47: COL32 | AJ47: COL33 | AK47: COL34 | AL47: COL35 | AM47: COL36 | AN47: COL37 | AO47: COL38 | AP47: =CB47&CC47 -> * El número de Beneficiarios NO DEBE ser mayor que el total. | CB47: =IF(CH47=1,"* El número de Beneficiarios NO DEBE ser mayor que el total. ","") -> * El número de Beneficiarios NO DEBE ser mayor que el total. | CC47: =IF(CI47=1,"* No olvide digitar la columna Beneficiarios. ","") | CH47: =IF(D47<AO47,1,0) -> 1 | CI47: =IF(AND(D47<>0,AO47=""),1,0) -> 0
A48: 06500900 | B48: PROGRAMA DE REHABILITACIÓN TIPO II | C48: DÍAS PERSONA | D48: COL01 | E48: COL02 | F48: COL03 | G48: COL04 | H48: COL05 | I48: COL06 | J48: COL07 | K48: COL08 | L48: COL09 | M48: COL10 | N48: COL11 | O48: COL12 | P48: COL13 | Q48: COL14 | R48: COL15 | S48: COL16 | T48: COL17 | U48: COL18 | V48: COL19 | W48: COL20 | X48: COL21 | Y48: COL22 | Z48: COL23 | AA48: COL24 | AB48: COL25 | AC48: COL26 | AD48: COL27 | AE48: COL28 | AF48: COL29 | AG48: COL30 | AH48: COL31 | AI48: COL32 | AJ48: COL33 | AK48: COL34 | AL48: COL35 | AM48: COL36 | AN48: COL37 | AO48: COL38 | AP48: =CB48&CC48 -> * El número de Beneficiarios NO DEBE ser mayor que el total. | CB48: =IF(CH48=1,"* El número de Beneficiarios NO DEBE ser mayor que el total. ","") -> * El número de Beneficiarios NO DEBE ser mayor que el total. | CC48: =IF(CI48=1,"* No olvide digitar la columna Beneficiarios. ","") | CH48: =IF(D48<AO48,1,0) -> 1 | CI48: =IF(AND(D48<>0,AO48=""),1,0) -> 0
B49: SECCIÓN B.3: ACTIVIDADES DE PSIQUIATRÍA FORENSE PARA PERSONAS EN CONFLICTO CON LA JUSTICIA (En lo Penal, Civil, Familiar, etc.)
B50: ACTIVIDAD | D50: TOTAL | G50: GRUPOS DE EDAD (en años) | AO50: Beneficiarios
G51: 0 - 4 | I51: 5 - 9 | K51: 10 - 14 | M51: 15 - 19 | O51: 20 - 24 | Q51: 25 - 29 | S51: 30 - 34 | U51: 35 - 39 | W51: 40 - 44 | Y51: 45 - 49 | AA51: 50 - 54 | AC51: 55 - 59 | AE51: 60 - 64 | AG51: 65 - 69 | AI51: 70 - 74 | AK51: 75 - 79 | AM51: 80 y mas
D52: Ambos Sexos | E52: Hombres | F52: Mujeres | G52: Hombres | H52: Mujeres | I52: Hombres | J52: Mujeres | K52: Hombres | L52: Mujeres | M52: Hombres | N52: Mujeres | O52: Hombres | P52: Mujeres | Q52: Hombres | R52: Mujeres | S52: Hombres | T52: Mujeres | U52: Hombres | V52: Mujeres | W52: Hombres | X52: Mujeres | Y52: Hombres | Z52: Mujeres | AA52: Hombres | AB52: Mujeres | AC52: Hombres | AD52: Mujeres | AE52: Hombres | AF52: Mujeres | AG52: Hombres | AH52: Mujeres | AI52: Hombres | AJ52: Mujeres | AK52: Hombres | AL52: Mujeres | AM52: Hombres | AN52: Mujeres
A53: 06600200 | B53: PERITAJE PSIQUIÁTRICO JUDICIAL | C53: MÉDICO | D53: COL01 | E53: COL02 | F53: COL03 | G53: COL04 | H53: COL05 | I53: COL06 | J53: COL07 | K53: COL08 | L53: COL09 | M53: COL10 | N53: COL11 | O53: COL12 | P53: COL13 | Q53: COL14 | R53: COL15 | S53: COL16 | T53: COL17 | U53: COL18 | V53: COL19 | W53: COL20 | X53: COL21 | Y53: COL22 | Z53: COL23 | AA53: COL24 | AB53: COL25 | AC53: COL26 | AD53: COL27 | AE53: COL28 | AF53: COL29 | AG53: COL30 | AH53: COL31 | AI53: COL32 | AJ53: COL33 | AK53: COL34 | AL53: COL35 | AM53: COL36 | AN53: COL37 | AO53: COL38 | AP53: =CB53&CC53 -> * El número de Beneficiarios NO DEBE ser mayor que el total. | CB53: =IF(CH53=1,"* El número de Beneficiarios NO DEBE ser mayor que el total. ","") -> * El número de Beneficiarios NO DEBE ser mayor que el total. | CC53: =IF(CI53=1,"* No olvide digitar la columna Beneficiarios. ","") | CH53: =IF(D53<AO53,1,0) -> 1 | CI53: =IF(AND(D53<>0,AO53=""),1,0) -> 0
A54: 06600300 | C54: MÉDICO PSIQUIATRA | D54: COL01 | E54: COL02 | F54: COL03 | G54: COL04 | H54: COL05 | I54: COL06 | J54: COL07 | K54: COL08 | L54: COL09 | M54: COL10 | N54: COL11 | O54: COL12 | P54: COL13 | Q54: COL14 | R54: COL15 | S54: COL16 | T54: COL17 | U54: COL18 | V54: COL19 | W54: COL20 | X54: COL21 | Y54: COL22 | Z54: COL23 | AA54: COL24 | AB54: COL25 | AC54: COL26 | AD54: COL27 | AE54: COL28 | AF54: COL29 | AG54: COL30 | AH54: COL31 | AI54: COL32 | AJ54: COL33 | AK54: COL34 | AL54: COL35 | AM54: COL36 | AN54: COL37 | AO54: COL38 | AP54: =CB54&CC54 -> * El número de Beneficiarios NO DEBE ser mayor que el total. | CB54: =IF(CH54=1,"* El número de Beneficiarios NO DEBE ser mayor que el total. ","") -> * El número de Beneficiarios NO DEBE ser mayor que el total. | CC54: =IF(CI54=1,"* No olvide digitar la columna Beneficiarios. ","") | CH54: =IF(D54<AO54,1,0) -> 1 | CI54: =IF(AND(D54<>0,AO54=""),1,0) -> 0
A55: 06600400 | C55: PSICÓLOGO/A | D55: COL01 | E55: COL02 | F55: COL03 | G55: COL04 | H55: COL05 | I55: COL06 | J55: COL07 | K55: COL08 | L55: COL09 | M55: COL10 | N55: COL11 | O55: COL12 | P55: COL13 | Q55: COL14 | R55: COL15 | S55: COL16 | T55: COL17 | U55: COL18 | V55: COL19 | W55: COL20 | X55: COL21 | Y55: COL22 | Z55: COL23 | AA55: COL24 | AB55: COL25 | AC55: COL26 | AD55: COL27 | AE55: COL28 | AF55: COL29 | AG55: COL30 | AH55: COL31 | AI55: COL32 | AJ55: COL33 | AK55: COL34 | AL55: COL35 | AM55: COL36 | AN55: COL37 | AO55: COL38 | AP55: =CB55&CC55 -> * El número de Beneficiarios NO DEBE ser mayor que el total. | CB55: =IF(CH55=1,"* El número de Beneficiarios NO DEBE ser mayor que el total. ","") -> * El número de Beneficiarios NO DEBE ser mayor que el total. | CC55: =IF(CI55=1,"* No olvide digitar la columna Beneficiarios. ","") | CH55: =IF(D55<AO55,1,0) -> 1 | CI55: =IF(AND(D55<>0,AO55=""),1,0) -> 0
A56: 06600500 | C56: ENFERMERO/A | D56: COL01 | E56: COL02 | F56: COL03 | G56: COL04 | H56: COL05 | I56: COL06 | J56: COL07 | K56: COL08 | L56: COL09 | M56: COL10 | N56: COL11 | O56: COL12 | P56: COL13 | Q56: COL14 | R56: COL15 | S56: COL16 | T56: COL17 | U56: COL18 | V56: COL19 | W56: COL20 | X56: COL21 | Y56: COL22 | Z56: COL23 | AA56: COL24 | AB56: COL25 | AC56: COL26 | AD56: COL27 | AE56: COL28 | AF56: COL29 | AG56: COL30 | AH56: COL31 | AI56: COL32 | AJ56: COL33 | AK56: COL34 | AL56: COL35 | AM56: COL36 | AN56: COL37 | AO56: COL38 | AP56: =CB56&CC56 -> * El número de Beneficiarios NO DEBE ser mayor que el total. | CB56: =IF(CH56=1,"* El número de Beneficiarios NO DEBE ser mayor que el total. ","") -> * El número de Beneficiarios NO DEBE ser mayor que el total. | CC56: =IF(CI56=1,"* No olvide digitar la columna Beneficiarios. ","") | CH56: =IF(D56<AO56,1,0) -> 1 | CI56: =IF(AND(D56<>0,AO56=""),1,0) -> 0
A57: 06600600 | C57: ASISTENTE SOCIAL | D57: COL01 | E57: COL02 | F57: COL03 | G57: COL04 | H57: COL05 | I57: COL06 | J57: COL07 | K57: COL08 | L57: COL09 | M57: COL10 | N57: COL11 | O57: COL12 | P57: COL13 | Q57: COL14 | R57: COL15 | S57: COL16 | T57: COL17 | U57: COL18 | V57: COL19 | W57: COL20 | X57: COL21 | Y57: COL22 | Z57: COL23 | AA57: COL24 | AB57: COL25 | AC57: COL26 | AD57: COL27 | AE57: COL28 | AF57: COL29 | AG57: COL30 | AH57: COL31 | AI57: COL32 | AJ57: COL33 | AK57: COL34 | AL57: COL35 | AM57: COL36 | AN57: COL37 | AO57: COL38 | AP57: =CB57&CC57 -> * El número de Beneficiarios NO DEBE ser mayor que el total. | CB57: =IF(CH57=1,"* El número de Beneficiarios NO DEBE ser mayor que el total. ","") -> * El número de Beneficiarios NO DEBE ser mayor que el total. | CC57: =IF(CI57=1,"* No olvide digitar la columna Beneficiarios. ","") | CH57: =IF(D57<AO57,1,0) -> 1 | CI57: =IF(AND(D57<>0,AO57=""),1,0) -> 0
A58: 06600700 | C58: OTROS PROFESIONALES | D58: COL01 | E58: COL02 | F58: COL03 | G58: COL04 | H58: COL05 | I58: COL06 | J58: COL07 | K58: COL08 | L58: COL09 | M58: COL10 | N58: COL11 | O58: COL12 | P58: COL13 | Q58: COL14 | R58: COL15 | S58: COL16 | T58: COL17 | U58: COL18 | V58: COL19 | W58: COL20 | X58: COL21 | Y58: COL22 | Z58: COL23 | AA58: COL24 | AB58: COL25 | AC58: COL26 | AD58: COL27 | AE58: COL28 | AF58: COL29 | AG58: COL30 | AH58: COL31 | AI58: COL32 | AJ58: COL33 | AK58: COL34 | AL58: COL35 | AM58: COL36 | AN58: COL37 | AO58: COL38 | AP58: =CB58&CC58 -> * El número de Beneficiarios NO DEBE ser mayor que el total. | CB58: =IF(CH58=1,"* El número de Beneficiarios NO DEBE ser mayor que el total. ","") -> * El número de Beneficiarios NO DEBE ser mayor que el total. | CC58: =IF(CI58=1,"* No olvide digitar la columna Beneficiarios. ","") | CH58: =IF(D58<AO58,1,0) -> 1 | CI58: =IF(AND(D58<>0,AO58=""),1,0) -> 0
A59: 06600800 | B59: EXAMEN PRELIMINAR EN DROGAS PARA ADOLESCENTES IMPUTADOS / CONDENADOS | C59: PSICÓLOGO/A | D59: COL01 | E59: COL02 | F59: COL03 | G59: COL04 | H59: COL05 | I59: COL06 | J59: COL07 | K59: COL08 | L59: COL09 | M59: COL10 | N59: COL11 | O59: COL12 | P59: COL13 | Q59: COL14 | R59: COL15 | S59: COL16 | T59: COL17 | U59: COL18 | V59: COL19 | W59: COL20 | X59: COL21 | Y59: COL22 | Z59: COL23 | AA59: COL24 | AB59: COL25 | AC59: COL26 | AD59: COL27 | AE59: COL28 | AF59: COL29 | AG59: COL30 | AH59: COL31 | AI59: COL32 | AJ59: COL33 | AK59: COL34 | AL59: COL35 | AM59: COL36 | AN59: COL37 | AO59: COL38 | AP59: =CB59&CC59 -> * El número de Beneficiarios NO DEBE ser mayor que el total. | CB59: =IF(CH59=1,"* El número de Beneficiarios NO DEBE ser mayor que el total. ","") -> * El número de Beneficiarios NO DEBE ser mayor que el total. | CC59: =IF(CI59=1,"* No olvide digitar la columna Beneficiarios. ","") | CH59: =IF(D59<AO59,1,0) -> 1 | CI59: =IF(AND(D59<>0,AO59=""),1,0) -> 0
A60: 06600900 | C60: ASISTENTE SOCIAL | D60: COL01 | E60: COL02 | F60: COL03 | G60: COL04 | H60: COL05 | I60: COL06 | J60: COL07 | K60: COL08 | L60: COL09 | M60: COL10 | N60: COL11 | O60: COL12 | P60: COL13 | Q60: COL14 | R60: COL15 | S60: COL16 | T60: COL17 | U60: COL18 | V60: COL19 | W60: COL20 | X60: COL21 | Y60: COL22 | Z60: COL23 | AA60: COL24 | AB60: COL25 | AC60: COL26 | AD60: COL27 | AE60: COL28 | AF60: COL29 | AG60: COL30 | AH60: COL31 | AI60: COL32 | AJ60: COL33 | AK60: COL34 | AL60: COL35 | AM60: COL36 | AN60: COL37 | AO60: COL38 | AP60: =CB60&CC60 -> * El número de Beneficiarios NO DEBE ser mayor que el total. | CB60: =IF(CH60=1,"* El número de Beneficiarios NO DEBE ser mayor que el total. ","") -> * El número de Beneficiarios NO DEBE ser mayor que el total. | CC60: =IF(CI60=1,"* No olvide digitar la columna Beneficiarios. ","") | CH60: =IF(D60<AO60,1,0) -> 1 | CI60: =IF(AND(D60<>0,AO60=""),1,0) -> 0
A61: 06700100 | B61: EVALUACIÓN CLÍNICA PARA ADOLESCENTES IMPUTADOS CON CONSUMO DE DROGAS | C61: MÉDICO | D61: COL01 | E61: COL02 | F61: COL03 | G61: COL04 | H61: COL05 | I61: COL06 | J61: COL07 | K61: COL08 | L61: COL09 | M61: COL10 | N61: COL11 | O61: COL12 | P61: COL13 | Q61: COL14 | R61: COL15 | S61: COL16 | T61: COL17 | U61: COL18 | V61: COL19 | W61: COL20 | X61: COL21 | Y61: COL22 | Z61: COL23 | AA61: COL24 | AB61: COL25 | AC61: COL26 | AD61: COL27 | AE61: COL28 | AF61: COL29 | AG61: COL30 | AH61: COL31 | AI61: COL32 | AJ61: COL33 | AK61: COL34 | AL61: COL35 | AM61: COL36 | AN61: COL37 | AO61: COL38 | AP61: =CB61&CC61 -> * El número de Beneficiarios NO DEBE ser mayor que el total. | CB61: =IF(CH61=1,"* El número de Beneficiarios NO DEBE ser mayor que el total. ","") -> * El número de Beneficiarios NO DEBE ser mayor que el total. | CC61: =IF(CI61=1,"* No olvide digitar la columna Beneficiarios. ","") | CH61: =IF(D61<AO61,1,0) -> 1 | CI61: =IF(AND(D61<>0,AO61=""),1,0) -> 0
A62: 06700200 | C62: MÉDICO PSIQUIATRA | D62: COL01 | E62: COL02 | F62: COL03 | G62: COL04 | H62: COL05 | I62: COL06 | J62: COL07 | K62: COL08 | L62: COL09 | M62: COL10 | N62: COL11 | O62: COL12 | P62: COL13 | Q62: COL14 | R62: COL15 | S62: COL16 | T62: COL17 | U62: COL18 | V62: COL19 | W62: COL20 | X62: COL21 | Y62: COL22 | Z62: COL23 | AA62: COL24 | AB62: COL25 | AC62: COL26 | AD62: COL27 | AE62: COL28 | AF62: COL29 | AG62: COL30 | AH62: COL31 | AI62: COL32 | AJ62: COL33 | AK62: COL34 | AL62: COL35 | AM62: COL36 | AN62: COL37 | AO62: COL38 | AP62: =CB62&CC62 -> * El número de Beneficiarios NO DEBE ser mayor que el total. | CB62: =IF(CH62=1,"* El número de Beneficiarios NO DEBE ser mayor que el total. ","") -> * El número de Beneficiarios NO DEBE ser mayor que el total. | CC62: =IF(CI62=1,"* No olvide digitar la columna Beneficiarios. ","") | CH62: =IF(D62<AO62,1,0) -> 1 | CI62: =IF(AND(D62<>0,AO62=""),1,0) -> 0
A63: 06700300 | C63: PSICÓLOGO/A | D63: COL01 | E63: COL02 | F63: COL03 | G63: COL04 | H63: COL05 | I63: COL06 | J63: COL07 | K63: COL08 | L63: COL09 | M63: COL10 | N63: COL11 | O63: COL12 | P63: COL13 | Q63: COL14 | R63: COL15 | S63: COL16 | T63: COL17 | U63: COL18 | V63: COL19 | W63: COL20 | X63: COL21 | Y63: COL22 | Z63: COL23 | AA63: COL24 | AB63: COL25 | AC63: COL26 | AD63: COL27 | AE63: COL28 | AF63: COL29 | AG63: COL30 | AH63: COL31 | AI63: COL32 | AJ63: COL33 | AK63: COL34 | AL63: COL35 | AM63: COL36 | AN63: COL37 | AO63: COL38 | AP63: =CB63&CC63 -> * El número de Beneficiarios NO DEBE ser mayor que el total. | CB63: =IF(CH63=1,"* El número de Beneficiarios NO DEBE ser mayor que el total. ","") -> * El número de Beneficiarios NO DEBE ser mayor que el total. | CC63: =IF(CI63=1,"* No olvide digitar la columna Beneficiarios. ","") | CH63: =IF(D63<AO63,1,0) -> 1 | CI63: =IF(AND(D63<>0,AO63=""),1,0) -> 0
A64: 06700400 | C64: ASISTENTE SOCIAL | D64: COL01 | E64: COL02 | F64: COL03 | G64: COL04 | H64: COL05 | I64: COL06 | J64: COL07 | K64: COL08 | L64: COL09 | M64: COL10 | N64: COL11 | O64: COL12 | P64: COL13 | Q64: COL14 | R64: COL15 | S64: COL16 | T64: COL17 | U64: COL18 | V64: COL19 | W64: COL20 | X64: COL21 | Y64: COL22 | Z64: COL23 | AA64: COL24 | AB64: COL25 | AC64: COL26 | AD64: COL27 | AE64: COL28 | AF64: COL29 | AG64: COL30 | AH64: COL31 | AI64: COL32 | AJ64: COL33 | AK64: COL34 | AL64: COL35 | AM64: COL36 | AN64: COL37 | AO64: COL38 | AP64: =CB64&CC64 -> * El número de Beneficiarios NO DEBE ser mayor que el total. | CB64: =IF(CH64=1,"* El número de Beneficiarios NO DEBE ser mayor que el total. ","") -> * El número de Beneficiarios NO DEBE ser mayor que el total. | CC64: =IF(CI64=1,"* No olvide digitar la columna Beneficiarios. ","") | CH64: =IF(D64<AO64,1,0) -> 1 | CI64: =IF(AND(D64<>0,AO64=""),1,0) -> 0
A65: 06700500 | B65: EXAMEN MENTAL PRELIMINAR A PERSONAS IMPUTADAS | C65: MÉDICO | D65: COL01 | E65: COL02 | F65: COL03 | G65: COL04 | H65: COL05 | I65: COL06 | J65: COL07 | K65: COL08 | L65: COL09 | M65: COL10 | N65: COL11 | O65: COL12 | P65: COL13 | Q65: COL14 | R65: COL15 | S65: COL16 | T65: COL17 | U65: COL18 | V65: COL19 | W65: COL20 | X65: COL21 | Y65: COL22 | Z65: COL23 | AA65: COL24 | AB65: COL25 | AC65: COL26 | AD65: COL27 | AE65: COL28 | AF65: COL29 | AG65: COL30 | AH65: COL31 | AI65: COL32 | AJ65: COL33 | AK65: COL34 | AL65: COL35 | AM65: COL36 | AN65: COL37 | AO65: COL38 | AP65: =CB65&CC65 -> * El número de Beneficiarios NO DEBE ser mayor que el total. | CB65: =IF(CH65=1,"* El número de Beneficiarios NO DEBE ser mayor que el total. ","") -> * El número de Beneficiarios NO DEBE ser mayor que el total. | CC65: =IF(CI65=1,"* No olvide digitar la columna Beneficiarios. ","") | CH65: =IF(D65<AO65,1,0) -> 1 | CI65: =IF(AND(D65<>0,AO65=""),1,0) -> 0
A66: 06700600 | C66: MÉDICO PSIQUIATRA | D66: COL01 | E66: COL02 | F66: COL03 | G66: COL04 | H66: COL05 | I66: COL06 | J66: COL07 | K66: COL08 | L66: COL09 | M66: COL10 | N66: COL11 | O66: COL12 | P66: COL13 | Q66: COL14 | R66: COL15 | S66: COL16 | T66: COL17 | U66: COL18 | V66: COL19 | W66: COL20 | X66: COL21 | Y66: COL22 | Z66: COL23 | AA66: COL24 | AB66: COL25 | AC66: COL26 | AD66: COL27 | AE66: COL28 | AF66: COL29 | AG66: COL30 | AH66: COL31 | AI66: COL32 | AJ66: COL33 | AK66: COL34 | AL66: COL35 | AM66: COL36 | AN66: COL37 | AO66: COL38 | AP66: =CB66&CC66 -> * El número de Beneficiarios NO DEBE ser mayor que el total. | CB66: =IF(CH66=1,"* El número de Beneficiarios NO DEBE ser mayor que el total. ","") -> * El número de Beneficiarios NO DEBE ser mayor que el total. | CC66: =IF(CI66=1,"* No olvide digitar la columna Beneficiarios. ","") | CH66: =IF(D66<AO66,1,0) -> 1 | CI66: =IF(AND(D66<>0,AO66=""),1,0) -> 0
A67: 06700700 | B67: PERITAJE DROGAS | C67: MÉDICO | D67: COL01 | E67: COL02 | F67: COL03 | G67: COL04 | H67: COL05 | I67: COL06 | J67: COL07 | K67: COL08 | L67: COL09 | M67: COL10 | N67: COL11 | O67: COL12 | P67: COL13 | Q67: COL14 | R67: COL15 | S67: COL16 | T67: COL17 | U67: COL18 | V67: COL19 | W67: COL20 | X67: COL21 | Y67: COL22 | Z67: COL23 | AA67: COL24 | AB67: COL25 | AC67: COL26 | AD67: COL27 | AE67: COL28 | AF67: COL29 | AG67: COL30 | AH67: COL31 | AI67: COL32 | AJ67: COL33 | AK67: COL34 | AL67: COL35 | AM67: COL36 | AN67: COL37 | AO67: COL38 | AP67: =CB67&CC67 -> * El número de Beneficiarios NO DEBE ser mayor que el total. | CB67: =IF(CH67=1,"* El número de Beneficiarios NO DEBE ser mayor que el total. ","") -> * El número de Beneficiarios NO DEBE ser mayor que el total. | CC67: =IF(CI67=1,"* No olvide digitar la columna Beneficiarios. ","") | CH67: =IF(D67<AO67,1,0) -> 1 | CI67: =IF(AND(D67<>0,AO67=""),1,0) -> 0
A68: 06700800 | C68: MÉDICO PSIQUIATRA | D68: COL01 | E68: COL02 | F68: COL03 | G68: COL04 | H68: COL05 | I68: COL06 | J68: COL07 | K68: COL08 | L68: COL09 | M68: COL10 | N68: COL11 | O68: COL12 | P68: COL13 | Q68: COL14 | R68: COL15 | S68: COL16 | T68: COL17 | U68: COL18 | V68: COL19 | W68: COL20 | X68: COL21 | Y68: COL22 | Z68: COL23 | AA68: COL24 | AB68: COL25 | AC68: COL26 | AD68: COL27 | AE68: COL28 | AF68: COL29 | AG68: COL30 | AH68: COL31 | AI68: COL32 | AJ68: COL33 | AK68: COL34 | AL68: COL35 | AM68: COL36 | AN68: COL37 | AO68: COL38 | AP68: =CB68&CC68 -> * El número de Beneficiarios NO DEBE ser mayor que el total. | CB68: =IF(CH68=1,"* El número de Beneficiarios NO DEBE ser mayor que el total. ","") -> * El número de Beneficiarios NO DEBE ser mayor que el total. | CC68: =IF(CI68=1,"* No olvide digitar la columna Beneficiarios. ","") | CH68: =IF(D68<AO68,1,0) -> 1 | CI68: =IF(AND(D68<>0,AO68=""),1,0) -> 0
A69: 06700900 | B69: ATENCIÓN A AGRESORES DERIVADOS DE TRIBUNALES (LEY DE VIOLENCIA INTRAFAMILIAR | C69: MÉDICO | D69: COL01 | E69: COL02 | F69: COL03 | G69: COL04 | H69: COL05 | I69: COL06 | J69: COL07 | K69: COL08 | L69: COL09 | M69: COL10 | N69: COL11 | O69: COL12 | P69: COL13 | Q69: COL14 | R69: COL15 | S69: COL16 | T69: COL17 | U69: COL18 | V69: COL19 | W69: COL20 | X69: COL21 | Y69: COL22 | Z69: COL23 | AA69: COL24 | AB69: COL25 | AC69: COL26 | AD69: COL27 | AE69: COL28 | AF69: COL29 | AG69: COL30 | AH69: COL31 | AI69: COL32 | AJ69: COL33 | AK69: COL34 | AL69: COL35 | AM69: COL36 | AN69: COL37 | AO69: COL38 | AP69: =CB69&CC69 -> * El número de Beneficiarios NO DEBE ser mayor que el total. | CB69: =IF(CH69=1,"* El número de Beneficiarios NO DEBE ser mayor que el total. ","") -> * El número de Beneficiarios NO DEBE ser mayor que el total. | CC69: =IF(CI69=1,"* No olvide digitar la columna Beneficiarios. ","") | CH69: =IF(D69<AO69,1,0) -> 1 | CI69: =IF(AND(D69<>0,AO69=""),1,0) -> 0
A70: 06800100 | C70: MÉDICO PSIQUIATRA | D70: COL01 | E70: COL02 | F70: COL03 | G70: COL04 | H70: COL05 | I70: COL06 | J70: COL07 | K70: COL08 | L70: COL09 | M70: COL10 | N70: COL11 | O70: COL12 | P70: COL13 | Q70: COL14 | R70: COL15 | S70: COL16 | T70: COL17 | U70: COL18 | V70: COL19 | W70: COL20 | X70: COL21 | Y70: COL22 | Z70: COL23 | AA70: COL24 | AB70: COL25 | AC70: COL26 | AD70: COL27 | AE70: COL28 | AF70: COL29 | AG70: COL30 | AH70: COL31 | AI70: COL32 | AJ70: COL33 | AK70: COL34 | AL70: COL35 | AM70: COL36 | AN70: COL37 | AO70: COL38 | AP70: =CB70&CC70 -> * El número de Beneficiarios NO DEBE ser mayor que el total. | CB70: =IF(CH70=1,"* El número de Beneficiarios NO DEBE ser mayor que el total. ","") -> * El número de Beneficiarios NO DEBE ser mayor que el total. | CC70: =IF(CI70=1,"* No olvide digitar la columna Beneficiarios. ","") | CH70: =IF(D70<AO70,1,0) -> 1 | CI70: =IF(AND(D70<>0,AO70=""),1,0) -> 0
A71: 06800200 | C71: PSICÓLOGO/A | D71: COL01 | E71: COL02 | F71: COL03 | G71: COL04 | H71: COL05 | I71: COL06 | J71: COL07 | K71: COL08 | L71: COL09 | M71: COL10 | N71: COL11 | O71: COL12 | P71: COL13 | Q71: COL14 | R71: COL15 | S71: COL16 | T71: COL17 | U71: COL18 | V71: COL19 | W71: COL20 | X71: COL21 | Y71: COL22 | Z71: COL23 | AA71: COL24 | AB71: COL25 | AC71: COL26 | AD71: COL27 | AE71: COL28 | AF71: COL29 | AG71: COL30 | AH71: COL31 | AI71: COL32 | AJ71: COL33 | AK71: COL34 | AL71: COL35 | AM71: COL36 | AN71: COL37 | AO71: COL38 | AP71: =CB71&CC71 -> * El número de Beneficiarios NO DEBE ser mayor que el total. | CB71: =IF(CH71=1,"* El número de Beneficiarios NO DEBE ser mayor que el total. ","") -> * El número de Beneficiarios NO DEBE ser mayor que el total. | CC71: =IF(CI71=1,"* No olvide digitar la columna Beneficiarios. ","") | CH71: =IF(D71<AO71,1,0) -> 1 | CI71: =IF(AND(D71<>0,AO71=""),1,0) -> 0
A72: 06800300 | C72: ENFERMERO/A | D72: COL01 | E72: COL02 | F72: COL03 | G72: COL04 | H72: COL05 | I72: COL06 | J72: COL07 | K72: COL08 | L72: COL09 | M72: COL10 | N72: COL11 | O72: COL12 | P72: COL13 | Q72: COL14 | R72: COL15 | S72: COL16 | T72: COL17 | U72: COL18 | V72: COL19 | W72: COL20 | X72: COL21 | Y72: COL22 | Z72: COL23 | AA72: COL24 | AB72: COL25 | AC72: COL26 | AD72: COL27 | AE72: COL28 | AF72: COL29 | AG72: COL30 | AH72: COL31 | AI72: COL32 | AJ72: COL33 | AK72: COL34 | AL72: COL35 | AM72: COL36 | AN72: COL37 | AO72: COL38 | AP72: =CB72&CC72 -> * El número de Beneficiarios NO DEBE ser mayor que el total. | CB72: =IF(CH72=1,"* El número de Beneficiarios NO DEBE ser mayor que el total. ","") -> * El número de Beneficiarios NO DEBE ser mayor que el total. | CC72: =IF(CI72=1,"* No olvide digitar la columna Beneficiarios. ","") | CH72: =IF(D72<AO72,1,0) -> 1 | CI72: =IF(AND(D72<>0,AO72=""),1,0) -> 0
A73: 06800400 | C73: ASISTENTE SOCIAL | D73: COL01 | E73: COL02 | F73: COL03 | G73: COL04 | H73: COL05 | I73: COL06 | J73: COL07 | K73: COL08 | L73: COL09 | M73: COL10 | N73: COL11 | O73: COL12 | P73: COL13 | Q73: COL14 | R73: COL15 | S73: COL16 | T73: COL17 | U73: COL18 | V73: COL19 | W73: COL20 | X73: COL21 | Y73: COL22 | Z73: COL23 | AA73: COL24 | AB73: COL25 | AC73: COL26 | AD73: COL27 | AE73: COL28 | AF73: COL29 | AG73: COL30 | AH73: COL31 | AI73: COL32 | AJ73: COL33 | AK73: COL34 | AL73: COL35 | AM73: COL36 | AN73: COL37 | AO73: COL38 | AP73: =CB73&CC73 -> * El número de Beneficiarios NO DEBE ser mayor que el total. | CB73: =IF(CH73=1,"* El número de Beneficiarios NO DEBE ser mayor que el total. ","") -> * El número de Beneficiarios NO DEBE ser mayor que el total. | CC73: =IF(CI73=1,"* No olvide digitar la columna Beneficiarios. ","") | CH73: =IF(D73<AO73,1,0) -> 1 | CI73: =IF(AND(D73<>0,AO73=""),1,0) -> 0
A74: 06800500 | C74: OTROS PROFESIONALES | D74: COL01 | E74: COL02 | F74: COL03 | G74: COL04 | H74: COL05 | I74: COL06 | J74: COL07 | K74: COL08 | L74: COL09 | M74: COL10 | N74: COL11 | O74: COL12 | P74: COL13 | Q74: COL14 | R74: COL15 | S74: COL16 | T74: COL17 | U74: COL18 | V74: COL19 | W74: COL20 | X74: COL21 | Y74: COL22 | Z74: COL23 | AA74: COL24 | AB74: COL25 | AC74: COL26 | AD74: COL27 | AE74: COL28 | AF74: COL29 | AG74: COL30 | AH74: COL31 | AI74: COL32 | AJ74: COL33 | AK74: COL34 | AL74: COL35 | AM74: COL36 | AN74: COL37 | AO74: COL38 | AP74: =CB74&CC74 -> * El número de Beneficiarios NO DEBE ser mayor que el total. | CB74: =IF(CH74=1,"* El número de Beneficiarios NO DEBE ser mayor que el total. ","") -> * El número de Beneficiarios NO DEBE ser mayor que el total. | CC74: =IF(CI74=1,"* No olvide digitar la columna Beneficiarios. ","") | CH74: =IF(D74<AO74,1,0) -> 1 | CI74: =IF(AND(D74<>0,AO74=""),1,0) -> 0
B75: SECCIÓN B.4: DISPOSITIVOS DE SALUD MENTAL
B76: TIPO DE DISPOSITIVO | D76: Nº DE PERSONAS ATENDIDAS | F76: DÍAS DE ESTADA DE PERSONAS ATENDIDAS EN EL MES | H76: Nº DE EGRESOS | J76: Nº DE PERSONAS EN LISTA DE ESPERA
D77: Menos de 20 años | E77: 20 y más años | F77: Menos de 20 años | G77: 20 y más años | H77: Menos de 20 años | I77: 20 y más años | J77: Menos de 20 años | K77: 20 y más años
A78: 06900300 | B78: HOGAR PROTEGIDO | D78: COL01 | E78: COL02 | F78: COL03 | G78: COL04 | H78: COL05 | I78: COL06 | J78: COL07 | K78: COL08
A79: 06900400 | B79: RESIDENCIA PROTEGIDA | D79: COL01 | E79: COL02 | F79: COL03 | G79: COL04 | H79: COL05 | I79: COL06 | J79: COL07 | K79: COL08
A80: 06900500 | B80: HOSPITAL PSIQUIÁTRICO DIURNO | D80: COL01 | E80: COL02 | F80: COL03 | G80: COL04 | H80: COL05 | I80: COL06 | J80: COL07 | K80: COL08
A81: 06900600 | B81: CENTRO PRIVATIVO DE LIBERTAD (SENAME) | D81: COL01 | E81: COL02 | F81: COL03 | G81: COL04 | H81: COL05 | I81: COL06 | J81: COL07 | K81: COL08
B82: SECCIÓN C.1: ACTIVIDADES DE COORDINACION SECTORIAL, INTERSECTORIAL Y COMUNITARIA
B83: ACTIVIDADES | C83: TOTAL DE PARTICIPANTES | D83: Nº REUNIONES / SESIONES | E83: Nº INSTITUCIONES, ORGANIZACIONES PARTICIPANTES
A85: 06905200 | B85: TRABAJO INTERSECTORIAL | C85: COL01 | D85: COL02 | E85: COL03
A86: 06905300 | B86: TRABAJO CON ORGANIZACIONES COMUNITARIAS DE BASE | C86: COL01 | D86: COL02 | E86: COL03
A87: 06905400 | B87: TRABAJO CON ORGANIZACIONES DE USUARIOS Y FAMILIARES | C87: COL01 | D87: COL02 | E87: COL03
A88: 06905911 | B88: COLABORACIÓN CON GRUPO DE AUTOAYUDA | C88: COL01 | D88: COL02 | E88: COL03
A89: 06905913 | B89: REUNIONES CON INSTITUCIONES DEL SECTOR SALUD PROGRAMA ACOMPAÑAMIENTO PSICOSOCIAL | C89: COL01 | D89: COL02 | E89: COL03
A90: 06905914 | B90: REUNIONES CON INSTITUCIONES DEL INTERSECTOR ACOMPAÑAMIENTO PSICOSOCIAL | C90: COL01 | D90: COL02 | E90: COL03
A91: 06905915 | B91: REUNIONES CON ORGANIZACIONES COMUNITARIAS ACOMPAÑAMIENTO PSICOSOCIAL | C91: COL01 | D91: COL02 | E91: COL03
B92: SECCIÓN C.2: INFORMES A TRIBUNALES
B93: TRIBUNALES | C93: Nº INFORMES | D93: ASISTENCIA A TRIBUNALES
D94: Nº de profesionales | E94: Nº de veces
A95: 06905500 | B95: DE FAMILIA | C95: COL01 | D95: COL02 | E95: COL03
A96: 06905600 | B96: PENALES | C96: COL01 | D96: COL02 | E96: COL03
A97: 06905700 | B97: CIVILES | C97: COL01 | D97: COL02 | E97: COL03
A98: 06905800 | B98: POLICIA LOCAL | C98: COL01 | D98: COL02 | E98: COL03
A99: 06905900 | B99: LABORALES | C99: COL01 | D99: COL02 | E99: COL03
B100: TOTAL | C100: =SUM(C95:C99) -> 0 | D100: =SUM(D95:D99) -> 0 | E100: =SUM(E95:E99) -> 0
B101: SECCIÓN D: PLANES Y EVALUACIONES PROGRAMA DE ACOMPAÑAMIENTO PSICOSOCIAL EN ATENCIÓN PRIMARIA
B102: ACTIVIDAD | C102: TOTAL | F102: GRUPOS DE EDAD (en años)
F103: 0 - 4 | H103: 5 - 9 | J103: 10 - 14 | L103: 15 - 19 | N103: 20 - 24
C104: Ambos Sexos | D104: Hombres | E104: Mujeres | F104: Hombres | G104: Mujeres | H104: Hombres | I104: Mujeres | J104: Hombres | K104: Mujeres | L104: Hombres | M104: Mujeres | N104: Hombres | O104: Mujeres
...

Sheet A07
B1: SERVICIO DE SALUD
B2: =CONCATENATE("COMUNA: ",NOMBRE!B2," - ","( ",NOMBRE!C2,NOMBRE!D2,NOMBRE!E2,NOMBRE!F2,NOMBRE!G2," )") -> COMUNA: - ( )
B3: =CONCATENATE("ESTABLECIMIENTO/ESTRATEGIA: ",NOMBRE!B3," - ","( ",NOMBRE!C3,NOMBRE!D3,NOMBRE!E3,NOMBRE!F3,NOMBRE!G3,NOMBRE!H3," )") -> ESTABLECIMIENTO/ESTRATEGIA: - ( )
B4: =CONCATENATE("MES: ",NOMBRE!B6," - ","( ",NOMBRE!C6,NOMBRE!D6," )") -> MES: - ( )
B5: =CONCATENATE("AÑO: ",NOMBRE!B7) -> AÑO: 2020
B6: REM-07. ATENCIÓN DE ESPECIALIDADES
B7: SECCIÓN A : CONSULTAS MÉDICAS
B8: ESPECIALIDADES Y SUB-ESPECIALIDADES | C8: CONSULTAS MÉDICAS | X8: CONSULTAS NUEVAS SEGÚN ORIGEN(*) | AF8: CONSULTAS PERTINENTES (Nuevas originadas en APS) | AH8: INASISTENTE A CONSULTA MÉDICA (NSP) | AJ8: CONSULTA ABREVIADA (Confección de recetas o lectura de exámenes) | AK8: INTERCONSULTAS A HOSPITALIZADOS (EN SALA) | AM8: ALTA DE CONSULTA DE ESPECIALIDAD AMBULATORIA | AO8: CONSULTAS REALIZADAS EN APS E INFORMADAS EN SECCIÓN A | AQ8: COMPRA DE SERVICIO | AR8: CONSULTAS MÉDICAS POR OPERATIVOS (no incluidas en produccion) | AS8: TOTAL INTERCONSULTAS GENERADAS EN APS PARA DERIVACION ESPECIALIDAD | AU8: CONSULTORÍAS DE MEDICOS ESPECIALISTAS OTORGADAS | AX8: CONSULTA MÉDICO GENERAL
A9: CODIGO DICCIONARIO | C9: TOTAL | D9: GRUPOS DE EDAD (en años) | U9: A BENEFICIARIOS | V9: POR SEXO | X9: Menos 15 años | AB9: De 15 y más años
D10: 0 - 4 | E10: 5 - 9 | F10: 10 - 14 | G10: 15 - 19 | H10: 20 - 24 | I10: 25 - 29 | J10: 30 - 34 | K10: 35 - 39 | L10: 40 - 44 | M10: 45 - 49 | N10: 50 - 54 | O10: 55 - 59 | P10: 60 - 64 | Q10: 65 - 69 | R10: 70 - 74 | S10: 75 - 79 | T10: 80 y mas | V10: Hombres | W10: Mujeres | X10: TOTAL | Y10: APS | Z10: CAE/CDT/CRS/HOSPITALIZACION | AA10: URGENCIA | AB10: TOTAL | AC10: APS | AD10: CAE/CDT/CRS/HOSPITALIZACION | AE10: URGENCIA | AF10: Según protocolo de referencia | AG10: Según tiempo establecido | AH10: NUEVAS | AI10: CONTROLES | AK10: Menos 15 años | AL10: 15 y más años | AM10: Menos 15 años | AN10: 15 y más años | AO10: CONTRATADOS POR EL ESTABLECIMIENTO O DIRECCIÓN DEL SERVICIO | AP10: ESPECIALISTAS DE HOSPITALES | AS10: Menos 15 años | AT10: 15 y más años | AU10: Nº Consultorías | AV10: Nº de casos revisados por el equipo | AW10: Nº de casos atendidos | AX10: Menos 15 años | AY10: 15 y más años
A11: 07020130 | B11: PEDIATRÍA | C11: COL01 | D11: COL02 | E11: COL03 | F11: COL04 | G11: COL05 | H11: COL06 | I11: COL07 | J11: COL08 | K11: COL09 | L11: COL10 | M11: COL11 | N11: COL12 | O11: COL13 | P11: COL14 | Q11: COL15 | R11: COL16 | S11: COL17 | T11: COL18 | U11: COL19 | V11: COL20 | W11: COL21 | X11: COL22 | Y11: COL23 | Z11: COL24 | AA11: COL25 | AB11: COL26 | AC11: COL27 | AD11: COL28 | AE11: COL29 | AF11: COL30 | AG11: COL31 | AH11: COL32 | AI11: COL33 | AJ11: COL34 | AK11: COL35 | AL11: COL36 | AM11: COL37 | AN11: COL38 | AO11: COL39 | AP11: COL40 | AQ11: COL41 | AR11: COL42 | AS11: COL43 | AT11: COL44 | AU11: COL45 | AV11: COL46 | AW11: COL47 | AX11: COL48 | AY11: COL49 | CA11: =IF(CG11=1,"* El número de consultas según sexo NO DEBE ser diferente al Total. ","") -> #REF! | CB11: =IF(CH11=1,"* No olvide digitar la columna Beneficiarios (Digite CEROS si no tiene). ","") | CC11: =IF(CI11=1,"* El número de Beneficiarios NO DEBE ser mayor que el Total. ","") -> * El número de Beneficiarios NO DEBE ser mayor que el Total. | CD11: =IF(CJ11=1,"* El total de Consultas Nuevas NO DEBE ser MAYOR que el total de las Consultas Médicas. ","") -> #VALUE! | CE11: =IF(CK11=1,"* No olvide registrar datos en Pertinencia (Digite CEROS si no tiene). ","") -> #VALUE! | CG11: =IF(C11<(#REF!+V11),1,0) -> #REF! | CH11: =IF(AND(C11<>0,U11=0),1,0) -> 0 | CI11: =IF(C11<(U11),1,0) -> 1 | CJ11: =IF(C11<(W11+AA11),1,0) -> #VALUE! | CK11: =IF(AND((X11+AB11)<>0,OR(AE11="",AF11="")),1,0) -> #VALUE!
A12: 07020230 | B12: MEDICINA INTERNA | C12: COL01 | D12: COL02 | E12: COL03 | F12: COL04 | G12: COL05 | H12: COL06 | I12: COL07 | J12: COL08 | K12: COL09 | L12: COL10 | M12: COL11 | N12: COL12 | O12: COL13 | P12: COL14 | Q12: COL15 | R12: COL16 | S12: COL17 | T12: COL18 | U12: COL19 | V12: COL20 | W12: COL21 | X12: COL22 | Y12: COL23 | Z12: COL24 | AA12: COL25 | AB12: COL26 | AC12: COL27 | AD12: COL28 | AE12: COL29 | AF12: COL30 | AG12: COL31 | AH12: COL32 | AI12: COL33 | AJ12: COL34 | AK12: COL35 | AL12: COL36 | AM12: COL37 | AN12: COL38 | AO12: COL39 | AP12: COL40 | AQ12: COL41 | AR12: COL42 | AS12: COL43 | AT12: COL44 | AU12: COL45 | AV12: COL46 | AW12: COL47 | AX12: COL48 | AY12: COL49 | CA12: =IF(CG12=1,"* El número de consultas según sexo NO DEBE ser diferente al Total. ","") -> #REF! | CB12: =IF(CH12=1,"* No olvide digitar la columna Beneficiarios (Digite CEROS si no tiene). ","") | CC12: =IF(CI12=1,"* El número de Beneficiarios NO DEBE ser mayor que el Total. ","") -> * El número de Beneficiarios NO DEBE ser mayor que el Total. | CD12: =IF(CJ12=1,"* El total de Consultas Nuevas NO DEBE ser MAYOR que el total de las Consultas Médicas. ","") -> #VALUE! | CE12: =IF(CK12=1,"* No olvide registrar datos en Pertinencia (Digite CEROS si no tiene). ","") -> #VALUE! | CG12: =IF(C12<(#REF!+V12),1,0) -> #REF! | CH12: =IF(AND(C12<>0,U12=0),1,0) -> 0 | CI12: =IF(C12<(U12),1,0) -> 1 | CJ12: =IF(C12<(W12+AA12),1,0) -> #VALUE! | CK12: =IF(AND((X12+AB12)<>0,OR(AE12="",AF12="")),1,0) -> #VALUE!
A13: 07020330 | B13: NEONATOLOGÍA | C13: COL01 | D13: COL02 | E13: COL03 | F13: COL04 | G13: COL05 | H13: COL06 | I13: COL07 | J13: COL08 | K13: COL09 | L13: COL10 | M13: COL11 | N13: COL12 | O13: COL13 | P13: COL14 | Q13: COL15 | R13: COL16 | S13: COL17 | T13: COL18 | U13: COL19 | V13: COL20 | W13: COL21 | X13: COL22 | Y13: COL23 | Z13: COL24 | AA13: COL25 | AB13: COL26 | AC13: COL27 | AD13: COL28 | AE13: COL29 | AF13: COL30 | AG13: COL31 | AH13: COL32 | AI13: COL33 | AJ13: COL34 | AK13: COL35 | AL13: COL36 | AM13: COL37 | AN13: COL38 | AO13: COL39 | AP13: COL40 | AQ13: COL41 | AR13: COL42 | AS13: COL43 | AT13: COL44 | AU13: COL45 | AV13: COL46 | AW13: COL47 | AX13: COL48 | AY13: COL49 | CA13: =IF(CG13=1,"* El número de consultas según sexo NO DEBE ser diferente al Total. ","") -> #REF! | CB13: =IF(CH13=1,"* No olvide digitar la columna Beneficiarios (Digite CEROS si no tiene). ","") | CC13: =IF(CI13=1,"* El número de Beneficiarios NO DEBE ser mayor que el Total. ","") -> * El número de Beneficiarios NO DEBE ser mayor que el Total. | CD13: =IF(CJ13=1,"* El total de Consultas Nuevas NO DEBE ser MAYOR que el total de las Consultas Médicas. ","") -> #VALUE! | CE13: =IF(CK13=1,"* No olvide registrar datos en Pertinencia (Digite CEROS si no tiene). ","") -> #VALUE! | CG13: =IF(C13<(#REF!+V13),1,0) -> #REF! | CH13: =IF(AND(C13<>0,U13=0),1,0) -> 0 | CI13: =IF(C13<(U13),1,0) -> 1 | CJ13: =IF(C13<(W13+AA13),1,0) -> #VALUE! | CK13: =IF(AND((X13+AB13)<>0,OR(AE13="",AF13="")),1,0) -> #VALUE!
A14: 07020331 | B14: ENFERMEDAD RESPIRATORIA PEDIÁTRICA (BRONCOPULMONAR INFANTIL) | C14: COL01 | D14: COL02 | E14: COL03 | F14: COL04 | G14: COL05 | H14: COL06 | I14: COL07 | J14: COL08 | K14: COL09 | L14: COL10 | M14: COL11 | N14: COL12 | O14: COL13 | P14: COL14 | Q14: COL15 | R14: COL16 | S14: COL17 | T14: COL18 | U14: COL19 | V14: COL20 | W14: COL21 | X14: COL22 | Y14: COL23 | Z14: COL24 | AA14: COL25 | AB14: COL26 | AC14: COL27 | AD14: COL28 | AE14: COL29 | AF14: COL30 | AG14: COL31 | AH14: COL32 | AI14: COL33 | AJ14: COL34 | AK14: COL35 | AL14: COL36 | AM14: COL37 | AN14: COL38 | AO14: COL39 | AP14: COL40 | AQ14: COL41 | AR14: COL42 | AS14: COL43 | AT14: COL44 | AU14: COL45 | AV14: COL46 | AW14: COL47 | AX14: COL48 | AY14: COL49 | CA14: =IF(CG14=1,"* El número de consultas según sexo NO DEBE ser diferente al Total. ","") -> #REF! | CB14: =IF(CH14=1,"* No olvide digitar la columna Beneficiarios (Digite CEROS si no tiene). ","") | CC14: =IF(CI14=1,"* El número de Beneficiarios NO DEBE ser mayor que el Total. ","") -> * El número de Beneficiarios NO DEBE ser mayor que el Total. | CD14: =IF(CJ14=1,"* El total de Consultas Nuevas NO DEBE ser MAYOR que el total de las Consultas Médicas. ","") -> #VALUE! | CE14: =IF(CK14=1,"* No olvide registrar datos en Pertinencia (Digite CEROS si no tiene). ","") -> #VALUE! | CG14: =IF(C14<(#REF!+V14),1,0) -> #REF! | CH14: =IF(AND(C14<>0,U14=0),1,0) -> 0 | CI14: =IF(C14<(U14),1,0) -> 1 | CJ14: =IF(C14<(W14+AA14),1,0) -> #VALUE! | CK14: =IF(AND((X14+AB14)<>0,OR(AE14="",AF14="")),1,0) -> #VALUE!
A15: 07020332 | B15: ENFERMEDAD RESPIRATORIA DE ADULTO (BRONCOPULMONAR) | C15: COL01 | D15: COL02 | E15: COL03 | F15: COL04 | G15: COL05 | H15: COL06 | I15: COL07 | J15: COL08 | K15: COL09 | L15: COL10 | M15: COL11 | N15: COL12 | O15: COL13 | P15: COL14 | Q15: COL15 | R15: COL16 | S15: COL17 | T15: COL18 | U15: COL19 | V15: COL20 | W15: COL21 | X15: COL22 | Y15: COL23 | Z15: COL24 | AA15: COL25 | AB15: COL26 | AC15: COL27 | AD15: COL28 | AE15: COL29 | AF15: COL30 | AG15: COL31 | AH15: COL32 | AI15: COL33 | AJ15: COL34 | AK15: COL35 | AL15: COL36 | AM15: COL37 | AN15: COL38 | AO15: COL39 | AP15: COL40 | AQ15: COL41 | AR15: COL42 | AS15: COL43 | AT15: COL44 | AU15: COL45 | AV15: COL46 | AW15: COL47 | AX15: COL48 | AY15: COL49 | CA15: =IF(CG15=1,"* El número de consultas según sexo NO DEBE ser diferente al Total. ","") -> #REF! | CB15: =IF(CH15=1,"* No olvide digitar la columna Beneficiarios (Digite CEROS si no tiene). ","") | CC15: =IF(CI15=1,"* El número de Beneficiarios NO DEBE ser mayor que el Total. ","") -> * El número de Beneficiarios NO DEBE ser mayor que el Total. | CD15: =IF(CJ15=1,"* El total de Consultas Nuevas NO DEBE ser MAYOR que el total de las Consultas Médicas. ","") -> #VALUE! | CE15: =IF(CK15=1,"* No olvide registrar datos en Pertinencia (Digite CEROS si no tiene). ","") -> #VALUE! | CG15: =IF(C15<(#REF!+V15),1,0) -> #REF! | CH15: =IF(AND(C15<>0,U15=0),1,0) -> 0 | CI15: =IF(C15<(U15),1,0) -> 1 | CJ15: =IF(C15<(W15+AA15),1,0) -> #VALUE! | CK15: =IF(AND((X15+AB15)<>0,OR(AE15="",AF15="")),1,0) -> #VALUE!
A16: 07024219 | B16: CARDIOLOGÍA PEDIÁTRICA | C16: COL01 | D16: COL02 | E16: COL03 | F16: COL04 | G16: COL05 | H16: COL06 | I16: COL07 | J16: COL08 | K16: COL09 | L16: COL10 | M16: COL11 | N16: COL12 | O16: COL13 | P16: COL14 | Q16: COL15 | R16: COL16 | S16: COL17 | T16: COL18 | U16: COL19 | V16: COL20 | W16: COL21 | X16: COL22 | Y16: COL23 | Z16: COL24 | AA16: COL25 | AB16: COL26 | AC16: COL27 | AD16: COL28 | AE16: COL29 | AF16: COL30 | AG16: COL31 | AH16: COL32 | AI16: COL33 | AJ16: COL34 | AK16: COL35 | AL16: COL36 | AM16: COL37 | AN16: COL38 | AO16: COL39 | AP16: COL40 | AQ16: COL41 | AR16: COL42 | AS16: COL43 | AT16: COL44 | AU16: COL45 | AV16: COL46 | AW16: COL47 | AX16: COL48 | AY16: COL49 | CA16: =IF(CG16=1,"* El número de consultas según sexo NO DEBE ser diferente al Total. ","") -> #REF! | CB16: =IF(CH16=1,"* No olvide digitar la columna Beneficiarios (Digite CEROS si no tiene). ","") | CC16: =IF(CI16=1,"* El número de Beneficiarios NO DEBE ser mayor que el Total. ","") -> * El número de Beneficiarios NO DEBE ser mayor que el Total. | CD16: =IF(CJ16=1,"* El total de Consultas Nuevas NO DEBE ser MAYOR que el total de las Consultas Médicas. ","") -> #VALUE! | CE16: =IF(CK16=1,"* No olvide registrar datos en Pertinencia (Digite CEROS si no tiene). ","") -> #VALUE! | CG16: =IF(C16<(#REF!+V16),1,0) -> #REF! | CH16: =IF(AND(C16<>0,U16=0),1,0) -> 0 | CI16: =IF(C16<(U16),1,0) -> 1 | CJ16: =IF(C16<(W16+AA16),1,0) -> #VALUE! | CK16: =IF(AND((X16+AB16)<>0,OR(AE16="",AF16="")),1,0) -> #VALUE!
